Workbook

Sheet Sheet1
A1: Account: Account Name | B1: Account: DBA 1 | C1: Account: DBA 2 | D1: Account: DBA 3 | E1: Account: Shipping Street 1 | F1: Account: Shipping Street 2 | G1: Account: Shipping City | H1: Account:ShippingState/Province | I1: Account: Shipping Zip/Postal Code | J1: Account: Shipping Country | K1: Account: Phone | L1: Account: Website | M1: Account:AirportCode | N1: Bus Category 1 | O1: Bus Category 2 | P1: Bus Category 3 | Q1: Bus Category 4 | R1: Bus Category 5 | S1: SyncStatus | T1: Google:SyncByPhone | U1: Google:SyncByNameAndAddress | V1: Google:SyncByWebsite | W1: Google:SyncByName | X1: Google:SyncByNearby | Y1: Google:MapsURL | Z1: Google:JSONCandidate | AA1: Google:JSONNearby | AB1: Google:CompanyName | AC1: Google:BusinessStatus | AD1: Google:PlaceID | AE1: Google:FormattedAddress | AF1: MatchStreet | AG1: MatchCity | AH1: MatchState | AI1: MatchZip | AJ1: Google:Latitude | AK1: Google:Longitude | AL1: Google:PlacesDetailsJSON | AM1: Google:AdrAddress | AN1: Google:FormattedPhone | AO1: Google:Icon | AP1: Google:ID | AQ1: Google:InternationalPhone | AR1: Google:ListingTypes | AS1: Google:UTCOffset | AT1: Google:Vicinity | AU1: Google:BusinessURL | AV1: Google:Rating | AW1: Google:NumReviews | AX1: Google:PriceLevel | AY1: Google:GlobalCode | AZ1: Google:CompoundCode | BA1: Google:OpeningHours
A2: 1 Vision Aviation | E2: 2044 Scanlan Ave | G2: Salina | H2: KS | I2: 67401 | J2: US | L2: http://1vision.aero/ | M2: SLN | N2: P145 | O2: REPO | P2: HANG | Y2: https://maps.google.com/?cid=14747138387774421522 | AB2: 1 Vision Aviation | AC2: OPERATIONAL | AD2: ChIJp2g5XB7JvIcREjrS4DpcqMw | AE2: 2044 Scanlan Ave, Salina, KS 67401, USA | AJ2: 38.807358 | AK2: -97.637337 | AL2: {"html_attributions":[],"result":{"address_components":[{"long_name":"2044","short_name":"2044","types":["street_number"]},{"long_name":"Scanlan Avenue","short_name":"Scanlan Ave","types":["route"]},{"long_name":"Salina","short_name":"Salina","types":["locality","political"]},{"long_name":"Saline County","short_name":"Saline County","types":["administrative_area_level_2","political"]},{"long_name":"Kansas","short_name":"KS","types":["administrative_area_level_1","political"]},{"long_name":"United States","short_name":"US","types":["country","political"]},{"long_name":"67401","short_name":"67401","types":["postal_code"]}],"adr_address":"<span class=\"street-address\">2044 Scanlan Ave</span>, <span class=\"locality\">Salina</span>, <span class=\"region\">KS</span> <span class=\"postal-code\">67401</span>, <span class=\"country-name\">USA</span>","formatted_address":"2044 Scanlan Ave, Salina, KS 67401, USA","formatted_phone_number":null,"geometry":{"location":{"lat":38.80735769999999,"lng":-97.63733669999999},"viewport":{"northeast":{"lat":38.80870703029149,"lng":-97.6355214197085},"southwest":{"lat":38.80600906970849,"lng":-97.6382193802915}}},"icon":"https://maps.gstatic.com/mapfiles/place_api/icons/v1/png_71/generic_business-71.png","id":null,"international_phone_number":null,"name":"1 Vision Aviation","place_id":"ChIJp2g5XB7JvIcREjrS4DpcqMw","rating":3.7,"reference":null,"reviews":[{"author_name":"Bobby Whiteman","author_url":"https://www.google.com/maps/contrib/109708439715971637247/reviews","language":"en","profile_photo_url":"https://lh3.googleusercontent.com/a/AATXAJwOg45O_L9TKpjKclElZALwu1ES7B5HWNRNP8iu=s128-c0x00000000-cc-rp-mo","rating":1,"relative_time_description":"10 months ago","text":"Had to give a full star because it wont let you give half star rating.surprised this place is still in buisiness.","time":1614626368},{"author_name":"Ethan Bertrand","author_url":"https://www.google.com/maps/contrib/108556567451515714129/reviews","language":"en","profile_photo_url":"https://lh3.googleusercontent.com/a/AATXAJxU38FBP5oPKcf_BjJEYKYVCDcDY7cc0JSJFlWl=s128-c0x00000000-cc-rp-mo","rating":5,"relative_time_description":"11 months ago","text":"Jimmy and team are knowledgeable, respectful and easy to work with.","time":1611253702},{"author_name":"Jett Vann","author_url":"https://www.google.com/maps/contrib/114548707315401440630/reviews","language":null,"profile_photo_url":"https://lh3.googleusercontent.com/a-/AOh14GjSQ5dAamUoCUqA0833Gp1LKWcAevssjZCjJ3i8=s128-c0x00000000-cc-rp-mo","rating":5,"relative_time_description":"9 months ago","text":"","time":1616819256},{"author_name":"Biruk Alemu","author_url":"https://www.google.com/maps/contrib/111253678928477014522/reviews","language":null,"profile_photo_url":"https://lh3.googleusercontent.com/a/AATXAJx4MNEjS5UkaOFCeLEDf7y_toRAG7u1MuE_c6sy=s128-c0x00000000-cc-rp-mo","rating":5,"relative_time_description":"a year ago","text":"","time":1606802599},{"author_name":"Amanda Monthei","author_url":"https://www.google.com/maps/contrib/116577537071926482113/reviews","language":null,"profile_photo_url":"https://lh3.googleusercontent.com/a/AATXAJwyVQTN6YVPIG--AFSsx1DHORRc8eTmffjc0lDq=s128-c0x00000000-cc-rp-mo","rating":1,"relative_time_description":"5 months ago","text":"","time":1626375660}],"types":["point_of_interest","establishment"],"url":"https://maps.google.com/?cid=14747138387774421522","utc_offset":-360,"vicinity":"2044 Scanlan Avenue, Salina","website":"http://1vision.aero/"},"status":"OK"} | AM2: <span class="street-address">2044 Scanlan Ave</span>, <span class="locality">Salina</span>, <span class="region">KS</span> <span class="postal-code">67401</span>, <span class="country-name">USA</span> | AO2: https://maps.gstatic.com/mapfiles/place_api/icons/v1/png_71/generic_business-71.png | AR2: point_of_interest,establishment | AS2: -360 | AT2: 2044 Scanlan Avenue, Salina | AU2: http://1vision.aero/ | AV2: 3.7 | AW2: 5
A3: 24/7 Flight Support | E3: 14121 NE Airport Way | G3: Portland | H3: OR | I3: 97230 | J3: US | K3: (631) 731-0565 | L3: http://www.247.aero/contact/ | M3: PDX | N3: CNSL | Y3: https://maps.google.com/?cid=12255980812482063639 | AB3: 24/7 Flight Support | AD3: ChIJ3bQdlZmjlVQRFy3_LZ39Fao | AE3: 14121 NE Airport Way, Portland, OR 97230, USA | AJ3: 45.561737 | AK3: -122.51725 | AL3: {"html_attributions":[],"result":{"address_components":[{"long_name":"14121","short_name":"14121","types":["street_number"]},{"long_name":"Northeast Airport Way","short_name":"NE Airport Way","types":["route"]},{"long_name":"Argay","short_name":"Argay","types":["neighborhood","political"]},{"long_name":"Portland","short_name":"Portland","types":["locality","political"]},{"long_name":"Multnomah County","short_name":"Multnomah County","types":["administrative_area_level_2","political"]},{"long_name":"Oregon","short_name":"OR","types":["administrative_area_level_1","political"]},{"long_name":"United States","short_name":"US","types":["country","political"]},{"long_name":"97230","short_name":"97230","types":["postal_code"]}],"adr_address":"<span class=\"street-address\">14121 NE Airport Way</span>, <span class=\"locality\">Portland</span>, <span class=\"region\">OR</span> <span class=\"postal-code\">97230</span>, <span class=\"country-name\">USA</span>","formatted_address":"14121 NE Airport Way, Portland, OR 97230, USA","formatted_phone_number":"(631) 731-0565","geometry":{"location":{"lat":45.5617374,"lng":-122.5172475},"viewport":{"northeast":{"lat":45.5629231802915,"lng":-122.5160710697085},"southwest":{"lat":45.5602252197085,"lng":-122.5187690302915}}},"icon":"https://maps.gstatic.com/mapfiles/place_api/icons/v1/png_71/generic_business-71.png","id":null,"international_phone_number":"+1 631-731-0565","name":"24/7 Flight Support","place_id":"ChIJ3bQdlZmjlVQRFy3_LZ39Fao","rating":5.0,"reference":null,"reviews":[{"author_name":"Ammar Eng","author_url":"https://www.google.com/maps/contrib/108465733041230473970/reviews","language":"en","profile_photo_url":"https://lh3.googleusercontent.com/a-/AOh14GjwMOzYWT104gA2VJEy36ksFtBPSs0h_Jg0C_iX=s128-c0x00000000-cc-rp-mo-ba2","rating":5,"relative_time_description":"6 months ago","text":"I love this Road","time":1625093755}],"types":["point_of_interest","establishment"],"url":"https://maps.google.com/?cid=12255980812482063639","utc_offset":-480,"vicinity":"14121 Northeast Airport Way, Portland","website":"http://www.247.aero/contact/"},"status":"OK"} | AM3: <span class="street-address">14121 NE Airport Way</span>, <span class="locality">Portland</span>, <span class="region">OR</span> <span class="postal-code">97230</span>, <span class="country-name">USA</span> | AN3: (631) 731-0565 | AO3: https://maps.gstatic.com/mapfiles/place_api/icons/v1/png_71/generic_business-71.png | AQ3: +1 631-731-0565 | AR3: point_of_interest,establishment | AS3: -480 | AT3: 14121 Northeast Airport Way, Portland | AU3: http://www.247.aero/contact/ | AV3: 5 | AW3: 1
A4: 3 D Aviation Inc | B4: Nassau Flyers | E4: 1300 New Hwy | G4: Farmingdale | H4: NY | I4: 11735-1517 | J4: US | K4: (631) 454-0626 | L4: http://www.flynfi.com/ | M4: FRG | N4: FLT61 | Y4: https://maps.google.com/?cid=9012127429399910560 | AB4: 3 D Aviation Inc | AC4: OPERATIONAL | AD4: ChIJsYGUsBwr6IkRoJjvEyaCEX0 | AE4: 1300 New Hwy, Farmingdale, NY 11735, USA | AJ4: 40.738428 | AK4: -73.413406 | AL4: {"html_attributions":[],"result":{"address_components":[{"long_name":"1300","short_name":"1300","types":["street_number"]},{"long_name":"New Highway","short_name":"New Hwy","types":["route"]},{"long_name":"Farmingdale","short_name":"Farmingdale","types":["locality","political"]},{"long_name":"Babylon","short_name":"Babylon","types":["administrative_area_level_3","political"]},{"long_name":"Suffolk County","short_name":"Suffolk County","types":["administrative_area_level_2","political"]},{"long_name":"New York","short_name":"NY","types":["administrative_area_level_1","political"]},{"long_name":"United States","short_name":"US","types":["country","political"]},{"long_name":"11735","short_name":"11735","types":["postal_code"]},{"long_name":"1517","short_name":"1517","types":["postal_code_suffix"]}],"adr_address":"<span class=\"street-address\">1300 New Hwy</span>, <span class=\"locality\">Farmingdale</span>, <span class=\"region\">NY</span> <span class=\"postal-code\">11735-1517</span>, <span class=\"country-name\">USA</span>","formatted_address":"1300 New Hwy, Farmingdale, NY 11735, USA","formatted_phone_number":"(631) 454-0626","geometry":{"location":{"lat":40.73842820000001,"lng":-73.41340629999999},"viewport":{"northeast":{"lat":40.7397872302915,"lng":-73.41191856970849},"southwest":{"lat":40.73708926970851,"lng":-73.4146165302915}}},"icon":"https://maps.gstatic.com/mapfiles/place_api/icons/v1/png_71/generic_business-71.png","id":null,"international_phone_number":"+1 631-454-0626","name":"3 D Aviation Inc","place_id":"ChIJsYGUsBwr6IkRoJjvEyaCEX0","rating":null,"reference":null,"reviews":null,"types":["point_of_interest","establishment"],"url":"https://maps.google.com/?cid=9012127429399910560","utc_offset":-300,"vicinity":"1300 New Highway, Farmingdale","website":"http://www.flynfi.com/"},"status":"OK"} | AM4: <span class="street-address">1300 New Hwy</span>, <span class="locality">Farmingdale</span>, <span class="region">NY</span> <span class="postal-code">11735-1517</span>, <span class="country-name">USA</span> | AN4: (631) 454-0626 | AO4: https://maps.gstatic.com/mapfiles/place_api/icons/v1/png_71/generic_business-71.png | AQ4: +1 631-454-0626 | AR4: point_of_interest,establishment | AS4: -300 | AT4: 1300 New Highway, Farmingdale | AU4: http://www.flynfi.com/
A5: 3D Aviation Charter & Cargo | B5: Nassau Flyers | E5: 1300 New Hwy | G5: Farmingdale | H5: NY | I5: 11735-1517 | J5: US | K5: (631) 465-0885 | L5: https://www.nassauflyers.com/ | M5: FRG | N5: P135 | O5: CRG | Y5: https://maps.google.com/?cid=11083942137109628795 | AB5: 3D Aviation Charter & Cargo | AC5: OPERATIONAL | AD5: ChIJsYGUsBwr6IkRe0dnAaYS0pk | AE5: 1300 New Hwy, Farmingdale, NY 11735, USA | AJ5: 40.738389 | AK5: -73.413397 | AL5: {"html_attributions":[],"result":{"address_components":[{"long_name":"1300","short_name":"1300","types":["street_number"]},{"long_name":"New Highway","short_name":"New Hwy","types":["route"]},{"long_name":"Farmingdale","short_name":"Farmingdale","types":["locality","political"]},{"long_name":"Babylon","short_name":"Babylon","types":["administrative_area_level_3","political"]},{"long_name":"Suffolk County","short_name":"Suffolk County","types":["administrative_area_level_2","political"]},{"long_name":"New York","short_name":"NY","types":["administrative_area_level_1","political"]},{"long_name":"United States","short_name":"US","types":["country","political"]},{"long_name":"11735","short_name":"11735","types":["postal_code"]},{"long_name":"1517","short_name":"1517","types":["postal_code_suffix"]}],"adr_address":"<span class=\"street-address\">1300 New Hwy</span>, <span class=\"locality\">Farmingdale</span>, <span class=\"region\">NY</span> <span class=\"postal-code\">11735-1517</span>, <span class=\"country-name\">USA</span>","formatted_address":"1300 New Hwy, Farmingdale, NY 11735, USA","formatted_phone_number":"(631) 465-0885","geometry":{"location":{"lat":40.7383893,"lng":-73.41339700000002},"viewport":{"northeast":{"lat":40.73974818029151,"lng":-73.4119114697085},"southwest":{"lat":40.73705021970851,"lng":-73.4146094302915}}},"icon":"https://maps.gstatic.com/mapfiles/place_api/icons/v1/png_71/generic_business-71.png","id":null,"international_phone_number":"+1 631-465-0885","name":"3D Aviation Charter & Cargo","place_id":"ChIJsYGUsBwr6IkRe0dnAaYS0pk","rating":null,"reference":null,"reviews":null,"types":["travel_agency","point_of_interest","establishment"],"url":"https://maps.google.com/?cid=11083942137109628795","utc_offset":-300,"vicinity":"1300 New Highway, Farmingdale","website":null},"status":"OK"} | AM5: <span class="street-address">1300 New Hwy</span>, <span class="locality">Farmingdale</span>, <span class="region">NY</span> <span class="postal-code">11735-1517</span>, <span class="country-name">USA</span> | AN5: (631) 465-0885 | AO5: https://maps.gstatic.com/mapfiles/place_api/icons/v1/png_71/generic_business-71.png | AQ5: +1 631-465-0885 | AR5: travel_agency,point_of_interest,establishment | AS5: -300 | AT5: 1300 New Highway, Farmingdale
A6: 4-J Aviation | G6: Tulsa | H6: OK | I6: 74152-0366 | J6: US | K6: (918) 299-2532 | M6: RVS | Y6: https://maps.google.com/?cid=16083813591999652084 | AB6: 4-J Aviation | AC6: OPERATIONAL | AD6: ChIJVVyuv3vrtocR9CC9CD8vNd8 | AE6: PO Box 52366, Tulsa, OK 74152, USA | AJ6: 36.141869 | AK6: -95.959952 | AL6: {"html_attributions":[],"result":{"address_components":[{"long_name":"PO Box 52366","short_name":"PO Box 52366","types":["post_box"]},{"long_name":"Cherry Street","short_name":"Cherry Street","types":["neighborhood","political"]},{"long_name":"Tulsa","short_name":"Tulsa","types":["locality","political"]},{"long_name":"Tulsa County","short_name":"Tulsa County","types":["administrative_area_level_2","political"]},{"long_name":"Oklahoma","short_name":"OK","types":["administrative_area_level_1","political"]},{"long_name":"United States","short_name":"US","types":["country","political"]},{"long_name":"74152","short_name":"74152","types":["postal_code"]},{"long_name":"0366","short_name":"0366","types":["postal_code_suffix"]}],"adr_address":"<span class=\"post-office-box\">PO Box 52366</span>, <span class=\"locality\">Tulsa</span>, <span class=\"region\">OK</span> <span class=\"postal-code\">74152-0366</span>, <span class=\"country-name\">USA</span>","formatted_address":"PO Box 52366, Tulsa, OK 74152, USA","formatted_phone_number":"(918) 299-2532","geometry":{"location":{"lat":36.1418688,"lng":-95.95995169999999},"viewport":{"northeast":{"lat":36.1432177802915,"lng":-95.95861071970849},"southwest":{"lat":36.1405198197085,"lng":-95.96130868029151}}},"icon":"https://maps.gstatic.com/mapfiles/place_api/icons/v1/png_71/generic_business-71.png","id":null,"international_phone_number":"+1 918-299-2532","name":"4-J Aviation","place_id":"ChIJVVyuv3vrtocR9CC9CD8vNd8","rating":null,"reference":null,"reviews":null,"types":["point_of_interest","establishment"],"url":"https://maps.google.com/?cid=16083813591999652084","utc_offset":-360,"vicinity":"Tulsa","website":null},"status":"OK"} | AM6: <span class="post-office-box">PO Box 52366</span>, <span class="locality">Tulsa</span>, <span class="region">OK</span> <span class="postal-code">74152-0366</span>, <span class="country-name">USA</span> | AN6: (918) 299-2532 | AO6: https://maps.gstatic.com/mapfiles/place_api/icons/v1/png_71/generic_business-71.png | AQ6: +1 918-299-2532 | AR6: point_of_interest,establishment | AS6: -360 | AT6: Tulsa
A7: A & P Aviation Consulting | E7: 2111 Smithtown Ave | G7: Ronkonkoma | H7: NY | I7: 11779-7364 | J7: US | K7: (631) 588-7774 | L7: http://www.apaviationconsulting.com/Home.html | M7: ISP | N7: CNSL | Y7: https://maps.google.com/?cid=4560746926675584844 | AB7: A & P Aviation Consulting | AC7: OPERATIONAL | AD7: ChIJBUpAFbY36IkRTOfzeioHSz8 | AE7: 2111 Smithtown Ave, Ronkonkoma, NY 11779, USA | AJ7: 40.79855 | AK7: -73.110028 | AL7: {"html_attributions":[],"result":{"address_components":[{"long_name":"2111","short_name":"2111","types":["street_number"]},{"long_name":"Smithtown Avenue","short_name":"Smithtown Ave","types":["route"]},{"long_name":"Ronkonkoma","short_name":"Ronkonkoma","types":["locality","political"]},{"long_name":"Islip","short_name":"Islip","types":["administrative_area_level_3","political"]},{"long_name":"Suffolk County","short_name":"Suffolk County","types":["administrative_area_level_2","political"]},{"long_name":"New York","short_name":"NY","types":["administrative_area_level_1","political"]},{"long_name":"United States","short_name":"US","types":["country","political"]},{"long_name":"11779","short_name":"11779","types":["postal_code"]},{"long_name":"7364","short_name":"7364","types":["postal_code_suffix"]}],"adr_address":"<span class=\"street-address\">2111 Smithtown Ave</span>, <span class=\"locality\">Ronkonkoma</span>, <span class=\"region\">NY</span> <span class=\"postal-code\">11779-7364</span>, <span class=\"country-name\">USA</span>","formatted_address":"2111 Smithtown Ave, Ronkonkoma, NY 11779, USA","formatted_phone_number":"(631) 588-7774","geometry":{"location":{"lat":40.7985504,"lng":-73.1100276},"viewport":{"northeast":{"lat":40.7999818802915,"lng":-73.10867806970849},"southwest":{"lat":40.7972839197085,"lng":-73.11137603029151}}},"icon":"https://maps.gstatic.com/mapfiles/place_api/icons/v1/png_71/generic_business-71.png","id":null,"international_phone_number":"+1 631-588-7774","name":"A & P Aviation Consulting","place_id":"ChIJBUpAFbY36IkRTOfzeioHSz8","rating":null,"reference":null,"reviews":null,"types":["point_of_interest","establishment"],"url":"https://maps.google.com/?cid=4560746926675584844","utc_offset":-300,"vicinity":"2111 Smithtown Avenue, Ronkonkoma","website":"http://www.apaviationconsulting.com/Home.html"},"status":"OK"} | AM7: <span class="street-address">2111 Smithtown Ave</span>, <span class="locality">Ronkonkoma</span>, <span class="region">NY</span> <span class="postal-code">11779-7364</span>, <span class="country-name">USA</span> | AN7: (631) 588-7774 | AO7: https://maps.gstatic.com/mapfiles/place_api/icons/v1/png_71/generic_business-71.png | AQ7: +1 631-588-7774 | AR7: point_of_interest,establishment | AS7: -300 | AT7: 2111 Smithtown Avenue, Ronkonkoma | AU7: http://www.apaviationconsulting.com/Home.html
A8: A Different Point of View | E8: 45 Hartley Pl | G8: Santa Barbara | H8: CA | I8: 93117 | J8: US | K8: (805) 698-6784 | L8: http://www.adifferentpointofview.org/ | M8: SBA | N8: NPRO | Y8: https://maps.google.com/?cid=7423200209373708 | AB8: A Different Point of View | AC8: OPERATIONAL | AD8: ChIJ5UX2GYFA6YARDIqTe1xfGgA | AE8: 45 Hartley Pl, Santa Barbara, CA 93117, USA | AJ8: 34.432998 | AK8: -119.83884 | AL8: {"html_attributions":[],"result":{"address_components":[{"long_name":"45","short_name":"45","types":["street_number"]},{"long_name":"Hartley Place","short_name":"Hartley Pl","types":["route"]},{"long_name":"Santa Barbara","short_name":"Santa Barbara","types":["locality","political"]},{"long_name":"Santa Barbara County","short_name":"Santa Barbara County","types":["administrative_area_level_2","political"]},{"long_name":"California","short_name":"CA","types":["administrative_area_level_1","political"]},{"long_name":"United States","short_name":"US","types":["country","political"]},{"long_name":"93117","short_name":"93117","types":["postal_code"]}],"adr_address":"<span class=\"street-address\">45 Hartley Pl</span>, <span class=\"locality\">Santa Barbara</span>, <span class=\"region\">CA</span> <span class=\"postal-code\">93117</span>, <span class=\"country-name\">USA</span>","formatted_address":"45 Hartley Pl, Santa Barbara, CA 93117, USA","formatted_phone_number":"(805) 698-6784","geometry":{"location":{"lat":34.43299769999999,"lng":-119.8388429},"viewport":{"northeast":{"lat":34.4343372802915,"lng":-119.8374574697085},"southwest":{"lat":34.4316393197085,"lng":-119.8401554302915}}},"icon":"https://maps.gstatic.com/mapfiles/place_api/icons/v1/png_71/generic_business-71.png","id":null,"international_phone_number":"+1 805-698-6784","name":"A Different Point of View","place_id":"ChIJ5UX2GYFA6YARDIqTe1xfGgA","rating":5.0,"reference":null,"reviews":[{"author_name":"Paul Andre","author_url":"https://www.google.com/maps/contrib/118104027240777327516/reviews","language":"en","profile_photo_url":"https://lh3.googleusercontent.com/a-/AOh14GhLCr6QDovMUCsnaik9EizYcE8UHRS-3fJ4b9vV=s128-c0x00000000-cc-rp-mo","rating":5,"relative_time_description":"6 years ago","text":"The work ADPOV does for today's youth just takes my breath away. It is transforming the lives of young people, who have not had the advantages of life - like the mind-changing experience of flying - that most of us take for granted. It works. I became a supporter and it's my favorite non-profit. It changes lives.","time":1433370616}],"types":["travel_agency","point_of_interest","establishment"],"url":"https://maps.google.com/?cid=7423200209373708","utc_offset":-480,"vicinity":"45 Hartley Place, Santa Barbara","website":"http://www.adifferentpointofview.org/"},"status":"OK"} | AM8: <span class="street-address">45 Hartley Pl</span>, <span class="locality">Santa Barbara</span>, <span class="region">CA</span> <span class="postal-code">93117</span>, <span class="country-name">USA</span> | AN8: (805) 698-6784 | AO8: https://maps.gstatic.com/mapfiles/place_api/icons/v1/png_71/generic_business-71.png | AQ8: +1 805-698-6784 | AR8: travel_agency,point_of_interest,establishment | AS8: -480 | AT8: 45 Hartley Place, Santa Barbara | AU8: http://www.adifferentpointofview.org/ | AV8: 5 | AW8: 1
A9: A M I R I O N E | G9: Tijuana | H9: B.C. | I9: 22300 | J9: MX | K9: 52790838791 | L9: http://amirione.com/ | M9: TIJ | Y9: https://maps.google.com/?cid=1335117292211012003 | AB9: A M I R I O N E | AC9: OPERATIONAL | AD9: ChIJf2aqLPhI2YARowG4fxpKhxI | AE9: AP 447, Libertad, 22300 Tijuana, B.C., Mexico | AJ9: 32.540637 | AK9: -117.02093 | AL9: {"html_attributions":[],"result":{"address_components":[{"long_name":"Tijuana","short_name":"Tijuana","types":["locality","political"]},{"long_name":"Libertad","short_name":"Libertad","types":["sublocality_level_1","sublocality","political"]},{"long_name":"Baja California","short_name":"B.C.","types":["administrative_area_level_1","political"]},{"long_name":"Mexico","short_name":"MX","types":["country","political"]},{"long_name":"22300","short_name":"22300","types":["postal_code"]}],"adr_address":"AP 447, <span class=\"extended-address\">Libertad</span>, <span class=\"postal-code\">22300</span> <span class=\"locality\">Tijuana</span>, <span class=\"region\">B.C.</span>, <span class=\"country-name\">Mexico</span>","formatted_address":"AP 447, Libertad, 22300 Tijuana, B.C., Mexico","formatted_phone_number":"52790838791","geometry":{"location":{"lat":32.5406369,"lng":-117.0209316},"viewport":{"northeast":{"lat":32.5420511302915,"lng":-117.0195264197085},"southwest":{"lat":32.5393531697085,"lng":-117.0222243802915}}},"icon":"https://maps.gstatic.com/mapfiles/place_api/icons/v1/png_71/school-71.png","id":null,"international_phone_number":"+52 52790838791","name":"A M I R I O N E","place_id":"ChIJf2aqLPhI2YARowG4fxpKhxI","rating":null,"reference":null,"reviews":null,"types":["university","point_of_interest","establishment"],"url":"https://maps.google.com/?cid=1335117292211012003","utc_offset":-480,"vicinity":"AP 447, Tijuana","website":null},"status":"OK"} | AM9: AP 447, <span class="extended-address">Libertad</span>, <span class="postal-code">22300</span> <span class="locality">Tijuana</span>, <span class="region">B.C.</span>, <span class="country-name">Mexico</span> | AN9: 52790838791 | AO9: https://maps.gstatic.com/mapfiles/place_api/icons/v1/png_71/school-71.png | AQ9: +52 52790838791 | AR9: university,point_of_interest,establishment | AS9: -480 | AT9: AP 447, Tijuana
A10: A P D Aviation | E10: 255 El Cielo Rd | F10: # 140 | G10: Palm Springs | H10: CA | I10: 92262-6910 | J10: US | K10: (760) 327-9247 | M10: PSP | Y10: https://maps.google.com/?cid=10564526803655890608 | AB10: A P D Aviation | AC10: OPERATIONAL | AD10: ChIJ_S9DpX8c24ARsJYAmCe9nJI | AE10: 255 El Cielo Rd # 140, Palm Springs, CA 92262, USA | AJ10: 33.825621 | AK10: -116.51163 | AL10: {"html_attributions":[],"result":{"address_components":[{"long_name":"# 140","short_name":"# 140","types":["subpremise"]},{"long_name":"255","short_name":"255","types":["street_number"]},{"long_name":"El Cielo Road","short_name":"El Cielo Rd","types":["route"]},{"long_name":"Palm Springs","short_name":"Palm Springs","types":["locality","political"]},{"long_name":"Riverside County","short_name":"Riverside County","types":["administrative_area_level_2","political"]},{"long_name":"California","short_name":"CA","types":["administrative_area_level_1","political"]},{"long_name":"United States","short_name":"US","types":["country","political"]},{"long_name":"92262","short_name":"92262","types":["postal_code"]},{"long_name":"6910","short_name":"6910","types":["postal_code_suffix"]}],"adr_address":"<span class=\"street-address\">255 El Cielo Rd # 140</span>, <span class=\"locality\">Palm Springs</span>, <span class=\"region\">CA</span> <span class=\"postal-code\">92262-6910</span>, <span class=\"country-name\">USA</span>","formatted_address":"255 El Cielo Rd # 140, Palm Springs, CA 92262, USA","formatted_phone_number":"(760) 327-9247","geometry":{"location":{"lat":33.825621,"lng":-116.511633},"viewport":{"northeast":{"lat":33.82683833029149,"lng":-116.5102864197085},"southwest":{"lat":33.82414036970849,"lng":-116.5129843802915}}},"icon":"https://maps.gstatic.com/mapfiles/place_api/icons/v1/png_71/generic_business-71.png","id":null,"international_phone_number":"+1 760-327-9247","name":"A P D Aviation","place_id":"ChIJ_S9DpX8c24ARsJYAmCe9nJI","rating":null,"reference":null,"reviews":null,"types":["point_of_interest","establishment"],"url":"https://maps.google.com/?cid=10564526803655890608","utc_offset":-480,"vicinity":"255 El Cielo Road # 140, Palm Springs","website":null},"status":"OK"} | AM10: <span class="street-address">255 El Cielo Rd # 140</span>, <span class="locality">Palm Springs</span>, <span class="region">CA</span> <span class="postal-code">92262-6910</span>, <span class="country-name">USA</span> | AN10: (760) 327-9247 | AO10: https://maps.gstatic.com/mapfiles/place_api/icons/v1/png_71/generic_business-71.png | AQ10: +1 760-327-9247 | AR10: point_of_interest,establishment | AS10: -480 | AT10: 255 El Cielo Road # 140, Palm Springs
A11: A-One FS LLC | E11: 37300 Palmdale Rd | G11: Rancho Mirage | H11: CA | I11: 92270-2246 | J11: US | K11: (760) 333-4906 | Y11: https://maps.google.com/?cid=9925962855924586417 | AB11: A-One FS LLC | AD11: ChIJVVVZC5YC24ARsVcboaAawIk | AE11: 37300 Palmdale Rd, Rancho Mirage, CA 92270, USA | AJ11: 33.777322 | AK11: -116.43675 | AL11: {"html_attributions":[],"result":{"address_components":[{"long_name":"37300","short_name":"37300","types":["street_number"]},{"long_name":"Palmdale Road","short_name":"Palmdale Rd","types":["route"]},{"long_name":"Rancho Mirage","short_name":"Rancho Mirage","types":["locality","political"]},{"long_name":"Riverside County","short_name":"Riverside County","types":["administrative_area_level_2","political"]},{"long_name":"California","short_name":"CA","types":["administrative_area_level_1","political"]},{"long_name":"United States","short_name":"US","types":["country","political"]},{"long_name":"92270","short_name":"92270","types":["postal_code"]},{"long_name":"2246","short_name":"2246","types":["postal_code_suffix"]}],"adr_address":"<span class=\"street-address\">37300 Palmdale Rd</span>, <span class=\"locality\">Rancho Mirage</span>, <span class=\"region\">CA</span> <span class=\"postal-code\">92270-2246</span>, <span class=\"country-name\">USA</span>","formatted_address":"37300 Palmdale Rd, Rancho Mirage, CA 92270, USA","formatted_phone_number":"(760) 333-4906","geometry":{"location":{"lat":33.7773218,"lng":-116.4367475},"viewport":{"northeast":{"lat":33.77866468029149,"lng":-116.4354951197085},"southwest":{"lat":33.7759667197085,"lng":-116.4381930802915}}},"icon":"https://maps.gstatic.com/mapfiles/place_api/icons/v1/png_71/generic_business-71.png","id":null,"international_phone_number":"+1 760-333-4906","name":"A-One FS LLC","place_id":"ChIJVVVZC5YC24ARsVcboaAawIk","rating":null,"reference":null,"reviews":null,"types":["point_of_interest","establishment"],"url":"https://maps.google.com/?cid=9925962855924586417","utc_offset":-480,"vicinity":"37300 Palmdale Road, Rancho Mirage","website":null},"status":"OK"} | AM11: <span class="street-address">37300 Palmdale Rd</span>, <span class="locality">Rancho Mirage</span>, <span class="region">CA</span> <span class="postal-code">92270-2246</span>, <span class="country-name">USA</span> | AN11: (760) 333-4906 | AO11: https://maps.gstatic.com/mapfiles/place_api/icons/v1/png_71/generic_business-71.png | AQ11: +1 760-333-4906 | AR11: point_of_interest,establishment | AS11: -480 | AT11: 37300 Palmdale Road, Rancho Mirage
A12: A&P Americas Best AMT Course | G12: Goodyear | H12: AZ | I12: 85338 | J12: US | K12: (602) 284-6994 | L12: http://www.americasbestamtcourses.com/ | M12: GEU | N12: TRNS | Y12: https://maps.google.com/?cid=296734959199369194 | AB12: A&P Americas Best AMT Course | AD12: ChIJWwFBTxw5K4cR6reEi982HgQ | AE12: 1300 South Litchfield Road Building: 150, Suite: A1020, Goodyear, AZ 85338, USA | AJ12: 33.432101 | AK12: -112.36015 | AL12: {"html_attributions":[],"result":{"address_components":[{"long_name":"Goodyear","short_name":"Goodyear","types":["locality","political"]},{"long_name":"Maricopa County","short_name":"Maricopa County","types":["administrative_area_level_2","political"]},{"long_name":"Arizona","short_name":"AZ","types":["administrative_area_level_1","political"]},{"long_name":"United States","short_name":"US","types":["country","political"]},{"long_name":"85338","short_name":"85338","types":["postal_code"]}],"adr_address":"1300 South Litchfield Road Building: 150, Suite: A1020, <span class=\"locality\">Goodyear</span>, <span class=\"region\">AZ</span> <span class=\"postal-code\">85338</span>, <span class=\"country-name\">USA</span>","formatted_address":"1300 South Litchfield Road Building: 150, Suite: A1020, Goodyear, AZ 85338, USA","formatted_phone_number":"(602) 284-6994","geometry":{"location":{"lat":33.4321013,"lng":-112.3601523},"viewport":{"northeast":{"lat":33.4333871302915,"lng":-112.3571457},"southwest":{"lat":33.4306891697085,"lng":-112.3611545}}},"icon":"https://maps.gstatic.com/mapfiles/place_api/icons/v1/png_71/school-71.png","id":null,"international_phone_number":"+1 602-284-6994","name":"A&P Americas Best AMT Course","place_id":"ChIJWwFBTxw5K4cR6reEi982HgQ","rating":4.7,"reference":null,"reviews":[{"author_name":"Mauricio","author_url":"https://www.google.com/maps/contrib/100190515489670838339/reviews","language":"en","profile_photo_url":"https://lh3.googleusercontent.com/a-/AOh14GjcX-uafQbZs23qvd9-Shck961dlgqi2JkDQU-wpQ=s128-c0x00000000-cc-rp-mo-ba4","rating":1,"relative_time_description":"2 months ago","text":"The worst experience that I've had. I payed for a course but never scheduled me, never answered my calls or emails. I'm looking for refund my money but, I think it will be very difficult, these people are opportunists.\nIf you are foreign don't go to this place.","time":1635352330},{"author_name":"Garrett Williams","author_url":"https://www.google.com/maps/contrib/101033541074527730761/reviews","language":"en","profile_photo_url":"https://lh3.googleusercontent.com/a-/AOh14GhbNNo-hbKy68jLJGKoXP1Ll5Ab-fG-Ke_DJv6zmQ=s128-c0x00000000-cc-rp-mo-ba2","rating":5,"relative_time_description":"10 months ago","text":"Antonio is the best instructor out there for this purpose. I just finished with the course and got my A&P. As long as you put in the work, he will help you to help yourself. Highly recommend if you're looking into it.","time":1614892373},{"author_name":"Manatees Moo","author_url":"https://www.google.com/maps/contrib/108463942080003028885/reviews","language":"en","profile_photo_url":"https://lh3.googleusercontent.com/a-/AOh14Ggvy1H3B29B7VMIdzcjbGKxLqB6OcwKZznWwi9myA=s128-c0x00000000-cc-rp-mo-ba6","rating":5,"relative_time_description":"4 months ago","text":"This reviews for the testing center portion of this facility and not its training. Friendly staff, great set up, clean facility, and awesome decor.","time":1629835256},{"author_name":"B","author_url":"https://www.google.com/maps/contrib/100160310465815865276/reviews","language":"en","profile_photo_url":"https://lh3.googleusercontent.com/a/AATXAJxaAJt449HO8jPA-JN-GQW1KLDn4zKHLhzDD7jg=s128-c0x00000000-cc-rp-mo","rating":5,"relative_time_description":"a year ago","text":"I just finished the A & P course there and it was awesome. It was extremely challenging, but Tony and the team at America’s Best AMT get the job done. They were always extremely professional and made the class fun. They were always available to help you out with any challenging areas and didn’t stop until you understood the material and felt comfortable. I highly recommend this course.","time":1582939093},{"author_name":"shane routery","author_url":"https://www.google.com/maps/contrib/115757146187641274885/reviews","language":"en","profile_photo_url":"https://lh3.googleusercontent.com/a/AATXAJycruw_GzZtFl2z0q4AbTpMgKn318k0ChcfrOI=s128-c0x00000000-cc-rp-mo-ba3","rating":5,"relative_time_description":"a year ago","text":"Best place for all military personal! Great staff and awesome instructors!","time":1603211099}],"types":["university","point_of_interest","establishment"],"url":"https://maps.google.com/?cid=296734959199369194","utc_offset":-420,"vicinity":"1300 South Litchfield Road Building: 150, Suite: A1020, Goodyear","website":"http://www.americasbestamtcourses.com/"},"status":"OK"} | AM12: 1300 South Litchfield Road Building: 150, Suite: A1020, <span class="locality">Goodyear</span>, <span class="region">AZ</span> <span class="postal-code">85338</span>, <span class="country-name">USA</span> | AN12: (602) 284-6994 | AO12: https://maps.gstatic.com/mapfiles/place_api/icons/v1/png_71/school-71.png | AQ12: +1 602-284-6994 | AR12: university,point_of_interest,establishment | AS12: -420 | AT12: 1300 South Litchfield Road Building: 150, Suite: A1020, Goodyear | AU12: http://www.americasbestamtcourses.com/ | AV12: 4.7 | AW12: 5
A13: A2M Consulting, LLC | E13: 15655 W Roosevelt St | F13: Ste 225 | G13: Goodyear | H13: AZ | I13: 85338 | J13: US | K13: (702) 351-4204 | L13: http://a2mpc.com/contact/ | M13: GEU | N13: CNSL | Y13: https://maps.google.com/?cid=16890128378300406271 | AB13: A2M Consulting, LLC | AD13: ChIJzRlgo284K4cR_xlXt0XKZeo | AE13: 15655 W Roosevelt St Ste 225, Goodyear, AZ 85338, USA | AJ13: 33.455609 | AK13: -112.39571 | AL13: {"html_attributions":[],"result":{"address_components":[{"long_name":"Ste 225","short_name":"Ste 225","types":["subpremise"]},{"long_name":"15655","short_name":"15655","types":["street_number"]},{"long_name":"West Roosevelt Street","short_name":"W Roosevelt St","types":["route"]},{"long_name":"Canyon Trails","short_name":"Canyon Trails","types":["neighborhood","political"]},{"long_name":"Goodyear","short_name":"Goodyear","types":["locality","political"]},{"long_name":"Maricopa County","short_name":"Maricopa County","types":["administrative_area_level_2","political"]},{"long_name":"Arizona","short_name":"AZ","types":["administrative_area_level_1","political"]},{"long_name":"United States","short_name":"US","types":["country","political"]},{"long_name":"85338","short_name":"85338","types":["postal_code"]}],"adr_address":"<span class=\"street-address\">15655 W Roosevelt St Ste 225</span>, <span class=\"locality\">Goodyear</span>, <span class=\"region\">AZ</span> <span class=\"postal-code\">85338</span>, <span class=\"country-name\">USA</span>","formatted_address":"15655 W Roosevelt St Ste 225, Goodyear, AZ 85338, USA","formatted_phone_number":"(702) 351-4204","geometry":{"location":{"lat":33.4556088,"lng":-112.3957055},"viewport":{"northeast":{"lat":33.4570946302915,"lng":-112.3942859697085},"southwest":{"lat":33.45439666970851,"lng":-112.3969839302915}}},"icon":"https://maps.gstatic.com/mapfiles/place_api/icons/v1/png_71/generic_business-71.png","id":null,"international_phone_number":"+1 702-351-4204","name":"A2M Consulting, LLC","place_id":"ChIJzRlgo284K4cR_xlXt0XKZeo","rating":5.0,"reference":null,"reviews":[{"author_name":"sean caffrey","author_url":"https://www.google.com/maps/contrib/118222312064658504028/reviews","language":"en","profile_photo_url":"https://lh3.googleusercontent.com/a-/AOh14Gg8YUvEDDZAqq8ku3YoeXMJ_Dh-7muWjzGlARKPLQ=s128-c0x00000000-cc-rp-mo","rating":5,"relative_time_description":"a year ago","text":"Had a good time working there for Al.","time":1603225516},{"author_name":"Al Arseo","author_url":"https://www.google.com/maps/contrib/105412599398032545278/reviews","language":null,"profile_photo_url":"https://lh3.googleusercontent.com/a/AATXAJwlB3-OyAPMXJ94HL2-yAh4IG-hOw0s_-6nPWpO=s128-c0x00000000-cc-rp-mo","rating":5,"relative_time_description":"3 years ago","text":"","time":1523931982}],"types":["point_of_interest","establishment"],"url":"https://maps.google.com/?cid=16890128378300406271","utc_offset":-420,"vicinity":"15655 West Roosevelt Street Ste 225, Goodyear","website":"http://a2mpc.com/contact/"},"status":"OK"} | AM13: <span class="street-address">15655 W Roosevelt St Ste 225</span>, <span class="locality">Goodyear</span>, <span class="region">AZ</span> <span class="postal-code">85338</span>, <span class="country-name">USA</span> | AN13: (702) 351-4204 | AO13: https://maps.gstatic.com/mapfiles/place_api/icons/v1/png_71/generic_business-71.png | AQ13: +1 702-351-4204 | AR13: point_of_interest,establishment | AS13: -420 | AT13: 15655 West Roosevelt Street Ste 225, Goodyear | AU13: http://a2mpc.com/contact/ | AV13: 5 | AW13: 2
A14: AA Flight Academy/Museum | E14: 13885 FAA Blvd | G14: Fort Worth | H14: TX | I14: 76155 | J14: US | K14: (848) 480-4217 | M14: DFW | N14: MSM | Y14: https://maps.google.com/?cid=2070084160800623114 | AB14: AA Flight Academy/Museum | AC14: OPERATIONAL | AD14: ChIJIWICQACBToYRCgqvk5Nquhw | AE14: 13885 FAA Blvd, Fort Worth, TX 76155, USA | AJ14: 32.833264 | AK14: -97.063254 | AL14: {"html_attributions":[],"result":{"address_components":[{"long_name":"13885","short_name":"13885","types":["street_number"]},{"long_name":"FAA Boulevard","short_name":"FAA Blvd","types":["route"]},{"long_name":"Fort Worth","short_name":"Fort Worth","types":["locality","political"]},{"long_name":"Tarrant County","short_name":"Tarrant County","types":["administrative_area_level_2","political"]},{"long_name":"Texas","short_name":"TX","types":["administrative_area_level_1","political"]},{"long_name":"United States","short_name":"US","types":["country","political"]},{"long_name":"76155","short_name":"76155","types":["postal_code"]}],"adr_address":"<span class=\"street-address\">13885 FAA Blvd</span>, <span class=\"locality\">Fort Worth</span>, <span class=\"region\">TX</span> <span class=\"postal-code\">76155</span>, <span class=\"country-name\">USA</span>","formatted_address":"13885 FAA Blvd, Fort Worth, TX 76155, USA","formatted_phone_number":"(848) 480-4217","geometry":{"location":{"lat":32.8332643,"lng":-97.06325389999999},"viewport":{"northeast":{"lat":32.8350984302915,"lng":-97.06184246970848},"southwest":{"lat":32.8324004697085,"lng":-97.0645404302915}}},"icon":"https://maps.gstatic.com/mapfiles/place_api/icons/v1/png_71/generic_business-71.png","id":null,"international_phone_number":"+1 848-480-4217","name":"AA Flight Academy/Museum","place_id":"ChIJIWICQACBToYRCgqvk5Nquhw","rating":4.7,"reference":null,"reviews":[{"author_name":"ladi da","author_url":"https://www.google.com/maps/contrib/117515253632858859444/reviews","language":"en","profile_photo_url":"https://lh3.googleusercontent.com/a-/AOh14GjRvKmSpldh9M1qkiGwD2XcLNQNOATQ6L6_zWbyEKE=s128-c0x00000000-cc-rp-mo-ba4","rating":5,"relative_time_description":"a month ago","text":"I loved this visit. Top things to me were the cockpit of the MD80 and the flight simulator. I also enjoyed walking in the old Flagship plane. Overall a wonderful visit.","time":1638659479},{"author_name":"Kyni Hartwell","author_url":"https://www.google.com/maps/contrib/111204301923461641770/reviews","language":"en","profile_photo_url":"https://lh3.googleusercontent.com/a-/AOh14GiHgzNsc1PWqKck5i2LimMEZP_iizizNbj2nZ5Bmw=s128-c0x00000000-cc-rp-mo-ba4","rating":5,"relative_time_description":"3 months ago","text":"Awesome entertainment space for events. The museum portion is amazing to stop and look at all the wonderful aviation history. There are also many interactive areas with great photo ops. I highly recommended this living space and museum. It has many details and is it one of the kind of experience.","time":1632696439},{"author_name":"Veronica Linkletter","author_url":"https://www.google.com/maps/contrib/101107613434055859982/reviews","language":"en","profile_photo_url":"https://lh3.googleusercontent.com/a-/AOh14GhC5SCXwy6i8LazGNGm1csVFd3SBoq-lBua2lanLw=s128-c0x00000000-cc-rp-mo-ba4","rating":4,"relative_time_description":"3 weeks ago","text":"Really neat museum, houses the history of American Airlines. There are flight simulators and a control center area where you can answer questions that the operations center has to handle. There is a kids play area other exhibits.","time":1639854826},{"author_name":"JC Gonzalez","author_url":"https://www.google.com/maps/contrib/113012812803848723682/reviews","language":"en","profile_photo_url":"https://lh3.googleusercontent.com/a/AATXAJzL6cxZjwRCAnfDoRFiUFS3ojF5pjUlh4x5D6sq=s128-c0x00000000-cc-rp-mo-ba3","rating":5,"relative_time_description":"3 months ago","text":"A nice place to visit, minutes from DFW, if you have a few hours between flights.","time":1631564298},{"author_name":"Kelly O'Donnell","author_url":"https://www.google.com/maps/contrib/114140844515925276073/reviews","language":"en","profile_photo_url":"https://lh3.googleusercontent.com/a-/AOh14GhWp2ecf1Y4YWe65FfUVt75F7bUlSMcxSG5ykYQ=s128-c0x00000000-cc-rp-mo","rating":5,"relative_time_description":"4 months ago","text":"Wonderful museum with a great staff. My boys loved the MD 80 cockpit!!","time":1628964326}],"types":["point_of_interest","establishment"],"url":"https://maps.google.com/?cid=2070084160800623114","utc_offset":-360,"vicinity":"13885 FAA Boulevard, Fort Worth","website":null},"status":"OK"} | AM14: <span class="street-address">13885 FAA Blvd</span>, <span class="locality">Fort Worth</span>, <span class="region">TX</span> <span class="postal-code">76155</span>, <span class="country-name">USA</span> | AN14: (848) 480-4217 | AO14: https://maps.gstatic.com/mapfiles/place_api/icons/v1/png_71/generic_business-71.png | AQ14: +1 848-480-4217 | AR14: point_of_interest,establishment | AS14: -360 | AT14: 13885 FAA Boulevard, Fort Worth | AV14: 4.7 | AW14: 5
A15: Aaco Avionics | E15: 9626 Rainier Ave S | G15: Seattle | H15: WA | I15: 98118-5935 | J15: US | K15: (206) 722-1571 | M15: SEA | N15: AVIONICS | Y15: https://maps.google.com/?cid=8427022462202789736 | AB15: Aaco Avionics | AC15: OPERATIONAL | AD15: ChIJCUd-R3dCkFQRaL_V9UfM8nQ | AE15: 9626 Rainier Ave S, Seattle, WA 98118, USA | AJ15: 47.518832 | AK15: -122.25631 | AL15: {"html_attributions":[],"result":{"address_components":[{"long_name":"9626","short_name":"9626","types":["street_number"]},{"long_name":"Rainier Avenue South","short_name":"Rainier Ave S","types":["route"]},{"long_name":"Seattle","short_name":"Seattle","types":["locality","political"]},{"long_name":"King County","short_name":"King County","types":["administrative_area_level_2","political"]},{"long_name":"Washington","short_name":"WA","types":["administrative_area_level_1","political"]},{"long_name":"United States","short_name":"US","types":["country","political"]},{"long_name":"98118","short_name":"98118","types":["postal_code"]},{"long_name":"5935","short_name":"5935","types":["postal_code_suffix"]}],"adr_address":"<span class=\"street-address\">9626 Rainier Ave S</span>, <span class=\"locality\">Seattle</span>, <span class=\"region\">WA</span> <span class=\"postal-code\">98118-5935</span>, <span class=\"country-name\">USA</span>","formatted_address":"9626 Rainier Ave S, Seattle, WA 98118, USA","formatted_phone_number":"(206) 722-1571","geometry":{"location":{"lat":47.518832,"lng":-122.2563109},"viewport":{"northeast":{"lat":47.52010913029149,"lng":-122.2550731197085},"southwest":{"lat":47.5174111697085,"lng":-122.2577710802915}}},"icon":"https://maps.gstatic.com/mapfiles/place_api/icons/v1/png_71/generic_business-71.png","id":null,"international_phone_number":"+1 206-722-1571","name":"Aaco Avionics","place_id":"ChIJCUd-R3dCkFQRaL_V9UfM8nQ","rating":null,"reference":null,"reviews":null,"types":["point_of_interest","establishment"],"url":"https://maps.google.com/?cid=8427022462202789736","utc_offset":-480,"vicinity":"9626 Rainier Avenue South, Seattle","website":null},"status":"OK"} | AM15: <span class="street-address">9626 Rainier Ave S</span>, <span class="locality">Seattle</span>, <span class="region">WA</span> <span class="postal-code">98118-5935</span>, <span class="country-name">USA</span> | AN15: (206) 722-1571 | AO15: https://maps.gstatic.com/mapfiles/place_api/icons/v1/png_71/generic_business-71.png | AQ15: +1 206-722-1571 | AR15: point_of_interest,establishment | AS15: -480 | AT15: 9626 Rainier Avenue South, Seattle
A16: ABM | Aviation | E16: 2300 Valley View Ln | F16: #150 | G16: Irving | H16: TX | I16: 75062 | J16: US | K16: (469) 647-5914 | L16: https://www.abm.com/careers/ | M16: DFW | N16: RECT | Y16: https://maps.google.com/?cid=12849398551782558568 | AB16: ABM Industries | AD16: ChIJsTpLHIKBToYRaAtrYOc7UrI | AE16: 2300 Valley View Ln #150, Irving, TX 75062, USA | AJ16: 32.839836 | AK16: -97.020832 | AL16: {"html_attributions":[],"result":{"address_components":[{"long_name":"#150","short_name":"#150","types":["subpremise"]},{"long_name":"2300","short_name":"2300","types":["street_number"]},{"long_name":"Valley View Lane","short_name":"Valley View Ln","types":["route"]},{"long_name":"Irving","short_name":"Irving","types":["locality","political"]},{"long_name":"Dallas County","short_name":"Dallas County","types":["administrative_area_level_2","political"]},{"long_name":"Texas","short_name":"TX","types":["administrative_area_level_1","political"]},{"long_name":"United States","short_name":"US","types":["country","political"]},{"long_name":"75062","short_name":"75062","types":["postal_code"]}],"adr_address":"<span class=\"street-address\">2300 Valley View Ln #150</span>, <span class=\"locality\">Irving</span>, <span class=\"region\">TX</span> <span class=\"postal-code\">75062</span>, <span class=\"country-name\">USA</span>","formatted_address":"2300 Valley View Ln #150, Irving, TX 75062, USA","formatted_phone_number":"(469) 647-5914","geometry":{"location":{"lat":32.83983589999999,"lng":-97.02083239999999},"viewport":{"northeast":{"lat":32.8410726802915,"lng":-97.01946001970849},"southwest":{"lat":32.8383747197085,"lng":-97.02215798029151}}},"icon":"https://maps.gstatic.com/mapfiles/place_api/icons/v1/png_71/school-71.png","id":null,"international_phone_number":"+1 469-647-5914","name":"ABM Industries","place_id":"ChIJsTpLHIKBToYRaAtrYOc7UrI","rating":2.8,"reference":null,"reviews":[{"author_name":"DT","author_url":"https://www.google.com/maps/contrib/111706885382491558854/reviews","language":"en","profile_photo_url":"https://lh3.googleusercontent.com/a/AATXAJyxy1kmBCdx90bw-ya8Etk47MtMjA3WrKQu4_u8=s128-c0x00000000-cc-rp-mo","rating":1,"relative_time_description":"a month ago","text":"I have an interview here tomorrow but after these reviews I'm scared to go😬","time":1639610040},{"author_name":"Richard Anderson","author_url":"https://www.google.com/maps/contrib/102099525037672421928/reviews","language":"en","profile_photo_url":"https://lh3.googleusercontent.com/a-/AOh14GhmYfukOx_SzTJuGNGttYCyP7xMW7fHoayMlHFerg=s128-c0x00000000-cc-rp-mo","rating":3,"relative_time_description":"a month ago","text":"It's non-stop driving on bus routes.","time":1639599632},{"author_name":"Lamont Taylor","author_url":"https://www.google.com/maps/contrib/114180552043246050201/reviews","language":"en","profile_photo_url":"https://lh3.googleusercontent.com/a/AATXAJzU3wMQU39A5-3-QPqBUS5smU4y_ccWU4rJ69wp=s128-c0x00000000-cc-rp-mo","rating":5,"relative_time_description":"7 months ago","text":"Very friendly people and I will enjoy working there","time":1623371764},{"author_name":"Amanda C","author_url":"https://www.google.com/maps/contrib/106464098680890407341/reviews","language":"en","profile_photo_url":"https://lh3.googleusercontent.com/a-/AOh14GgAq2JqVm6WiDoWAvdySKA-h7EImtyBMy9kUVN7=s128-c0x00000000-cc-rp-mo","rating":1,"relative_time_description":"5 months ago","text":"Down right rude people work for this company.","time":1627755964},{"author_name":"Alexis Harmon","author_url":"https://www.google.com/maps/contrib/101904813653223178881/reviews","language":"en","profile_photo_url":"https://lh3.googleusercontent.com/a/AATXAJw9h81K3gXOjXv8bkVgFNXjrZQ9kt3AMJkAUgvv=s128-c0x00000000-cc-rp-mo","rating":1,"relative_time_description":"a year ago","text":"Not very professional and very disorganized. You will get into a verbal altercation. Looking for another job at this moment . Will not stay to be treated terribly, especially not at this pay rate .","time":1579901797}],"types":["point_of_interest","establishment"],"url":"https://maps.google.com/?cid=12849398551782558568","utc_offset":-360,"vicinity":"2300 Valley View Lane #150, Irving","website":"https://www.abm.com/careers/"},"status":"OK"} | AM16: <span class="street-address">2300 Valley View Ln #150</span>, <span class="locality">Irving</span>, <span class="region">TX</span> <span class="postal-code">75062</span>, <span class="country-name">USA</span> | AN16: (469) 647-5914 | AO16: https://maps.gstatic.com/mapfiles/place_api/icons/v1/png_71/school-71.png | AQ16: +1 469-647-5914 | AR16: point_of_interest,establishment | AS16: -360 | AT16: 2300 Valley View Lane #150, Irving | AU16: https://www.abm.com/careers/ | AV16: 2.8 | AW16: 5
A17: Above All Aviation | E17: 1523 Cook Pl | G17: Santa Barbara | H17: CA | I17: 93117 | J17: US | K17: (805) 683-7575 | L17: http://www.aboveallsba.com/ | M17: SBA | N17: FLT61 | O17: FLT141 | Y17: https://maps.google.com/?cid=5290151183609906946 | AB17: Above All Aviation | AC17: OPERATIONAL | AD17: ChIJm1lhdYI_6YARAkcuG3lkakk | AE17: 1523 Cook Pl, Santa Barbara, CA 93117, USA | AJ17: 34.429697 | AK17: -119.84488 | AL17: {"html_attributions":[],"result":{"address_components":[{"long_name":"1523","short_name":"1523","types":["street_number"]},{"long_name":"Cook Place","short_name":"Cook Pl","types":["route"]},{"long_name":"Santa Barbara","short_name":"Santa Barbara","types":["locality","political"]},{"long_name":"Santa Barbara County","short_name":"Santa Barbara County","types":["administrative_area_level_2","political"]},{"long_name":"California","short_name":"CA","types":["administrative_area_level_1","political"]},{"long_name":"United States","short_name":"US","types":["country","political"]},{"long_name":"93117","short_name":"93117","types":["postal_code"]}],"adr_address":"<span class=\"street-address\">1523 Cook Pl</span>, <span class=\"locality\">Santa Barbara</span>, <span class=\"region\">CA</span> <span class=\"postal-code\">93117</span>, <span class=\"country-name\">USA</span>","formatted_address":"1523 Cook Pl, Santa Barbara, CA 93117, USA","formatted_phone_number":"(805) 683-7575","geometry":{"location":{"lat":34.42969739999999,"lng":-119.8448822},"viewport":{"northeast":{"lat":34.4310578302915,"lng":-119.8439841697085},"southwest":{"lat":34.4283598697085,"lng":-119.8466821302915}}},"icon":"https://maps.gstatic.com/mapfiles/place_api/icons/v1/png_71/school-71.png","id":null,"international_phone_number":"+1 805-683-7575","name":"Above All Aviation","place_id":"ChIJm1lhdYI_6YARAkcuG3lkakk","rating":4.7,"reference":null,"reviews":[{"author_name":"Igor D'Angelo","author_url":"https://www.google.com/maps/contrib/112571911736698558034/reviews","language":"en","profile_photo_url":"https://lh3.googleusercontent.com/a-/AOh14GhO_oh2HZUaPOF49WLXP8ca2f2PKa0aCgxz7kuNBA=s128-c0x00000000-cc-rp-mo-ba2","rating":5,"relative_time_description":"7 months ago","text":"I can't say enough positive things about this flight school. Everyone is simply fantastic, professional and a pleasure to work with. A special 'thank you' to Juliet for being a truly outstanding instructor.","time":1621886254},{"author_name":"Charles Ray","author_url":"https://www.google.com/maps/contrib/112547477137212425213/reviews","language":"en","profile_photo_url":"https://lh3.googleusercontent.com/a-/AOh14Gj3ErdARXdbtbnSr-g6gOovgYDzwQcLasi4TFfkhw=s128-c0x00000000-cc-rp-mo-ba3","rating":5,"relative_time_description":"a year ago","text":"This is where I'm getting my BFR (bi-annual flight review) and they are very thorough and attentive, but they do try to drag out the instruction so you have to pay more, and if you miss a lesson and cancel in advance, they still charge you.","time":1607637775},{"author_name":"Jay Ward","author_url":"https://www.google.com/maps/contrib/116031611364296692863/reviews","language":"en","profile_photo_url":"https://lh3.googleusercontent.com/a-/AOh14GiygULg1KGwKpYwb6tRe87rF_OkpyxUNMWu-3odpA=s128-c0x00000000-cc-rp-mo","rating":5,"relative_time_description":"2 years ago","text":"Above all aviation is amazing! Great staff and great testing center! The owner is very helpful! I can’t say enough good things about the place!","time":1575559986},{"author_name":"Mark S","author_url":"https://www.google.com/maps/contrib/113758101848201964592/reviews","language":"en","profile_photo_url":"https://lh3.googleusercontent.com/a/AATXAJzEDXMGDFVlLIOIO4zEmD6H8GMrPyypaPaTtNtx=s128-c0x00000000-cc-rp-mo","rating":5,"relative_time_description":"a year ago","text":"I wanted to rent an aircraft to take my girlfriend up flying and propose afterwards. Everyone at Above All Aviation were very professional and quick to respond to any questions I had. The aircraft were well maintained and they were very accommodating. I would highly recommend to anyone looking to learn how to fly or rent an aircraft for a few hours to go through Above All Aviation. I will definitely fly through them again.","time":1603729985},{"author_name":"Mitch McCarley","author_url":"https://www.google.com/maps/contrib/106382280856245329971/reviews","language":"en","profile_photo_url":"https://lh3.googleusercontent.com/a-/AOh14Ggye2eDWlO7VFECATvT7WHpa2Nvuf6GSYeezag=s128-c0x00000000-cc-rp-mo-ba2","rating":5,"relative_time_description":"8 months ago","text":"Great scenic flight tour of Santa Barbara and Santa Ynez. Thanks Steve!","time":1618880149}],"types":["university","point_of_interest","establishment"],"url":"https://maps.google.com/?cid=5290151183609906946","utc_offset":-480,"vicinity":"1523 Cook Place, Santa Barbara","website":"http://www.aboveallsba.com/"},"status":"OK"} | AM17: <span class="street-address">1523 Cook Pl</span>, <span class="locality">Santa Barbara</span>, <span class="region">CA</span> <span class="postal-code">93117</span>, <span class="country-name">USA</span> | AN17: (805) 683-7575 | AO17: https://maps.gstatic.com/mapfiles/place_api/icons/v1/png_71/school-71.png | AQ17: +1 805-683-7575 | AR17: university,point_of_interest,establishment | AS17: -480 | AT17: 1523 Cook Place, Santa Barbara | AU17: http://www.aboveallsba.com/ | AV17: 4.7 | AW17: 5
A18: Above and Beyond Aviation | E18: 4309 Emma Browning Ave | G18: Austin | H18: TX | I18: 78719-3327 | J18: US | K18: (512) 766-8359 | L18: https://aboveaviation.com/ | M18: AUS | N18: RENT | O18: FLT61 | Y18: https://maps.google.com/?cid=80889634303685321 | AB18: Above and Beyond Aviation | AC18: OPERATIONAL | AD18: ChIJIzQmlhmxRIYRybKunrFgHwE | AE18: 4309 Emma Browning Ave, Austin, TX 78719, USA | AJ18: 30.18607 | AK18: -97.662526 | AL18: {"html_attributions":[],"result":{"address_components":[{"long_name":"4309","short_name":"4309","types":["street_number"]},{"long_name":"Emma Browning Avenue","short_name":"Emma Browning Ave","types":["route"]},{"long_name":"Austin","short_name":"Austin","types":["locality","political"]},{"long_name":"Travis County","short_name":"Travis County","types":["administrative_area_level_2","political"]},{"long_name":"Texas","short_name":"TX","types":["administrative_area_level_1","political"]},{"long_name":"United States","short_name":"US","types":["country","political"]},{"long_name":"78719","short_name":"78719","types":["postal_code"]},{"long_name":"3327","short_name":"3327","types":["postal_code_suffix"]}],"adr_address":"<span class=\"street-address\">4309 Emma Browning Ave</span>, <span class=\"locality\">Austin</span>, <span class=\"region\">TX</span> <span class=\"postal-code\">78719-3327</span>, <span class=\"country-name\">USA</span>","formatted_address":"4309 Emma Browning Ave, Austin, TX 78719, USA","formatted_phone_number":"(512) 766-8359","geometry":{"location":{"lat":30.1860704,"lng":-97.6625256},"viewport":{"northeast":{"lat":30.18778328029149,"lng":-97.66142906970848},"southwest":{"lat":30.1850853197085,"lng":-97.6641270302915}}},"icon":"https://maps.gstatic.com/mapfiles/place_api/icons/v1/png_71/school-71.png","id":null,"international_phone_number":"+1 512-766-8359","name":"Above and Beyond Aviation","place_id":"ChIJIzQmlhmxRIYRybKunrFgHwE","rating":4.8,"reference":null,"reviews":[{"author_name":"Kate Greenstein","author_url":"https://www.google.com/maps/contrib/102018300703383932413/reviews","language":"en","profile_photo_url":"https://lh3.googleusercontent.com/a-/AOh14Gi6-zl1bjlHxh4IGCM3pkA5CydcdrZp4mBZDvw9xA=s128-c0x00000000-cc-rp-mo","rating":5,"relative_time_description":"3 months ago","text":"I took my discovery flight with Above and Beyond Aviation and it was amazing! Bobbi was incredibly attentive and quick to respond and paired me with Andrew for my first flight. Andrew was AMAZING!!! He was super knowledgable, calm, encouraging, and fun to fly with. I absolutely want to continue flying with them and I'm so stoked I found them. I would definitely recommend!","time":1632587706},{"author_name":"Daniel Zimlich","author_url":"https://www.google.com/maps/contrib/106597409750371044575/reviews","language":"en","profile_photo_url":"https://lh3.googleusercontent.com/a-/AOh14Gi-brD72BPXVV7iusgsAp8BxFaMyJvt4NIO8gyfNbw=s128-c0x00000000-cc-rp-mo","rating":5,"relative_time_description":"a year ago","text":"Shawn T. is a great instructor and the management team is quick to respond to any feedback. Great location, seamless rentals!","time":1599580299},{"author_name":"Ethan Gregerson","author_url":"https://www.google.com/maps/contrib/100815922436897937793/reviews","language":"en","profile_photo_url":"https://lh3.googleusercontent.com/a-/AOh14Gig5XxgzNb6t0Xtxw2FEb5UQ1g31uzAkFhVGufs=s128-c0x00000000-cc-rp-mo","rating":5,"relative_time_description":"9 months ago","text":"This has got to be one of the best flight schools out there. If you're in the Austin Area, this is the one to choose. I have not done training with them yet due to an unforeseen issue with my Medical, but I'll write based on my experience leading up to this point.\n\nFirst of all, their communication is unmatched. I've never had a better experience with any other business I've worked with. They reply in a very timely manner, answer all of your questions, send detailed and clear instructions for everything leading up to your first flight. I don't think the process could have been easier.\n\nI booked a discovery flight with them and my instructor, Andrew, reached out to me separately, and gave me all the information regarding the flight upcoming. He was extremely responsive, and answered all the questions I had for him. I arrived to the airport the day of my discovery flight, and Andrew was right there to greet me. He did a great job walking me through what we were doing on the flight, and he was once again always happy to answer my questions. We walked out and preflighted the aircraft, hopped in and taxied to the runway. That's where we we're cleared for takeoff, and he let me take off myself on my first flight, which was definitely an experience I'll never forget. After flying around the city for some time and performing a few basic maneuvers (all of which I was at the controls of the majority of the time) we headed back to the airport and landed. Afterwards, we went and chatted about training and parted ways.\n\nAs the time came to start training, unfortunately complications arose with my medical exam that grounded me. I reached out to Bobbi to let her know what happened, and she could not have been better. She wrote me a long and caring email, giving me all the information I needed to move forward, and made an effort to connect me with people who have gone through similar situations, which was extremely comforting. She quite literally went \"above and beyond\" what she needed to and as a consumer there is nothing that I could have imagined going better.\n\nAs a 16 year old trying to figure out my passion, and trying to pave my own path to pursue my dreams of being a pilot, the process of becoming a pilot can be confusing and very intimidating, and nobody could have done better to be there to answer my questions and help me along every step of my journey so far than Above and Beyond, and I have absolutely no doubt that will continue to be the case as I move forward with this journey.\n\nThanks and thank you again to everyone at above and beyond for being so awesome. If you're thinking about working with them, I'd highly recommend them!!","time":1617718271},{"author_name":"Charles Toothaker","author_url":"https://www.google.com/maps/contrib/104493300870962970955/reviews","language":"en","profile_photo_url":"https://lh3.googleusercontent.com/a/AATXAJwcj3_0SbLIYOugC0fnToXJYAWVn9GNp1oV_5br=s128-c0x00000000-cc-rp-mo","rating":5,"relative_time_description":"a year ago","text":"I started my PPL training with Above & Beyond in December 2019 and passed my check ride early July 2020 (with two months off due to the Covid shutdown). I had some past training from a few years prior in a 150 but transitioned to the 172 at Above & Beyond.\n\nI did my training with Mike, who was an excellent instructor and gave me confidence in flying the airplane. Lesson times were very flexible. I did most of my training on the weekends or after 4PM during the week.","time":1594655189},{"author_name":"Cole DeGroat","author_url":"https://www.google.com/maps/contrib/114209462965656627982/reviews","language":"en","profile_photo_url":"https://lh3.googleusercontent.com/a/AATXAJxCasGKDbPv4fktJiL0QAx3CPrH0MaFfcCPRuz3=s128-c0x00000000-cc-rp-mo","rating":4,"relative_time_description":"a year ago","text":"I started my private pilot training at Above and Beyond Aviation last summer, and it was essentially where I learned to fly. I trained with Jeff Uskert a CFI out of here, who also took me on my discovery flight and cemented my attraction to aviation. Jeff was a kind, easy to communicate with instructor, and you can tell he truly cares about his students and their success. I did not finish my PPL in Austin, however I still communicate and chat with Jeff quite regularly. One point of emphasis he also was keen on was safety and doing things the right way. Jeff was truly a great instructor and I still regret to this day not finishing my license with him. As far as the aircraft and airport were concerned, AUS is quite the busy field which can induce challenges and benefits to trianing. The planes were typically well kept and maintained as best as could be expected. The administrative side of things and scheduling also went quite smoothly.","time":1601936370}],"types":["university","point_of_interest","establishment"],"url":"https://maps.google.com/?cid=80889634303685321","utc_offset":-360,"vicinity":"4309 Emma Browning Avenue, Austin","website":"https://aboveaviation.com/"},"status":"OK"} | AM18: <span class="street-address">4309 Emma Browning Ave</span>, <span class="locality">Austin</span>, <span class="region">TX</span> <span class="postal-code">78719-3327</span>, <span class="country-name">USA</span> | AN18: (512) 766-8359 | AO18: https://maps.gstatic.com/mapfiles/place_api/icons/v1/png_71/school-71.png | AQ18: +1 512-766-8359 | AR18: university,point_of_interest,establishment | AS18: -360 | AT18: 4309 Emma Browning Avenue, Austin | AU18: https://aboveaviation.com/ | AV18: 4.8 | AW18: 5
A19: Above it All Aviation | E19: 5025 Voyager Dr | G19: Dallas | H19: TX | I19: 75237 | J19: US | K19: (214) 402-9916 | L19: http://www.flyaboveitall.com/ | M19: RBD | N19: FLT61 | Y19: https://maps.google.com/?cid=12299055521669472541 | AB19: Above it All Aviation | AC19: OPERATIONAL | AD19: ChIJg_AFqlIhTIYRHWHqcdUFr6o | AE19: 5025 Voyager Dr, Dallas, TX 75237, USA | AJ19: 32.683745 | AK19: -96.865098 | AL19: {"html_attributions":[],"result":{"address_components":[{"long_name":"5025","short_name":"5025","types":["street_number"]},{"long_name":"Voyager Drive","short_name":"Voyager Dr","types":["route"]},{"long_name":"Oak Cliff","short_name":"Oak Cliff","types":["neighborhood","political"]},{"long_name":"Dallas","short_name":"Dallas","types":["locality","political"]},{"long_name":"Dallas County","short_name":"Dallas County","types":["administrative_area_level_2","political"]},{"long_name":"Texas","short_name":"TX","types":["administrative_area_level_1","political"]},{"long_name":"United States","short_name":"US","types":["country","political"]},{"long_name":"75237","short_name":"75237","types":["postal_code"]}],"adr_address":"<span class=\"street-address\">5025 Voyager Dr</span>, <span class=\"locality\">Dallas</span>, <span class=\"region\">TX</span> <span class=\"postal-code\">75237</span>, <span class=\"country-name\">USA</span>","formatted_address":"5025 Voyager Dr, Dallas, TX 75237, USA","formatted_phone_number":"(214) 402-9916","geometry":{"location":{"lat":32.6837447,"lng":-96.8650984},"viewport":{"northeast":{"lat":32.6851016802915,"lng":-96.8635000697085},"southwest":{"lat":32.6824037197085,"lng":-96.8661980302915}}},"icon":"https://maps.gstatic.com/mapfiles/place_api/icons/v1/png_71/school-71.png","id":null,"international_phone_number":"+1 214-402-9916","name":"Above it All Aviation","place_id":"ChIJg_AFqlIhTIYRHWHqcdUFr6o","rating":4.3,"reference":null,"reviews":[{"author_name":"Brooks Johnson","author_url":"https://www.google.com/maps/contrib/116244307001096183975/reviews","language":"en","profile_photo_url":"https://lh3.googleusercontent.com/a-/AOh14GhkZmJdrCxoidVCft4rjlO3pCZwYCfj80VipYcwmA=s128-c0x00000000-cc-rp-mo","rating":5,"relative_time_description":"9 months ago","text":"Flew with Torrey and Aidan, some fantastic CFIIs, and earned my PPL. Looking forward to working with them on my Instrument next! Awesome value, tailored courses to meet your timeline/skill and all under part 61... can’t be beat in DFW.","time":1617115667},{"author_name":"Paul Voorhies","author_url":"https://www.google.com/maps/contrib/110972449144920444992/reviews","language":"en","profile_photo_url":"https://lh3.googleusercontent.com/a/AATXAJyQAGz7iViIBd68Q40Dhl2XDMvfhTYIWXogScHI=s128-c0x00000000-cc-rp-mo","rating":5,"relative_time_description":"a year ago","text":"Great place and excellent communication. Just earned my Instrument Rating with Above it All Aviation. I had transferred from another school where I felt like my instructor and the school were just trying to make money off me. Above it All really came through and showed me the areas I needed to work on. And bam! 2 months later I was done!! Thank you so much!!","time":1603492378},{"author_name":"Robert Thomas","author_url":"https://www.google.com/maps/contrib/104159181040462550699/reviews","language":"en","profile_photo_url":"https://lh3.googleusercontent.com/a/AATXAJyadvgSGPimcPc_3OmRnl-ZMymDcr6aJfaswZRR=s128-c0x00000000-cc-rp-mo","rating":5,"relative_time_description":"a year ago","text":"Great school! I really enjoyed the personal attention they showed us. Both my wife and I recently earned our license through Above it All Aviation and are sure excited about new adventure together.","time":1603490963},{"author_name":"Ayodele Fadahunsi","author_url":"https://www.google.com/maps/contrib/110931819384142783155/reviews","language":"en","profile_photo_url":"https://lh3.googleusercontent.com/a/AATXAJxt-GF97pYUzJuQSX1lKxlCiZ4APyT7kZj3zR1B=s128-c0x00000000-cc-rp-mo","rating":1,"relative_time_description":"2 years ago","text":"Impossible to schedule a session. I was given a gift certificate for a flight lesson on 09/6/19 which expired on 12/31/19 despite multiple attempts on my part to book a session throughout the 4 months. If you call the number, you may or may not get text message response from Above it All 1-2 weeks later. I am trying to figure out how to get a refund ordered on behalf of PCI Pharmacy who awarded me the gift certificate because Above it All Aviation has clearly stolen money from them.","time":1578163127},{"author_name":"Blake Brininstool","author_url":"https://www.google.com/maps/contrib/114179981903016217886/reviews","language":null,"profile_photo_url":"https://lh3.googleusercontent.com/a/AATXAJztJG1dXN_IzncdnxX8o43xPyjHV-T9lNWYM72D=s128-c0x00000000-cc-rp-mo-ba3","rating":5,"relative_time_description":"11 months ago","text":"","time":1611959656}],"types":["university","point_of_interest","establishment"],"url":"https://maps.google.com/?cid=12299055521669472541","utc_offset":-360,"vicinity":"5025 Voyager Drive, Dallas","website":"http://www.flyaboveitall.com/"},"status":"OK"} | AM19: <span class="street-address">5025 Voyager Dr</span>, <span class="locality">Dallas</span>, <span class="region">TX</span> <span class="postal-code">75237</span>, <span class="country-name">USA</span> | AN19: (214) 402-9916 | AO19: https://maps.gstatic.com/mapfiles/place_api/icons/v1/png_71/school-71.png | AQ19: +1 214-402-9916 | AR19: university,point_of_interest,establishment | AS19: -360 | AT19: 5025 Voyager Drive, Dallas | AU19: http://www.flyaboveitall.com/ | AV19: 4.3 | AW19: 5
A20: ABOVE Private Aviation | E20: 433 Plaza Real | F20: Suite 275 | G20: Boca Raton | H20: FL | I20: 33432 | J20: US | K20: (855) 755-5387 | L20: http://www.iflyabove.com/ | M20: BCT | N20: P135 | Y20: https://maps.google.com/?cid=7006606555665585425 | AB20: ABOVE Private Aviation | AC20: OPERATIONAL | AD20: ChIJJ4KKi7jj2IgREdVeL4p3PGE | AE20: 433 Plaza Real Suite 275, Boca Raton, FL 33432, USA | AJ20: 26.355441 | AK20: -80.085721 | AL20: {"html_attributions":[],"result":{"address_components":[{"long_name":"Suite 275","short_name":"Suite 275","types":["subpremise"]},{"long_name":"433","short_name":"433","types":["street_number"]},{"long_name":"Plaza Real","short_name":"Plaza Real","types":["route"]},{"long_name":"Boca Raton","short_name":"Boca Raton","types":["locality","political"]},{"long_name":"Palm Beach County","short_name":"Palm Beach County","types":["administrative_area_level_2","political"]},{"long_name":"Florida","short_name":"FL","types":["administrative_area_level_1","political"]},{"long_name":"United States","short_name":"US","types":["country","political"]},{"long_name":"33432","short_name":"33432","types":["postal_code"]}],"adr_address":"<span class=\"street-address\">433 Plaza Real Suite 275</span>, <span class=\"locality\">Boca Raton</span>, <span class=\"region\">FL</span> <span class=\"postal-code\">33432</span>, <span class=\"country-name\">USA</span>","formatted_address":"433 Plaza Real Suite 275, Boca Raton, FL 33432, USA","formatted_phone_number":"(855) 755-5387","geometry":{"location":{"lat":26.355441,"lng":-80.0857209},"viewport":{"northeast":{"lat":26.3567679302915,"lng":-80.08421591970848},"southwest":{"lat":26.3540699697085,"lng":-80.08691388029149}}},"icon":"https://maps.gstatic.com/mapfiles/place_api/icons/v1/png_71/generic_business-71.png","id":null,"international_phone_number":"+1 855-755-5387","name":"ABOVE Private Aviation","place_id":"ChIJJ4KKi7jj2IgREdVeL4p3PGE","rating":5.0,"reference":null,"reviews":[{"author_name":"Cornelia ( Nina) Bonnie","author_url":"https://www.google.com/maps/contrib/113986243055229746582/reviews","language":"en","profile_photo_url":"https://lh3.googleusercontent.com/a/AATXAJwiqy132QuN9WV51xXOv2X9JnKCDH4y3pmfQ0Zu=s128-c0x00000000-cc-rp-mo","rating":5,"relative_time_description":"a month ago","text":"My son and i had to make a quick trip which included tight schedule and deadlines. The flight was perfect. we were meet by a driver who delivered us on time and was there to get us back to the Airport. PERFECT TRIP FROM BEGINNING TO END! WOW!","time":1636595737},{"author_name":"Lisa Berger","author_url":"https://www.google.com/maps/contrib/111351709687234465714/reviews","language":"en","profile_photo_url":"https://lh3.googleusercontent.com/a/AATXAJx7aKKUPOMDMcfbTEwOGMramUQasbIncg5yuC-2=s128-c0x00000000-cc-rp-mo","rating":5,"relative_time_description":"11 months ago","text":"First class service from start to finish! David Hammer went ABOVE and beyond to create a stress-free and memorable experience with every flight!\n\nAmidst the pandemic, we were referred to David to help my parents charter private flights between FL and NJ. He was extremely helpful and provided my parents with outstanding service, safety and comfort.\n\nSo when I decided - at the last minute - to surprise my parents for my father's milestone birthday in January, I knew that David was the only person to call to fly my family comfortably and safely to FL. David's service was second to none, and the flight crew was fantastic. The 'downside' is that now my 9 and 13 year old children only want to fly private!! :)\n\nI highly recommend David and ABOVE Private Aviation to anyone looking for incredible service, convenience and truly stress-free travel...","time":1612392211},{"author_name":"Jeff Sussman","author_url":"https://www.google.com/maps/contrib/115848641663618254346/reviews","language":"en","profile_photo_url":"https://lh3.googleusercontent.com/a/AATXAJw7q0gp_4R_R1jpVevAltFKZv-4MPH14JkAa148=s128-c0x00000000-cc-rp-mo","rating":5,"relative_time_description":"7 months ago","text":"I Fly Above rocks!!!! The absolute best experience from initial wheels up. David is a pro and couldn't do enough to make every detail of our trip perfect. I will absolutely be using his services again.","time":1623271288},{"author_name":"Linda Neal","author_url":"https://www.google.com/maps/contrib/116319815157669408927/reviews","language":"en","profile_photo_url":"https://lh3.googleusercontent.com/a/AATXAJwgkgFGWYlmC8Lya8ewg7J6mG_MK_4DV6oMPCP9=s128-c0x00000000-cc-rp-mo","rating":5,"relative_time_description":"5 months ago","text":"We had to fly private as it was the only way to get our dogs to the States with covid restrictions unless we flew them cargo which we didn’t want to do.\nDavid at Above private aviation made everything very easy and we and the dogs thouroughly enjoyed the flight.\nGoing to be difficult to go back to commercial!","time":1626460105},{"author_name":"Carol Medley","author_url":"https://www.google.com/maps/contrib/109438622958394995312/reviews","language":"en","profile_photo_url":"https://lh3.googleusercontent.com/a/AATXAJyKimSUQ3XmfgsZ1tRYqzZgx5S44csZhqxRZx_Q=s128-c0x00000000-cc-rp-mo","rating":5,"relative_time_description":"10 months ago","text":"Working with David Hammer is a pleasure from start to finish. He is a very professional and really knows what he is doing. He always presents several options and always manages to get the best prices, so there is no reason to look elsewhere. He is my go to guy for private aviation!","time":1615753044}],"types":["travel_agency","point_of_interest","establishment"],"url":"https://maps.google.com/?cid=7006606555665585425","utc_offset":-300,"vicinity":"433 Plaza Real Suite 275, Boca Raton","website":"http://www.iflyabove.com/"},"status":"OK"} | AM20: <span class="street-address">433 Plaza Real Suite 275</span>, <span class="locality">Boca Raton</span>, <span class="region">FL</span> <span class="postal-code">33432</span>, <span class="country-name">USA</span> | AN20: (855) 755-5387 | AO20: https://maps.gstatic.com/mapfiles/place_api/icons/v1/png_71/generic_business-71.png | AQ20: +1 855-755-5387 | AR20: travel_agency,point_of_interest,establishment | AS20: -300 | AT20: 433 Plaza Real Suite 275, Boca Raton | AU20: http://www.iflyabove.com/ | AV20: 5 | AW20: 5
A21: Absolute Aero Maintenance | E21: 21889 Skywest Dr | G21: Hayward | H21: CA | I21: 94541-7021 | J21: US | K21: (510) 782-6591 | L21: http://www.absolute-aero.com/ | M21: HWD | N21: APIA | Y21: https://maps.google.com/?cid=12855017089275632239 | AB21: Absolute Aero Maintenance | AD21: ChIJ9yMNHxeRj4ARb5rZE-8xZrI | AE21: 21889 Skywest Dr, Hayward, CA 94541, USA | AJ21: 37.66019 | AK21: -122.11651 | AL21: {"html_attributions":[],"result":{"address_components":[{"long_name":"21889","short_name":"21889","types":["street_number"]},{"long_name":"Skywest Drive","short_name":"Skywest Dr","types":["route"]},{"long_name":"Hayward","short_name":"Hayward","types":["locality","political"]},{"long_name":"Alameda County","short_name":"Alameda County","types":["administrative_area_level_2","political"]},{"long_name":"California","short_name":"CA","types":["administrative_area_level_1","political"]},{"long_name":"United States","short_name":"US","types":["country","political"]},{"long_name":"94541","short_name":"94541","types":["postal_code"]},{"long_name":"7021","short_name":"7021","types":["postal_code_suffix"]}],"adr_address":"<span class=\"street-address\">21889 Skywest Dr</span>, <span class=\"locality\">Hayward</span>, <span class=\"region\">CA</span> <span class=\"postal-code\">94541-7021</span>, <span class=\"country-name\">USA</span>","formatted_address":"21889 Skywest Dr, Hayward, CA 94541, USA","formatted_phone_number":"(510) 782-6591","geometry":{"location":{"lat":37.6601898,"lng":-122.1165115},"viewport":{"northeast":{"lat":37.66133463029149,"lng":-122.1149261197085},"southwest":{"lat":37.65863666970849,"lng":-122.1176240802915}}},"icon":"https://maps.gstatic.com/mapfiles/place_api/icons/v1/png_71/generic_business-71.png","id":null,"international_phone_number":"+1 510-782-6591","name":"Absolute Aero Maintenance","place_id":"ChIJ9yMNHxeRj4ARb5rZE-8xZrI","rating":4.7,"reference":null,"reviews":[{"author_name":"Joel Stephens","author_url":"https://www.google.com/maps/contrib/107477045899324900744/reviews","language":"en","profile_photo_url":"https://lh3.googleusercontent.com/a-/AOh14GgMBB1MidmRhP1Yhfm35DLzyfDmaFCkXIcK_Fv3VQ=s128-c0x00000000-cc-rp-mo-ba5","rating":5,"relative_time_description":"8 months ago","text":"Awesome team of mechanics here. They are detail oriented and are more concerned with doing it right than just getting planes in and out. After my last service was done they let me know that I should go fly a bit and they wanted me to come back just so they could do a double check. Even if nothing was wrong they just wanted to give it one last look to make sure it was right. That speaks really highly to their commitment to quality. Thanks guys, N86SK.","time":1619620501},{"author_name":"Henry Telfeian","author_url":"https://www.google.com/maps/contrib/117795143929812003016/reviews","language":"en","profile_photo_url":"https://lh3.googleusercontent.com/a/AATXAJzphpzCIjdv_qh20rIBMsnwGManEI2v-FJCTP6b=s128-c0x00000000-cc-rp-mo","rating":5,"relative_time_description":"a year ago","text":"I have been using Absolute Aero for seven years and have never been disappointed in the quality of their work, their thoroughness, or how quickly they respond to my needs. When minor issues come up, they readily come over to the hangar to check things out and get me on my way. They have always completed my annuals as well as replacing all six cylinders. I have complete confidence in the work they perform and would recommend them to any pilot. Matt and Brandon are a real pleasure to work with and a great find.","time":1604969983},{"author_name":"Kareem Fahmi","author_url":"https://www.google.com/maps/contrib/116071957509732527614/reviews","language":"en","profile_photo_url":"https://lh3.googleusercontent.com/a-/AOh14GjDKil-9VZrv1W3qvytaEkNdNpn_EZEKs3ZfM-s3Q=s128-c0x00000000-cc-rp-mo-ba3","rating":5,"relative_time_description":"a year ago","text":"I've trusted Absolute with all of my aircraft maintenance needs for the past 7 years, including annuals and a complete engine removal and reinstall.. Matt, Brandon, and their staff are simply awesome. They're extremely honest, detail-oriented, responsive, affordable, and trustworthy. Basically, everything you'd want in an aircraft maintenance shop. General aviation needs more places like Absolute Aero.","time":1603839221},{"author_name":"Andrew Segal","author_url":"https://www.google.com/maps/contrib/107426208208067348281/reviews","language":"en","profile_photo_url":"https://lh3.googleusercontent.com/a/AATXAJymJ9ybSWGoHYzdA7GaafH6f8uEx6ctO9ir2t7P=s128-c0x00000000-cc-rp-mo","rating":5,"relative_time_description":"a year ago","text":"Matt and Brandon routinely go above and beyond. Beyond bringing their highly competent skills to bear on the DA40NG, they have worked hard to accommodate schedules around training and check rides for two individual pilots pursuing ratings this year. Highly recommend!","time":1605555424},{"author_name":"Tim Prachar","author_url":"https://www.google.com/maps/contrib/117788246274198114516/reviews","language":"en","profile_photo_url":"https://lh3.googleusercontent.com/a-/AOh14Gi_uYiIkNZAvMjqZCosW0ij4-qh69YX_JqouJJJN5M=s128-c0x00000000-cc-rp-mo-ba3","rating":5,"relative_time_description":"3 months ago","text":"Worth flying across the bay for!","time":1632349922}],"types":["point_of_interest","establishment"],"url":"https://maps.google.com/?cid=12855017089275632239","utc_offset":-480,"vicinity":"21889 Skywest Drive, Hayward","website":"http://www.absolute-aero.com/"},"status":"OK"} | AM21: <span class="street-address">21889 Skywest Dr</span>, <span class="locality">Hayward</span>, <span class="region">CA</span> <span class="postal-code">94541-7021</span>, <span class="country-name">USA</span> | AN21: (510) 782-6591 | AO21: https://maps.gstatic.com/mapfiles/place_api/icons/v1/png_71/generic_business-71.png | AQ21: +1 510-782-6591 | AR21: point_of_interest,establishment | AS21: -480 | AT21: 21889 Skywest Drive, Hayward | AU21: http://www.absolute-aero.com/ | AV21: 4.7 | AW21: 5
A22: AC Air Technology | E22: 13832 Magnolia Ave | G22: Chino | H22: CA | I22: 91710-7027 | J22: US | K22: (855) 884-7222 | L22: https://acairtechnology.com/ | M22: CNO | N22: GSERT | Y22: https://maps.google.com/?cid=1403520538580697814 | AB22: AC Air Technology | AC22: OPERATIONAL | AD22: ChIJN0D6oMzM3IAR1kIRYX5OehM | AE22: 13832 Magnolia Ave, Chino, CA 91710, USA | AJ22: 34.002028 | AK22: -117.67296 | AL22: {"html_attributions":[],"result":{"address_components":[{"long_name":"13832","short_name":"13832","types":["street_number"]},{"long_name":"Magnolia Avenue","short_name":"Magnolia Ave","types":["route"]},{"long_name":"Chino","short_name":"Chino","types":["locality","political"]},{"long_name":"San Bernardino County","short_name":"San Bernardino County","types":["administrative_area_level_2","political"]},{"long_name":"California","short_name":"CA","types":["administrative_area_level_1","political"]},{"long_name":"United States","short_name":"US","types":["country","political"]},{"long_name":"91710","short_name":"91710","types":["postal_code"]},{"long_name":"7027","short_name":"7027","types":["postal_code_suffix"]}],"adr_address":"<span class=\"street-address\">13832 Magnolia Ave</span>, <span class=\"locality\">Chino</span>, <span class=\"region\">CA</span> <span class=\"postal-code\">91710-7027</span>, <span class=\"country-name\">USA</span>","formatted_address":"13832 Magnolia Ave, Chino, CA 91710, USA","formatted_phone_number":"(855) 884-7222","geometry":{"location":{"lat":34.002028,"lng":-117.672962},"viewport":{"northeast":{"lat":34.0035179802915,"lng":-117.6716225197085},"southwest":{"lat":34.0008200197085,"lng":-117.6743204802915}}},"icon":"https://maps.gstatic.com/mapfiles/place_api/icons/v1/png_71/generic_business-71.png","id":null,"international_phone_number":"+1 855-884-7222","name":"AC Air Technology","place_id":"ChIJN0D6oMzM3IAR1kIRYX5OehM","rating":5.0,"reference":null,"reviews":[{"author_name":"John Godfrey","author_url":"https://www.google.com/maps/contrib/112425945923068879511/reviews","language":"en","profile_photo_url":"https://lh3.googleusercontent.com/a-/AOh14GgNG_rdaVw79q5QOL8bBma4pkfvv6O3aW6VtJPJ=s128-c0x00000000-cc-rp-mo","rating":5,"relative_time_description":"3 weeks ago","text":"After years with various gasoline powered tugs and some experience with a \"stick steer\" electric tug, I managed to buy a very early, used AC Air T-1 tug. Not only is the tug a wonder to behold but because of age and previous heavy use, I have had the chance to interact with AC for problem solving. They are great! The tug and the company are to be commended. My tug is 10 years old and it works as well as when I got it, thanks to the ingenious design and the availability of new batteries, new treads and the help/support in updating.","time":1639600767},{"author_name":"Jay Curtis","author_url":"https://www.google.com/maps/contrib/112356198271605293747/reviews","language":"en","profile_photo_url":"https://lh3.googleusercontent.com/a-/AOh14Giebj8NrqhDzD9nTYRU4BBEl6e1rwxYgONjmiD8=s128-c0x00000000-cc-rp-mo","rating":5,"relative_time_description":"a month ago","text":"This machine saved my back and allowed me to bet another plane in my hangar safely. Being able to spot your own wings and tail is a huge benefit. The customer service has always been fantastic . Even the small\nOne will tow a citation","time":1637867109},{"author_name":"Miguel Nelson","author_url":"https://www.google.com/maps/contrib/117344570145788283338/reviews","language":"en","profile_photo_url":"https://lh3.googleusercontent.com/a-/AOh14Gh67bQmRat4m-PL3OtsOdgOTCvTlgx-VRSHYK4VHQ=s128-c0x00000000-cc-rp-mo","rating":5,"relative_time_description":"a month ago","text":"I purchased the T1X2 tug earlier this year, for my 1943 Howard DGA-15P. Andy and his company have built an outstanding product, with great customer service. Being able to walk alongside, vice looking over my shoulder with a driving tug, while precisely controlling the aircraft parking among 3 other planes in my hangar is a godsend. The tug had been bulletproof thus far, and is worth every penny.","time":1637952403},{"author_name":"Marla Boone","author_url":"https://www.google.com/maps/contrib/116884840950516188152/reviews","language":"en","profile_photo_url":"https://lh3.googleusercontent.com/a-/AOh14Ggs4npnTnPPrhoXjKxZ7oV3qy7tkxp5NJL3Fk2C=s128-c0x00000000-cc-rp-mo","rating":5,"relative_time_description":"a month ago","text":"Customer service is the best. Britney was great when I ordered. When the shipping company lost track of the shipment, she launched an investigation and the tug showed up very shortly. The tug itself is a wonder. My WACO is over 2,000 pounds and it hauls it around no trouble at all.","time":1637864749},{"author_name":"Bill Kalivas","author_url":"https://www.google.com/maps/contrib/102186425061435892829/reviews","language":"en","profile_photo_url":"https://lh3.googleusercontent.com/a/AATXAJxxktP4EYL83zzbrl-bUBJc3v3OZQ1WW8lME46_=s128-c0x00000000-cc-rp-mo","rating":5,"relative_time_description":"a month ago","text":"This is the best \"upgrade\" you can give yourself... I have a C180 that this tug makes ground handling a breeze. It's as cool a toy you can have as well. Highly recommend it..","time":1637936912}],"types":["point_of_interest","establishment"],"url":"https://maps.google.com/?cid=1403520538580697814","utc_offset":-480,"vicinity":"13832 Magnolia Avenue, Chino","website":"https://acairtechnology.com/"},"status":"OK"} | AM22: <span class="street-address">13832 Magnolia Ave</span>, <span class="locality">Chino</span>, <span class="region">CA</span> <span class="postal-code">91710-7027</span>, <span class="country-name">USA</span> | AN22: (855) 884-7222 | AO22: https://maps.gstatic.com/mapfiles/place_api/icons/v1/png_71/generic_business-71.png | AQ22: +1 855-884-7222 | AR22: point_of_interest,establishment | AS22: -480 | AT22: 13832 Magnolia Avenue, Chino | AU22: https://acairtechnology.com/ | AV22: 5 | AW22: 5
A23: ACA Aviation Clean Air | E23: 123 Westside Blvd | G23: Pooler | H23: GA | I23: 31322 | J23: US | K23: (912) 401-0335 | L23: http://www.aviationcleanair.com/ | M23: SAV | N23: DINF | Y23: https://maps.google.com/?cid=3338497463369072360 | AB23: ACA Aviation Clean Air | AC23: OPERATIONAL | AD23: ChIJzX6Ovhqh-4gR6P6nO8G5VC4 | AE23: 123 Westside Blvd, Pooler, GA 31322, USA | AJ23: 32.106785 | AK23: -81.220007 | AL23: {"html_attributions":[],"result":{"address_components":[{"long_name":"123","short_name":"123","types":["street_number"]},{"long_name":"Westside Boulevard","short_name":"Westside Blvd","types":["route"]},{"long_name":"Pooler","short_name":"Pooler","types":["locality","political"]},{"long_name":"Chatham County","short_name":"Chatham County","types":["administrative_area_level_2","political"]},{"long_name":"Georgia","short_name":"GA","types":["administrative_area_level_1","political"]},{"long_name":"United States","short_name":"US","types":["country","political"]},{"long_name":"31322","short_name":"31322","types":["postal_code"]}],"adr_address":"<span class=\"street-address\">123 Westside Blvd</span>, <span class=\"locality\">Pooler</span>, <span class=\"region\">GA</span> <span class=\"postal-code\">31322</span>, <span class=\"country-name\">USA</span>","formatted_address":"123 Westside Blvd, Pooler, GA 31322, USA","formatted_phone_number":"(912) 401-0335","geometry":{"location":{"lat":32.106785,"lng":-81.220007},"viewport":{"northeast":{"lat":32.1078974802915,"lng":-81.21874281970851},"southwest":{"lat":32.1051995197085,"lng":-81.22144078029152}}},"icon":"https://maps.gstatic.com/mapfiles/place_api/icons/v1/png_71/generic_business-71.png","id":null,"international_phone_number":"+1 912-401-0335","name":"ACA Aviation Clean Air","place_id":"ChIJzX6Ovhqh-4gR6P6nO8G5VC4","rating":null,"reference":null,"reviews":null,"types":["point_of_interest","establishment"],"url":"https://maps.google.com/?cid=3338497463369072360","utc_offset":-300,"vicinity":"123 Westside Boulevard, Pooler","website":"http://www.aviationcleanair.com/"},"status":"OK"} | AM23: <span class="street-address">123 Westside Blvd</span>, <span class="locality">Pooler</span>, <span class="region">GA</span> <span class="postal-code">31322</span>, <span class="country-name">USA</span> | AN23: (912) 401-0335 | AO23: https://maps.gstatic.com/mapfiles/place_api/icons/v1/png_71/generic_business-71.png | AQ23: +1 912-401-0335 | AR23: point_of_interest,establishment | AS23: -300 | AT23: 123 Westside Boulevard, Pooler | AU23: http://www.aviationcleanair.com/
A24: Academy of Aviation | E24: 7150 Republic Airport | F24: # 101 | G24: Farmingdale | H24: NY | I24: 11735-3999 | J24: US | K24: (516) 613-4556 | L24: https://www.academyofaviation.com/ | M24: FRG | N24: FLT141 | Y24: https://maps.google.com/?cid=2855351368674333751 | AB24: Academy of Aviation | AC24: OPERATIONAL | AD24: ChIJ8yi6gNkq6IkRN1TCBvE-oCc | AE24: 7150 Republic Airport # 101, Farmingdale, NY 11735, USA | AJ24: 40.726179 | AK24: -73.416788 | AL24: {"html_attributions":[],"result":{"address_components":[{"long_name":"# 101","short_name":"# 101","types":["subpremise"]},{"long_name":"7150","short_name":"7150","types":["street_number"]},{"long_name":"Republic Airport","short_name":"Republic Airport","types":["route"]},{"long_name":"Farmingdale","short_name":"Farmingdale","types":["locality","political"]},{"long_name":"Babylon","short_name":"Babylon","types":["administrative_area_level_3","political"]},{"long_name":"Suffolk County","short_name":"Suffolk County","types":["administrative_area_level_2","political"]},{"long_name":"New York","short_name":"NY","types":["administrative_area_level_1","political"]},{"long_name":"United States","short_name":"US","types":["country","political"]},{"long_name":"11735","short_name":"11735","types":["postal_code"]},{"long_name":"3999","short_name":"3999","types":["postal_code_suffix"]}],"adr_address":"<span class=\"street-address\">7150 Republic Airport # 101</span>, <span class=\"locality\">Farmingdale</span>, <span class=\"region\">NY</span> <span class=\"postal-code\">11735-3999</span>, <span class=\"country-name\">USA</span>","formatted_address":"7150 Republic Airport # 101, Farmingdale, NY 11735, USA","formatted_phone_number":"(516) 613-4556","geometry":{"location":{"lat":40.72617939999999,"lng":-73.4167882},"viewport":{"northeast":{"lat":40.72752838029149,"lng":-73.4154392197085},"southwest":{"lat":40.72483041970849,"lng":-73.41813718029151}}},"icon":"https://maps.gstatic.com/mapfiles/place_api/icons/v1/png_71/school-71.png","id":null,"international_phone_number":"+1 516-613-4556","name":"Academy of Aviation","place_id":"ChIJ8yi6gNkq6IkRN1TCBvE-oCc","rating":4.6,"reference":null,"reviews":[{"author_name":"Joey Adflow","author_url":"https://www.google.com/maps/contrib/114448965142366331917/reviews","language":"en","profile_photo_url":"https://lh3.googleusercontent.com/a/AATXAJzd3WfYhZ8kb3TtYuW9sm-5ZdKYZMo9MaQlbwdT=s128-c0x00000000-cc-rp-mo","rating":1,"relative_time_description":"2 months ago","text":"This isn't a school its a business. They pay their instructions minimum wage who show up to the job just because they need their requirement hours. They aren't 'teachers' they are simply showing up.\n\nThe will rope you into a contract that they refuse to let you out of, and keep your money if you ask for a refund.\n\nThere are much better, and cheaper options when it comes to flight lessons. I do not recommend.","time":1635163071},{"author_name":"Hari Govind","author_url":"https://www.google.com/maps/contrib/102675063856226315259/reviews","language":"en","profile_photo_url":"https://lh3.googleusercontent.com/a-/AOh14GiYJd5VIe5v0V6MsRAtdlTIxl6nEaPz87PY3rnNrA=s128-c0x00000000-cc-rp-mo","rating":5,"relative_time_description":"11 months ago","text":"Now getting the information ☺️☺️👍🏻😊😊😊","time":1611602646},{"author_name":"jay","author_url":"https://www.google.com/maps/contrib/113669293330529162716/reviews","language":"en","profile_photo_url":"https://lh3.googleusercontent.com/a-/AOh14GhJqFnPqLIwS9MyS0RN9kHZLe5ot14_-xI7n2SMng=s128-c0x00000000-cc-rp-mo","rating":5,"relative_time_description":"a year ago","text":"Nice place and aviation school in New York to success as a pilot. I went for a discovery flight with my cousin and the staff and instructor explained everything detailed to us and also other schools just care about the money you spend in hours and this school care about your success. I'm considering to apply for this year .","time":1582553265},{"author_name":"Mingyu Kang","author_url":"https://www.google.com/maps/contrib/109211177344953630497/reviews","language":"en","profile_photo_url":"https://lh3.googleusercontent.com/a-/AOh14GjlcBK8fBWAlFCUqMiByebeLIRJDwny0fWX4Od1=s128-c0x00000000-cc-rp-mo","rating":5,"relative_time_description":"a year ago","text":"If you are looking for flight school around New York area, This is the place where to go for your dream. I ve got my private and Instrument rating.\nvery satisfied and great faculty member. great instructors.","time":1594352285},{"author_name":"Charles Cunningham","author_url":"https://www.google.com/maps/contrib/116630197277772878565/reviews","language":"en","profile_photo_url":"https://lh3.googleusercontent.com/a-/AOh14Ggf1Q60Q46B4DFjJD8KwLWzVEy6-UXU27f5BM9hiw=s128-c0x00000000-cc-rp-mo","rating":5,"relative_time_description":"3 years ago","text":"Would recommend. I did not train there but recently got checked out to rent. Checkout went perfectly and the instructor I flew with was very knowledgeable and gave me lots of good advice for my future ratings.\nI would definitely recommend their instructors. Everyone at AOA is very professional and they have a wide selection of planes. They manage their school well and it is well organized. Good experience overall.","time":1520893590}],"types":["airport","university","school","point_of_interest","establishment"],"url":"https://maps.google.com/?cid=2855351368674333751","utc_offset":-300,"vicinity":"7150 Republic Airport # 101, Farmingdale","website":"https://www.academyofaviation.com/"},"status":"OK"} | AM24: <span class="street-address">7150 Republic Airport # 101</span>, <span class="locality">Farmingdale</span>, <span class="region">NY</span> <span class="postal-code">11735-3999</span>, <span class="country-name">USA</span> | AN24: (516) 613-4556 | AO24: https://maps.gstatic.com/mapfiles/place_api/icons/v1/png_71/school-71.png | AQ24: +1 516-613-4556 | AR24: airport,university,school,point_of_interest,establishment | AS24: -300 | AT24: 7150 Republic Airport # 101, Farmingdale | AU24: https://www.academyofaviation.com/ | AV24: 4.6 | AW24: 5
A25: Accelerated Flight Training LLC d/b/a AFTCenter | E25: 14181 Fern Ave | G25: Chino | H25: CA | I25: 91710 | J25: US | K25: (714) 321-3725 | L25: http://www.aftcenter.com/ | M25: CNO | N25: FLT61 | O25: FLT141 | Y25: https://maps.google.com/?cid=7615948261646824856 | AB25: Accelerated Flight Training LLC d/b/a AFTCenter | AC25: OPERATIONAL | AD25: ChIJh6c6ZM0z3YARmHU2y5dIsWk | AE25: 14181 Fern Ave, Chino, CA 91710, USA | AJ25: 33.995929 | AK25: -117.6538 | AL25: {"html_attributions":[],"result":{"address_components":[{"long_name":"14181","short_name":"14181","types":["street_number"]},{"long_name":"Fern Avenue","short_name":"Fern Ave","types":["route"]},{"long_name":"Chino","short_name":"Chino","types":["locality","political"]},{"long_name":"San Bernardino County","short_name":"San Bernardino County","types":["administrative_area_level_2","political"]},{"long_name":"California","short_name":"CA","types":["administrative_area_level_1","political"]},{"long_name":"United States","short_name":"US","types":["country","political"]},{"long_name":"91710","short_name":"91710","types":["postal_code"]}],"adr_address":"<span class=\"street-address\">14181 Fern Ave</span>, <span class=\"locality\">Chino</span>, <span class=\"region\">CA</span> <span class=\"postal-code\">91710</span>, <span class=\"country-name\">USA</span>","formatted_address":"14181 Fern Ave, Chino, CA 91710, USA","formatted_phone_number":"(714) 321-3725","geometry":{"location":{"lat":33.9959289,"lng":-117.6537976},"viewport":{"northeast":{"lat":33.9971772302915,"lng":-117.6524513697085},"southwest":{"lat":33.9944792697085,"lng":-117.6551493302915}}},"icon":"https://maps.gstatic.com/mapfiles/place_api/icons/v1/png_71/school-71.png","id":null,"international_phone_number":"+1 714-321-3725","name":"Accelerated Flight Training LLC d/b/a AFTCenter","place_id":"ChIJh6c6ZM0z3YARmHU2y5dIsWk","rating":4.3,"reference":null,"reviews":[{"author_name":"FlyUAAK","author_url":"https://www.google.com/maps/contrib/107515408853464046023/reviews","language":"en","profile_photo_url":"https://lh3.googleusercontent.com/a-/AOh14GisOHwrFJX4fXIxhbvEvKRPGDSbfH2GO4jc8crCTg=s128-c0x00000000-cc-rp-mo","rating":1,"relative_time_description":"2 months ago","text":"I would not recommend this flight training center. This person the owner of this flight training center name is Wenho Zhang. She has taken money in advance for training from our student and we asked for refund since the student discontinued flight training. She owe us back and our student almost $40,000.00. We have talked many times over and over and we have been waiting for this refund for 2 years. She has stopped all communication and never kept her promise. We are in process of Law Suit and legal action. Avoid this this flight training school at all cost or else you could be next victim. Don't not apply to this school and if you need more infos you could contact me direct. Also most of those 5 Stars feedbacks are all fake.","time":1635971488},{"author_name":"Xiaofei Gao","author_url":"https://www.google.com/maps/contrib/106564885940820315256/reviews","language":"en","profile_photo_url":"https://lh3.googleusercontent.com/a-/AOh14GjC7rh9k5O5hsu8AgVf3_ko3UpOxzptkLyQOugA=s128-c0x00000000-cc-rp-mo","rating":5,"relative_time_description":"11 months ago","text":"This is a really good place to start learning fly.they have helicopter and fixed wing training! I am graduated heli commercial pilot.doing CFI now.I’m thinking to get fixed wing now. Classmates and everyone was really nice!!","time":1611181200},{"author_name":"Siddhant Munj","author_url":"https://www.google.com/maps/contrib/111221182369232079608/reviews","language":"en","profile_photo_url":"https://lh3.googleusercontent.com/a/AATXAJztTeUJzBmjtn3LyvDJqNPpjY-POfHj8c_dkxYf=s128-c0x00000000-cc-rp-mo","rating":5,"relative_time_description":"2 years ago","text":"I am currently a student pilot at aft center i just completed my 1st flight and it was a very good exprience. The weather in california is too good for flying and aft center is very well suggested for anyone who wants to pursue their career as a pilot","time":1575419725},{"author_name":"jay singer","author_url":"https://www.google.com/maps/contrib/107916504559899165165/reviews","language":"en","profile_photo_url":"https://lh3.googleusercontent.com/a/AATXAJwyF_I8ZT1m_o8MigbnO91uQTtizECJXkEN4M6A=s128-c0x00000000-cc-rp-mo","rating":5,"relative_time_description":"2 years ago","text":"What a place! From the moment i met them to explain what i was looking for in my flight training to all the dealings i have had with them. Totally professional and honest. I couldn't have found a better flight school. So happy i chose AFT","time":1554754579},{"author_name":"Michael Thayer","author_url":"https://www.google.com/maps/contrib/115767908719570779598/reviews","language":"en","profile_photo_url":"https://lh3.googleusercontent.com/a/AATXAJzHH_gEn7QjKOesSqPmcYCTGYW8lJvvjkjseV2j=s128-c0x00000000-cc-rp-mo","rating":5,"relative_time_description":"a year ago","text":"Great place with great instructors and staff!!!","time":1598140024}],"types":["university","point_of_interest","establishment"],"url":"https://maps.google.com/?cid=7615948261646824856","utc_offset":-480,"vicinity":"14181 Fern Avenue, Chino","website":"http://www.aftcenter.com/"},"status":"OK"} | AM25: <span class="street-address">14181 Fern Ave</span>, <span class="locality">Chino</span>, <span class="region">CA</span> <span class="postal-code">91710</span>, <span class="country-name">USA</span> | AN25: (714) 321-3725 | AO25: https://maps.gstatic.com/mapfiles/place_api/icons/v1/png_71/school-71.png | AQ25: +1 714-321-3725 | AR25: university,point_of_interest,establishment | AS25: -480 | AT25: 14181 Fern Avenue, Chino | AU25: http://www.aftcenter.com/ | AV25: 4.3 | AW25: 5
A26: Access Professional Air | E26: 107 W Piper Dr | G26: Tulsa | H26: OK | I26: 74132 | J26: US | K26: (918) 298-3718 | L26: http://www.accessproair.com/ | M26: RVS | N26: P135 | Y26: https://maps.google.com/?cid=2200410570813803632 | AB26: Access Professional Air | AD26: ChIJ24aXOnaVtocRcAxfgcFtiR4 | AE26: 107 W Piper Dr, Tulsa, OK 74132, USA | AJ26: 36.04003 | AK26: -95.991338 | AL26: {"html_attributions":[],"result":{"address_components":[{"long_name":"107","short_name":"107","types":["street_number"]},{"long_name":"West Piper Drive","short_name":"W Piper Dr","types":["route"]},{"long_name":"Tulsa","short_name":"Tulsa","types":["locality","political"]},{"long_name":"Tulsa County","short_name":"Tulsa County","types":["administrative_area_level_2","political"]},{"long_name":"Oklahoma","short_name":"OK","types":["administrative_area_level_1","political"]},{"long_name":"United States","short_name":"US","types":["country","political"]},{"long_name":"74132","short_name":"74132","types":["postal_code"]}],"adr_address":"<span class=\"street-address\">107 W Piper Dr</span>, <span class=\"locality\">Tulsa</span>, <span class=\"region\">OK</span> <span class=\"postal-code\">74132</span>, <span class=\"country-name\">USA</span>","formatted_address":"107 W Piper Dr, Tulsa, OK 74132, USA","formatted_phone_number":"(918) 298-3718","geometry":{"location":{"lat":36.04003,"lng":-95.9913378},"viewport":{"northeast":{"lat":36.04118253029151,"lng":-95.9900464697085},"southwest":{"lat":36.03848456970851,"lng":-95.99274443029151}}},"icon":"https://maps.gstatic.com/mapfiles/place_api/icons/v1/png_71/generic_business-71.png","id":null,"international_phone_number":"+1 918-298-3718","name":"Access Professional Air","place_id":"ChIJ24aXOnaVtocRcAxfgcFtiR4","rating":null,"reference":null,"reviews":null,"types":["point_of_interest","establishment"],"url":"https://maps.google.com/?cid=2200410570813803632","utc_offset":-360,"vicinity":"107 West Piper Drive, Tulsa","website":"http://www.accessproair.com/"},"status":"OK"} | AM26: <span class="street-address">107 W Piper Dr</span>, <span class="locality">Tulsa</span>, <span class="region">OK</span> <span class="postal-code">74132</span>, <span class="country-name">USA</span> | AN26: (918) 298-3718 | AO26: https://maps.gstatic.com/mapfiles/place_api/icons/v1/png_71/generic_business-71.png | AQ26: +1 918-298-3718 | AR26: point_of_interest,establishment | AS26: -360 | AT26: 107 West Piper Drive, Tulsa | AU26: http://www.accessproair.com/
A27: Accessible Aviation | E27: 8517 Earhart Rd | F27: 300 | G27: Oakland | H27: CA | I27: 94621 | J27: US | K27: (662) 244-8434 | L27: https://www.accessibleaviation.com/golden_triangle.php | M27: GTR | N27: FLT61 | O27: FLT141 | Y27: https://maps.google.com/?cid=8706500524799807913 | AB27: Accessible Aviation | AC27: OPERATIONAL | AD27: ChIJsfI40q-Fj4ARqdFxKRm003g | AE27: 8517 Earhart Rd #300, Oakland, CA 94621, USA | AJ27: 37.730421 | AK27: -122.21122 | AL27: {"html_attributions":[],"result":{"address_components":[{"long_name":"300","short_name":"300","types":["subpremise"]},{"long_name":"8517","short_name":"8517","types":["street_number"]},{"long_name":"Earhart Road","short_name":"Earhart Rd","types":["route"]},{"long_name":"Oakland","short_name":"Oakland","types":["locality","political"]},{"long_name":"Alameda County","short_name":"Alameda County","types":["administrative_area_level_2","political"]},{"long_name":"California","short_name":"CA","types":["administrative_area_level_1","political"]},{"long_name":"United States","short_name":"US","types":["country","political"]},{"long_name":"94621","short_name":"94621","types":["postal_code"]}],"adr_address":"<span class=\"street-address\">8517 Earhart Rd #300</span>, <span class=\"locality\">Oakland</span>, <span class=\"region\">CA</span> <span class=\"postal-code\">94621</span>, <span class=\"country-name\">USA</span>","formatted_address":"8517 Earhart Rd #300, Oakland, CA 94621, USA","formatted_phone_number":"(662) 244-8434","geometry":{"location":{"lat":37.7304211,"lng":-122.2112235},"viewport":{"northeast":{"lat":37.7319167302915,"lng":-122.2097432197085},"southwest":{"lat":37.7292187697085,"lng":-122.2124411802915}}},"icon":"https://maps.gstatic.com/mapfiles/place_api/icons/v1/png_71/school-71.png","id":null,"international_phone_number":"+1 662-244-8434","name":"Accessible Aviation","place_id":"ChIJsfI40q-Fj4ARqdFxKRm003g","rating":null,"reference":null,"reviews":null,"types":["university","school","point_of_interest","establishment"],"url":"https://maps.google.com/?cid=8706500524799807913","utc_offset":-480,"vicinity":"8517 Earhart Road #300, Oakland","website":"https://www.accessibleaviation.com/golden_triangle.php"},"status":"OK"} | AM27: <span class="street-address">8517 Earhart Rd #300</span>, <span class="locality">Oakland</span>, <span class="region">CA</span> <span class="postal-code">94621</span>, <span class="country-name">USA</span> | AN27: (662) 244-8434 | AO27: https://maps.gstatic.com/mapfiles/place_api/icons/v1/png_71/school-71.png | AQ27: +1 662-244-8434 | AR27: university,school,point_of_interest,establishment | AS27: -480 | AT27: 8517 Earhart Road #300, Oakland | AU27: https://www.accessibleaviation.com/golden_triangle.php
A28: Accord Aviation Interiors, LLC | E28: 4701 N Main St | G28: Fort Worth | H28: TX | I28: 76106-2432 | J28: US | K28: (817) 626-1431 | L28: http://www.accordaviation.com/ | M28: FTW | N28: P145INT | Y28: https://maps.google.com/?cid=17683576416810099833 | AB28: Accord Aviation Interiors, LLC | AC28: OPERATIONAL | AD28: ChIJG2Vgdtp1ToYReeRwOg-vaPU | AE28: 4701 N Main St, Fort Worth, TX 76106, USA | AJ28: 32.829142 | AK28: -97.358837 | AL28: {"html_attributions":[],"result":{"address_components":[{"long_name":"4701","short_name":"4701","types":["street_number"]},{"long_name":"North Main Street","short_name":"N Main St","types":["route"]},{"long_name":"Fort Worth","short_name":"Fort Worth","types":["locality","political"]},{"long_name":"Tarrant County","short_name":"Tarrant County","types":["administrative_area_level_2","political"]},{"long_name":"Texas","short_name":"TX","types":["administrative_area_level_1","political"]},{"long_name":"United States","short_name":"US","types":["country","political"]},{"long_name":"76106","short_name":"76106","types":["postal_code"]},{"long_name":"2432","short_name":"2432","types":["postal_code_suffix"]}],"adr_address":"<span class=\"street-address\">4701 N Main St</span>, <span class=\"locality\">Fort Worth</span>, <span class=\"region\">TX</span> <span class=\"postal-code\">76106-2432</span>, <span class=\"country-name\">USA</span>","formatted_address":"4701 N Main St, Fort Worth, TX 76106, USA","formatted_phone_number":"(817) 626-1431","geometry":{"location":{"lat":32.82914230000001,"lng":-97.358837},"viewport":{"northeast":{"lat":32.83054938029151,"lng":-97.35708796970849},"southwest":{"lat":32.82785141970851,"lng":-97.3597859302915}}},"icon":"https://maps.gstatic.com/mapfiles/place_api/icons/v1/png_71/generic_business-71.png","id":null,"international_phone_number":"+1 817-626-1431","name":"Accord Aviation Interiors, LLC","place_id":"ChIJG2Vgdtp1ToYReeRwOg-vaPU","rating":5.0,"reference":null,"reviews":[{"author_name":"Ken Hensley","author_url":"https://www.google.com/maps/contrib/115593419045130202227/reviews","language":null,"profile_photo_url":"https://lh3.googleusercontent.com/a/AATXAJz0-N1phRju-Gu3699ZPWKPnnAfL0qj9qMZk28D=s128-c0x00000000-cc-rp-mo","rating":5,"relative_time_description":"a week ago","text":"","time":1640632316},{"author_name":"David Simmons","author_url":"https://www.google.com/maps/contrib/102245483770689115805/reviews","language":null,"profile_photo_url":"https://lh3.googleusercontent.com/a-/AOh14GiJZeUr2VmJ6d6CDAQCvb55drtaY8100jhpAGWf=s128-c0x00000000-cc-rp-mo-ba5","rating":5,"relative_time_description":"a year ago","text":"","time":1580083077}],"types":["general_contractor","point_of_interest","store","establishment"],"url":"https://maps.google.com/?cid=17683576416810099833","utc_offset":-360,"vicinity":"4701 North Main Street, Fort Worth","website":"http://www.accordaviation.com/"},"status":"OK"} | AM28: <span class="street-address">4701 N Main St</span>, <span class="locality">Fort Worth</span>, <span class="region">TX</span> <span class="postal-code">76106-2432</span>, <span class="country-name">USA</span> | AN28: (817) 626-1431 | AO28: https://maps.gstatic.com/mapfiles/place_api/icons/v1/png_71/generic_business-71.png | AQ28: +1 817-626-1431 | AR28: general_contractor,point_of_interest,store,establishment | AS28: -360 | AT28: 4701 North Main Street, Fort Worth | AU28: http://www.accordaviation.com/ | AV28: 5 | AW28: 2
A29: Accurate Aviation | E29: 204 Moffett Pl | G29: Goleta | H29: CA | I29: 93117 | J29: US | K29: (805) 770-2500 | L29: http://www.accurateaviation.com/ | M29: SBA | Y29: https://maps.google.com/?cid=1138104404890300826 | AB29: Accurate Aviation | AC29: OPERATIONAL | AD29: ChIJvfEzSH8_6YARmjHLIu1byw8 | AE29: Santa Barbara Airport, 204 Moffett Pl, Goleta, CA 93117, USA | AJ29: 34.42353 | AK29: -119.8357 | AL29: {"html_attributions":[],"result":{"address_components":[{"long_name":"Santa Barbara Airport","short_name":"Santa Barbara Airport","types":["point_of_interest","establishment"]},{"long_name":"204","short_name":"204","types":["street_number"]},{"long_name":"Moffett Place","short_name":"Moffett Pl","types":["route"]},{"long_name":"Goleta","short_name":"Goleta","types":["locality","political"]},{"long_name":"Santa Barbara County","short_name":"Santa Barbara County","types":["administrative_area_level_2","political"]},{"long_name":"California","short_name":"CA","types":["administrative_area_level_1","political"]},{"long_name":"United States","short_name":"US","types":["country","political"]},{"long_name":"93117","short_name":"93117","types":["postal_code"]}],"adr_address":"<span class=\"extended-address\">Santa Barbara Airport</span>, <span class=\"street-address\">204 Moffett Pl</span>, <span class=\"locality\">Goleta</span>, <span class=\"region\">CA</span> <span class=\"postal-code\">93117</span>, <span class=\"country-name\">USA</span>","formatted_address":"Santa Barbara Airport, 204 Moffett Pl, Goleta, CA 93117, USA","formatted_phone_number":"(805) 770-2500","geometry":{"location":{"lat":34.4235301,"lng":-119.8356957},"viewport":{"northeast":{"lat":34.4248840802915,"lng":-119.8342812197085},"southwest":{"lat":34.4221861197085,"lng":-119.8369791802915}}},"icon":"https://maps.gstatic.com/mapfiles/place_api/icons/v1/png_71/school-71.png","id":null,"international_phone_number":"+1 805-770-2500","name":"Accurate Aviation","place_id":"ChIJvfEzSH8_6YARmjHLIu1byw8","rating":null,"reference":null,"reviews":null,"types":["point_of_interest","establishment"],"url":"https://maps.google.com/?cid=1138104404890300826","utc_offset":-480,"vicinity":"Santa Barbara Airport, 204 Moffett Place, Goleta","website":"http://www.accurateaviation.com/"},"status":"OK"} | AM29: <span class="extended-address">Santa Barbara Airport</span>, <span class="street-address">204 Moffett Pl</span>, <span class="locality">Goleta</span>, <span class="region">CA</span> <span class="postal-code">93117</span>, <span class="country-name">USA</span> | AN29: (805) 770-2500 | AO29: https://maps.gstatic.com/mapfiles/place_api/icons/v1/png_71/school-71.png | AQ29: +1 805-770-2500 | AR29: point_of_interest,establishment | AS29: -480 | AT29: Santa Barbara Airport, 204 Moffett Place, Goleta | AU29: http://www.accurateaviation.com/
A30: Ace Aviation | E30: 289 E Perimeter Rd | G30: Renton | H30: WA | I30: 98057 | J30: US | K30: (425) 204-0845 | L30: http://www.aceaviationinc.com/ | M30: BFI | N30: P145 | O30: PART | Y30: https://maps.google.com/?cid=6879038064806790922 | AB30: Ace Aviation | AC30: OPERATIONAL | AD30: ChIJpcbS4KhCkFQRCgczWaxAd18 | AE30: 289 E Perimeter Rd, Renton, WA 98057, USA | AJ30: 47.486075 | AK30: -122.21061 | AL30: {"html_attributions":[],"result":{"address_components":[{"long_name":"289","short_name":"289","types":["street_number"]},{"long_name":"East Perimeter Road","short_name":"E Perimeter Rd","types":["route"]},{"long_name":"Renton","short_name":"Renton","types":["locality","political"]},{"long_name":"King County","short_name":"King County","types":["administrative_area_level_2","political"]},{"long_name":"Washington","short_name":"WA","types":["administrative_area_level_1","political"]},{"long_name":"United States","short_name":"US","types":["country","political"]},{"long_name":"98057","short_name":"98057","types":["postal_code"]}],"adr_address":"<span class=\"street-address\">289 E Perimeter Rd</span>, <span class=\"locality\">Renton</span>, <span class=\"region\">WA</span> <span class=\"postal-code\">98057</span>, <span class=\"country-name\">USA</span>","formatted_address":"289 E Perimeter Rd, Renton, WA 98057, USA","formatted_phone_number":"(425) 204-0845","geometry":{"location":{"lat":47.4860755,"lng":-122.2106065},"viewport":{"northeast":{"lat":47.4876145802915,"lng":-122.2092090197085},"southwest":{"lat":47.4849166197085,"lng":-122.2119069802915}}},"icon":"https://maps.gstatic.com/mapfiles/place_api/icons/v1/png_71/generic_business-71.png","id":null,"international_phone_number":"+1 425-204-0845","name":"Ace Aviation","place_id":"ChIJpcbS4KhCkFQRCgczWaxAd18","rating":4.5,"reference":null,"reviews":[{"author_name":"Jared P. Hernandez","author_url":"https://www.google.com/maps/contrib/113007456908305921194/reviews","language":"en","profile_photo_url":"https://lh3.googleusercontent.com/a-/AOh14GhRnjWdHO_2TBV-32HU3vY0ztfwxt6vns4LE6-AOQ=s128-c0x00000000-cc-rp-mo-ba3","rating":5,"relative_time_description":"4 years ago","text":"Didn't have much of a chance to look around, but the lobby area is nice and the hangar was very clean and well-maintained. I just loved being there as someone who'd love to have their pilot's license someday.","time":1497240804},{"author_name":"john lesh","author_url":"https://www.google.com/maps/contrib/100977662532694455088/reviews","language":"en","profile_photo_url":"https://lh3.googleusercontent.com/a/AATXAJyI4Ksf2sO-D7fq7ySoRuXS9oYLZBDDQKJQqRhQ=s128-c0x00000000-cc-rp-mo","rating":5,"relative_time_description":"3 years ago","text":"Great shop, I wouldn't take my plane anywhere else","time":1535481391},{"author_name":"howard cordell","author_url":"https://www.google.com/maps/contrib/100916495297036841184/reviews","language":"en","profile_photo_url":"https://lh3.googleusercontent.com/a/AATXAJwmG1HxupU9p76wohgX9n_DddcIZovHZxkR2zh6=s128-c0x00000000-cc-rp-mo-ba4","rating":4,"relative_time_description":"a year ago","text":"Very professional as expected from the aviation industry","time":1581560762},{"author_name":"En el mundo de los ciegos El tuerto es el rey","author_url":"https://www.google.com/maps/contrib/104098129727115374796/reviews","language":"en-US","profile_photo_url":"https://lh3.googleusercontent.com/a-/AOh14GggzZE1NWg_bXxqogVwNkvVqnfYzN5ECWtrePc-_Q4=s128-c0x00000000-cc-rp-mo-ba4","rating":5,"relative_time_description":"5 years ago","text":"More handsome boys: 3","time":1471149788},{"author_name":"Luis Salas","author_url":"https://www.google.com/maps/contrib/106298529873928305138/reviews","language":null,"profile_photo_url":"https://lh3.googleusercontent.com/a/AATXAJy5qMs9e6q-CVe51ppw8rXcO4BJoGBgt8r1-PE3=s128-c0x00000000-cc-rp-mo-ba2","rating":4,"relative_time_description":"2 months ago","text":"","time":1635970023}],"types":["point_of_interest","store","establishment"],"url":"https://maps.google.com/?cid=6879038064806790922","utc_offset":-480,"vicinity":"289 East Perimeter Road, Renton","website":"http://www.aceaviationinc.com/"},"status":"OK"} | AM30: <span class="street-address">289 E Perimeter Rd</span>, <span class="locality">Renton</span>, <span class="region">WA</span> <span class="postal-code">98057</span>, <span class="country-name">USA</span> | AN30: (425) 204-0845 | AO30: https://maps.gstatic.com/mapfiles/place_api/icons/v1/png_71/generic_business-71.png | AQ30: +1 425-204-0845 | AR30: point_of_interest,store,establishment | AS30: -480 | AT30: 289 East Perimeter Road, Renton | AU30: http://www.aceaviationinc.com/ | AV30: 4.5 | AW30: 5
A31: ACI Jet - San Luis Obispo | E31: 4751 Aviadores Wy | G31: San Luis Obispo | H31: CA | I31: 93401 | J31: US | K31: (805) 782-9722 | L31: https://www.acijet.com/ | M31: SBP | N31: FBO | O31: MGC | P31: P135 | Y31: https://maps.google.com/?cid=3227798343341513158 | AB31: ACI Jet - San Luis Obispo | AC31: OPERATIONAL | AD31: ChIJPyKYMLn27IARxhl33X1xyyw | AE31: 4751 Aviadores Wy, San Luis Obispo, CA 93401, USA | AJ31: 35.236952 | AK31: -120.63538 | AL31: {"html_attributions":[],"result":{"address_components":[{"long_name":"4751","short_name":"4751","types":["street_number"]},{"long_name":"Aviadores Way","short_name":"Aviadores Wy","types":["route"]},{"long_name":"San Luis Obispo","short_name":"San Luis Obispo","types":["locality","political"]},{"long_name":"San Luis Obispo County","short_name":"San Luis Obispo County","types":["administrative_area_level_2","political"]},{"long_name":"California","short_name":"CA","types":["administrative_area_level_1","political"]},{"long_name":"United States","short_name":"US","types":["country","political"]},{"long_name":"93401","short_name":"93401","types":["postal_code"]}],"adr_address":"<span class=\"street-address\">4751 Aviadores Wy</span>, <span class=\"locality\">San Luis Obispo</span>, <span class=\"region\">CA</span> <span class=\"postal-code\">93401</span>, <span class=\"country-name\">USA</span>","formatted_address":"4751 Aviadores Wy, San Luis Obispo, CA 93401, USA","formatted_phone_number":"(805) 782-9722","geometry":{"location":{"lat":35.2369515,"lng":-120.6353846},"viewport":{"northeast":{"lat":35.2383421802915,"lng":-120.6339683197085},"southwest":{"lat":35.2356442197085,"lng":-120.6366662802915}}},"icon":"https://maps.gstatic.com/mapfiles/place_api/icons/v1/png_71/airport-71.png","id":null,"international_phone_number":"+1 805-782-9722","name":"ACI Jet - San Luis Obispo","place_id":"ChIJPyKYMLn27IARxhl33X1xyyw","rating":4.7,"reference":null,"reviews":[{"author_name":"Indra Singhal","author_url":"https://www.google.com/maps/contrib/100226032093244986605/reviews","language":"en","profile_photo_url":"https://lh3.googleusercontent.com/a-/AOh14Gj9CNIcBt7tzr2GkW-CBnzEFoiVLNuTjeHabSw7i0U=s128-c0x00000000-cc-rp-mo-ba5","rating":5,"relative_time_description":"4 months ago","text":"Private flyers looking for professional meeting space at the airport will be well served at ACI Jet in San Luis Obispo. Excellent conference and meeting facilities, refreshments, snacks, and friendly staff to support your needs.\n\nVery impressive.","time":1629991317},{"author_name":"Andrew Lynch","author_url":"https://www.google.com/maps/contrib/112826906616813670064/reviews","language":"en","profile_photo_url":"https://lh3.googleusercontent.com/a-/AOh14GiCRYxSuNDdPy7JD_4wZAROrDE_dtI4y26g33CMaQ=s128-c0x00000000-cc-rp-mo","rating":5,"relative_time_description":"a month ago","text":"Excellent FBO. Friendly service, even for a little bugsmasher airplane. Keep up the good work keeping flying fun and enjoyable for the little guys.","time":1638072173},{"author_name":"Dillon Francis","author_url":"https://www.google.com/maps/contrib/107365275669082009477/reviews","language":"en","profile_photo_url":"https://lh3.googleusercontent.com/a-/AOh14Gj6pm3Qe2joMuxDMxDpGQCRPt9lhh8C4uXhs027RA=s128-c0x00000000-cc-rp-mo-ba3","rating":5,"relative_time_description":"2 months ago","text":"Astonishingly nice FBO, with state of the art facilities including meeting rooms with touch surfaces, private pilot lounges, flight planning rooms, and a spacious, aesthetically pleasing lobby with second floor view of the airport. Dont forget the ice cream by a local creamery. 10/10, with nice, knowledgeable and professional staff.","time":1634248417},{"author_name":"Dirk Dreyer","author_url":"https://www.google.com/maps/contrib/116177325758576900925/reviews","language":"en","profile_photo_url":"https://lh3.googleusercontent.com/a-/AOh14GjHPM7IEQ98arEMtMot2q4yv5qkxyE_gx4G32CVMb8=s128-c0x00000000-cc-rp-mo-ba4","rating":5,"relative_time_description":"5 months ago","text":"Super nice facility, friendly staff, excellent service and free snacks...we will be back.","time":1626301265},{"author_name":"D'Artagnan Heath","author_url":"https://www.google.com/maps/contrib/105142090006289414317/reviews","language":"en","profile_photo_url":"https://lh3.googleusercontent.com/a-/AOh14Gj3RNPWiUr8mloS4-qcQosY_JZa8od2Apq4e5ARuMI=s128-c0x00000000-cc-rp-mo-ba3","rating":5,"relative_time_description":"a year ago","text":"Kate at the front desk and everyone else we interacted with at ACI were super nice, extremely friendly and helpful!\n\nThey had great service, cheap fuel and wonderful recommendations for dinner as well.\n\nWe can't wait to come back to enjoy their hospitality again!","time":1602795697}],"types":["airport","point_of_interest","establishment"],"url":"https://maps.google.com/?cid=3227798343341513158","utc_offset":-480,"vicinity":"4751 Aviadores Way, San Luis Obispo","website":"https://www.acijet.com/"},"status":"OK"} | AM31: <span class="street-address">4751 Aviadores Wy</span>, <span class="locality">San Luis Obispo</span>, <span class="region">CA</span> <span class="postal-code">93401</span>, <span class="country-name">USA</span> | AN31: (805) 782-9722 | AO31: https://maps.gstatic.com/mapfiles/place_api/icons/v1/png_71/airport-71.png | AQ31: +1 805-782-9722 | AR31: airport,point_of_interest,establishment | AS31: -480 | AT31: 4751 Aviadores Way, San Luis Obispo | AU31: https://www.acijet.com/ | AV31: 4.7 | AW31: 5
A32: ACI Jet Maintenance, Repair & Overhaul (MRO) | E32: 4751 Aviadores Wy | G32: San Luis Obispo | H32: CA | I32: 93401 | J32: US | K32: (805) 548-1350 | L32: http://mro.acijet.com/ | M32: SBP | N32: P145 | O32: AFLIM | Y32: https://maps.google.com/?cid=13809807537779313467 | AB32: ACI Jet Maintenance, Repair & Overhaul (MRO) | AC32: OPERATIONAL | AD32: ChIJ-Sw8pb327IAROwvZwclKpr8 | AE32: 4751 Aviadores Wy, San Luis Obispo, CA 93401, USA | AJ32: 35.236584 | AK32: -120.63536 | AL32: {"html_attributions":[],"result":{"address_components":[{"long_name":"4751","short_name":"4751","types":["street_number"]},{"long_name":"Aviadores Way","short_name":"Aviadores Wy","types":["route"]},{"long_name":"San Luis Obispo","short_name":"San Luis Obispo","types":["locality","political"]},{"long_name":"San Luis Obispo County","short_name":"San Luis Obispo County","types":["administrative_area_level_2","political"]},{"long_name":"California","short_name":"CA","types":["administrative_area_level_1","political"]},{"long_name":"United States","short_name":"US","types":["country","political"]},{"long_name":"93401","short_name":"93401","types":["postal_code"]}],"adr_address":"<span class=\"street-address\">4751 Aviadores Wy</span>, <span class=\"locality\">San Luis Obispo</span>, <span class=\"region\">CA</span> <span class=\"postal-code\">93401</span>, <span class=\"country-name\">USA</span>","formatted_address":"4751 Aviadores Wy, San Luis Obispo, CA 93401, USA","formatted_phone_number":"(805) 548-1350","geometry":{"location":{"lat":35.2365842,"lng":-120.6353596},"viewport":{"northeast":{"lat":35.23800468029149,"lng":-120.6338119697085},"southwest":{"lat":35.2353067197085,"lng":-120.6365099302915}}},"icon":"https://maps.gstatic.com/mapfiles/place_api/icons/v1/png_71/generic_business-71.png","id":null,"international_phone_number":"+1 805-548-1350","name":"ACI Jet Maintenance, Repair & Overhaul (MRO)","place_id":"ChIJ-Sw8pb327IAROwvZwclKpr8","rating":5.0,"reference":null,"reviews":[{"author_name":"Oscar Lima Québec California usa","author_url":"https://www.google.com/maps/contrib/104472515941212092551/reviews","language":"en","profile_photo_url":"https://lh3.googleusercontent.com/a-/AOh14GiKdBshbnFoIIh3xAMgCUaExwRZ7MkWbGfCiAW09g=s128-c0x00000000-cc-rp-mo","rating":5,"relative_time_description":"7 years ago","text":"very good FBO and perfect charter service.\nalways a pleasure to travel with you. leclercq family santa barbara.","time":1396851016}],"types":["point_of_interest","establishment"],"url":"https://maps.google.com/?cid=13809807537779313467","utc_offset":-480,"vicinity":"4751 Aviadores Way, San Luis Obispo","website":"http://mro.acijet.com/"},"status":"OK"} | AM32: <span class="street-address">4751 Aviadores Wy</span>, <span class="locality">San Luis Obispo</span>, <span class="region">CA</span> <span class="postal-code">93401</span>, <span class="country-name">USA</span> | AN32: (805) 548-1350 | AO32: https://maps.gstatic.com/mapfiles/place_api/icons/v1/png_71/generic_business-71.png | AQ32: +1 805-548-1350 | AR32: point_of_interest,establishment | AS32: -480 | AT32: 4751 Aviadores Way, San Luis Obispo | AU32: http://mro.acijet.com/ | AV32: 5 | AW32: 1
A33: Ackerman Aviation Group | E33: 20002 Horizon Way | G33: San Antonio | H33: TX | I33: 78258-3154 | J33: US | K33: (210) 377-2717 | L33: http://www.acavgroup.com/ | M33: SAT | N33: CNSL | O33: ACAC | Y33: https://maps.google.com/?cid=12297752955550346454 | AB33: Ackerman Aviation Group | AD33: ChIJo9dpKjhiXIYR1qwWIyhlqqo | AE33: 20002 Horizon Way, San Antonio, TX 78258, USA | AJ33: 29.628191 | AK33: -98.517095 | AL33: {"html_attributions":[],"result":{"address_components":[{"long_name":"20002","short_name":"20002","types":["street_number"]},{"long_name":"Horizon Way","short_name":"Horizon Way","types":["route"]},{"long_name":"Stone Oak","short_name":"Stone Oak","types":["neighborhood","political"]},{"long_name":"San Antonio","short_name":"San Antonio","types":["locality","political"]},{"long_name":"Bexar County","short_name":"Bexar County","types":["administrative_area_level_2","political"]},{"long_name":"Texas","short_name":"TX","types":["administrative_area_level_1","political"]},{"long_name":"United States","short_name":"US","types":["country","political"]},{"long_name":"78258","short_name":"78258","types":["postal_code"]},{"long_name":"3154","short_name":"3154","types":["postal_code_suffix"]}],"adr_address":"<span class=\"street-address\">20002 Horizon Way</span>, <span class=\"locality\">San Antonio</span>, <span class=\"region\">TX</span> <span class=\"postal-code\">78258-3154</span>, <span class=\"country-name\">USA</span>","formatted_address":"20002 Horizon Way, San Antonio, TX 78258, USA","formatted_phone_number":"(210) 377-2717","geometry":{"location":{"lat":29.628191,"lng":-98.517095},"viewport":{"northeast":{"lat":29.6295104802915,"lng":-98.5158559697085},"southwest":{"lat":29.6268125197085,"lng":-98.5185539302915}}},"icon":"https://maps.gstatic.com/mapfiles/place_api/icons/v1/png_71/generic_business-71.png","id":null,"international_phone_number":"+1 210-377-2717","name":"Ackerman Aviation Group","place_id":"ChIJo9dpKjhiXIYR1qwWIyhlqqo","rating":null,"reference":null,"reviews":null,"types":["point_of_interest","establishment"],"url":"https://maps.google.com/?cid=12297752955550346454","utc_offset":-360,"vicinity":"20002 Horizon Way, San Antonio","website":"http://www.acavgroup.com/"},"status":"OK"} | AM33: <span class="street-address">20002 Horizon Way</span>, <span class="locality">San Antonio</span>, <span class="region">TX</span> <span class="postal-code">78258-3154</span>, <span class="country-name">USA</span> | AN33: (210) 377-2717 | AO33: https://maps.gstatic.com/mapfiles/place_api/icons/v1/png_71/generic_business-71.png | AQ33: +1 210-377-2717 | AR33: point_of_interest,establishment | AS33: -360 | AT33: 20002 Horizon Way, San Antonio | AU33: http://www.acavgroup.com/
A34: Acropolis Aviation | G34: Boca Raton | H34: FL | I34: 33487 | J34: US | K34: (561) 988-2226 | L34: http://acropolisaviation.net/ | M34: BCT | N34: PART | Y34: https://maps.google.com/?cid=16146854400688432070 | AB34: Acropolis Aviation | AD34: ChIJpWHtFDMe2YgRdAElTucAEF0 | AE34: 6453 West Rogers Circle, Bay S-5, Boca Raton, FL 33487, USA | AJ34: 26.405001 | AK34: -80.113982 | AL34: {"html_attributions":[],"result":{"address_components":[{"long_name":"Boca Raton","short_name":"Boca Raton","types":["locality","political"]},{"long_name":"Palm Beach County","short_name":"Palm Beach County","types":["administrative_area_level_2","political"]},{"long_name":"Florida","short_name":"FL","types":["administrative_area_level_1","political"]},{"long_name":"United States","short_name":"US","types":["country","political"]},{"long_name":"33487","short_name":"33487","types":["postal_code"]}],"adr_address":"6453 West Rogers Circle, <span class=\"street-address\">Bay S-5</span>, <span class=\"locality\">Boca Raton</span>, <span class=\"region\">FL</span> <span class=\"postal-code\">33487</span>, <span class=\"country-name\">USA</span>","formatted_address":"6453 West Rogers Circle, Bay S-5, Boca Raton, FL 33487, USA","formatted_phone_number":"(561) 988-2226","geometry":{"location":{"lat":26.405001,"lng":-80.1139819},"viewport":{"northeast":{"lat":26.4063965302915,"lng":-80.1126333197085},"southwest":{"lat":26.4036985697085,"lng":-80.11533128029151}}},"icon":"https://maps.gstatic.com/mapfiles/place_api/icons/v1/png_71/generic_business-71.png","id":null,"international_phone_number":"+1 561-988-2226","name":"Acropolis Aviation","place_id":"ChIJ2b3yFDMe2YgRxqP8GIcmFeA","rating":null,"reference":null,"reviews":null,"types":["point_of_interest","store","establishment"],"url":"https://maps.google.com/?cid=16146854400688432070","utc_offset":-300,"vicinity":"6453 West Rogers Circle, Bay S-5, Boca Raton","website":"http://acropolisaviation.net/"},"status":"OK"} | AM34: 6453 West Rogers Circle, <span class="street-address">Bay S-5</span>, <span class="locality">Boca Raton</span>, <span class="region">FL</span> <span class="postal-code">33487</span>, <span class="country-name">USA</span> | AN34: (561) 988-2226 | AO34: https://maps.gstatic.com/mapfiles/place_api/icons/v1/png_71/generic_business-71.png | AQ34: +1 561-988-2226 | AR34: point_of_interest,store,establishment | AS34: -300 | AT34: 6453 West Rogers Circle, Bay S-5, Boca Raton | AU34: http://acropolisaviation.net/
A35: Addison Aviation Services | E35: 4584 Claire Chennault Dr | G35: Addison | H35: TX | I35: 75001-5321 | J35: US | K35: (972) 248-1707 | L35: https://addisontexas.net/addison-aviation-services | M35: ADS | AD35: ChIJJ-ekcFMhTIYRu1ciStqaR-I
A36: Addison Pilot Shop | E36: 4653 Westgrove Dr | G36: Addison | H36: TX | I36: 75001-3216 | J36: US | K36: (972) 735-8710 | L36: http://www.addisonpilotshop.com/ | M36: ADS | N36: PILOT | Y36: https://maps.google.com/?cid=17019798744652519475 | AB36: Addison Pilot Shop | AC36: OPERATIONAL | AD36: ChIJRTsWllMhTIYRMxink8h4Muw | AE36: 4653 Westgrove Dr, Addison, TX 75001, USA | AJ36: 32.976036 | AK36: -96.831314 | AL36: {"html_attributions":[],"result":{"address_components":[{"long_name":"4653","short_name":"4653","types":["street_number"]},{"long_name":"Westgrove Drive","short_name":"Westgrove Dr","types":["route"]},{"long_name":"Addison","short_name":"Addison","types":["locality","political"]},{"long_name":"Dallas County","short_name":"Dallas County","types":["administrative_area_level_2","political"]},{"long_name":"Texas","short_name":"TX","types":["administrative_area_level_1","political"]},{"long_name":"United States","short_name":"US","types":["country","political"]},{"long_name":"75001","short_name":"75001","types":["postal_code"]},{"long_name":"3216","short_name":"3216","types":["postal_code_suffix"]}],"adr_address":"<span class=\"street-address\">4653 Westgrove Dr</span>, <span class=\"locality\">Addison</span>, <span class=\"region\">TX</span> <span class=\"postal-code\">75001-3216</span>, <span class=\"country-name\">USA</span>","formatted_address":"4653 Westgrove Dr, Addison, TX 75001, USA","formatted_phone_number":"(972) 735-8710","geometry":{"location":{"lat":32.9760365,"lng":-96.8313137},"viewport":{"northeast":{"lat":32.9772726302915,"lng":-96.82998916970848},"southwest":{"lat":32.9745746697085,"lng":-96.83268713029149}}},"icon":"https://maps.gstatic.com/mapfiles/place_api/icons/v1/png_71/generic_business-71.png","id":null,"international_phone_number":"+1 972-735-8710","name":"Addison Pilot Shop","place_id":"ChIJRTsWllMhTIYRMxink8h4Muw","rating":4.8,"reference":null,"reviews":[{"author_name":"Jordan Bellinger","author_url":"https://www.google.com/maps/contrib/107790228448294465257/reviews","language":"en","profile_photo_url":"https://lh3.googleusercontent.com/a-/AOh14GhcGOV720Vi2rZr5I3LI1VfkZCFsu2EpRXNO8b5OCY=s128-c0x00000000-cc-rp-mo-ba4","rating":5,"relative_time_description":"2 weeks ago","text":"Just started my pilot training and I heard these ladies are the go to for supplies and equipment in the Dallas area. They are nice and very knowledgeable with absolutely great customer service. I ran into some issues yesterday and they went above and beyond to help me out. Thank you.","time":1640093596},{"author_name":"Michael McLoughlin","author_url":"https://www.google.com/maps/contrib/115277764856931653139/reviews","language":"en","profile_photo_url":"https://lh3.googleusercontent.com/a/AATXAJyeyJg6dRdCqb3d6_G33aheE1iBj1Bli3qjB-fO=s128-c0x00000000-cc-rp-mo","rating":5,"relative_time_description":"a month ago","text":"A great location for pilot supplies, especially headsets. The owner is helpful and knowledgeable.","time":1637644686},{"author_name":"Ahmet Öncü","author_url":"https://www.google.com/maps/contrib/112725237291349415666/reviews","language":"en","profile_photo_url":"https://lh3.googleusercontent.com/a-/AOh14Gg_p5IcT9Wbyq7hPTn77_kAJdXaxjM23GEfeCcgJAY=s128-c0x00000000-cc-rp-mo-ba5","rating":5,"relative_time_description":"4 months ago","text":"Beautiful customer service from the owner she is a sweetheart very helpful. I'll definitely come back.\n\nNote: prices are lower than Amazon","time":1629180563},{"author_name":"Ray Dauphinais","author_url":"https://www.google.com/maps/contrib/106153461944626076266/reviews","language":"en","profile_photo_url":"https://lh3.googleusercontent.com/a-/AOh14GjwEwYEt4_KSsZrpWu2FaExmXsGXfHKYy6nH-uzI-0=s128-c0x00000000-cc-rp-mo-ba3","rating":5,"relative_time_description":"8 months ago","text":"Well stocked. Friendly, knowledgeable manager.","time":1620082894},{"author_name":"75876","author_url":"https://www.google.com/maps/contrib/108459124695466668779/reviews","language":"en","profile_photo_url":"https://lh3.googleusercontent.com/a/AATXAJy2m4qIPJ1EqsRGvaYq4KPUZt5P2E8Z98NiTZSj=s128-c0x00000000-cc-rp-mo","rating":5,"relative_time_description":"6 months ago","text":"This is my go to shop for anything aviation. My schedule had changed at the last moment at work and was getting off 30 minutes before the shop was to close, well I was going to get there 10 minutes after closing due to heavy traffic in the afternoon and called to make sure what time they closed, I spoke with Brenda and she said \"no worries, I will wait for you\" to me that is going above and beyond and she has won my business for life. Thank you!","time":1624670148}],"types":["point_of_interest","store","establishment"],"url":"https://maps.google.com/?cid=17019798744652519475","utc_offset":-360,"vicinity":"4653 Westgrove Drive, Addison","website":"http://www.addisonpilotshop.com/"},"status":"OK"} | AM36: <span class="street-address">4653 Westgrove Dr</span>, <span class="locality">Addison</span>, <span class="region">TX</span> <span class="postal-code">75001-3216</span>, <span class="country-name">USA</span> | AN36: (972) 735-8710 | AO36: https://maps.gstatic.com/mapfiles/place_api/icons/v1/png_71/generic_business-71.png | AQ36: +1 972-735-8710 | AR36: point_of_interest,store,establishment | AS36: -360 | AT36: 4653 Westgrove Drive, Addison | AU36: http://www.addisonpilotshop.com/ | AV36: 4.8 | AW36: 5
A37: ADF Airways Miami Flight School | E37: 14532 SW 129th St | G37: Miami | H37: FL | I37: 33186-5305 | J37: US | K37: (305) 233-6648 | L37: http://www.adfairways.net/ | M37: TMB | N37: FLT61 | O37: FLT141 | Y37: https://maps.google.com/?cid=16137764906724569226 | AB37: ADF Airways Miami Flight School | AC37: OPERATIONAL | AD37: ChIJFXrIrpPB2YgRijAVXq7b9N8 | AE37: 14532 SW 129th St, Miami, FL 33186, USA | AJ37: 25.64608 | AK37: -80.4294 | AL37: {"html_attributions":[],"result":{"address_components":[{"long_name":"14532","short_name":"14532","types":["street_number"]},{"long_name":"Southwest 129th Street","short_name":"SW 129th St","types":["route"]},{"long_name":"West End","short_name":"West End","types":["neighborhood","political"]},{"long_name":"Miami","short_name":"Miami","types":["locality","political"]},{"long_name":"Miami-Dade County","short_name":"Miami-Dade County","types":["administrative_area_level_2","political"]},{"long_name":"Florida","short_name":"FL","types":["administrative_area_level_1","political"]},{"long_name":"United States","short_name":"US","types":["country","political"]},{"long_name":"33186","short_name":"33186","types":["postal_code"]},{"long_name":"5305","short_name":"5305","types":["postal_code_suffix"]}],"adr_address":"<span class=\"street-address\">14532 SW 129th St</span>, <span class=\"locality\">Miami</span>, <span class=\"region\">FL</span> <span class=\"postal-code\">33186-5305</span>, <span class=\"country-name\">USA</span>","formatted_address":"14532 SW 129th St, Miami, FL 33186, USA","formatted_phone_number":"(305) 233-6648","geometry":{"location":{"lat":25.6460801,"lng":-80.4294001},"viewport":{"northeast":{"lat":25.64752888029151,"lng":-80.4280550197085},"southwest":{"lat":25.6448309197085,"lng":-80.43075298029152}}},"icon":"https://maps.gstatic.com/mapfiles/place_api/icons/v1/png_71/school-71.png","id":null,"international_phone_number":"+1 305-233-6648","name":"ADF Airways Miami Flight School","place_id":"ChIJFXrIrpPB2YgRijAVXq7b9N8","rating":4.7,"reference":null,"reviews":[{"author_name":"USAC Tricentenaria","author_url":"https://www.google.com/maps/contrib/114626016083122883865/reviews","language":"en","profile_photo_url":"https://lh3.googleusercontent.com/a-/AOh14GjngAZ4g49VreqfVePPr6oghXm6pU3wkBqLQhhe=s128-c0x00000000-cc-rp-mo","rating":1,"relative_time_description":"5 months ago","text":"Horrible school! I wanted to learn to fly and no one ever picks up the phone at the school, when I showed up for an intro flight they refused to see me because I wore shorts. Much better options at this airport","time":1628435678},{"author_name":"Just Me","author_url":"https://www.google.com/maps/contrib/101640743696142514866/reviews","language":"en","profile_photo_url":"https://lh3.googleusercontent.com/a-/AOh14GivEcSep6NY-PAvOqvJ9Q9X101bObHvsexz-t5_vQ=s128-c0x00000000-cc-rp-mo-ba4","rating":5,"relative_time_description":"a year ago","text":"AMAZING experience for introductory flight for my son, from the moment I called to ask questions and schedule, to finishing the flight. Everyone is kind, professional, helpful - and you can tell they are happy to be there. The business is super clean and well organized, from completing paperwork in advance to the protections in place for COVID. Super impressed. Our pilot was Ricardo, and he took an interest in showing my son around the plane, and answering questions. He and his team were first rate. Thank you so much for making my son's first flight such a great experience!!!","time":1601142702},{"author_name":"Nicolas Rios","author_url":"https://www.google.com/maps/contrib/117617159963875730949/reviews","language":"en","profile_photo_url":"https://lh3.googleusercontent.com/a-/AOh14GjTSFgrlCecpPc5kyxhk2IxiLtHRvIxqIl5Bstt3A=s128-c0x00000000-cc-rp-mo","rating":5,"relative_time_description":"a year ago","text":"It is one of the best flight schools I have known and is currently offering some courses from home due to the situation with the virus. Really professional.","time":1588800258},{"author_name":"Lenyn Pazmiño","author_url":"https://www.google.com/maps/contrib/117683878751927908808/reviews","language":"en","profile_photo_url":"https://lh3.googleusercontent.com/a-/AOh14GhZAqs1Lg2M2_9H5tuPOAK2PLZPxafFbtL1xQ1e5Q=s128-c0x00000000-cc-rp-mo-ba3","rating":5,"relative_time_description":"5 months ago","text":"Is the future of my son","time":1626874154},{"author_name":"Chris Anderson","author_url":"https://www.google.com/maps/contrib/113515219227513460069/reviews","language":"en","profile_photo_url":"https://lh3.googleusercontent.com/a/AATXAJy3E0A3ES5FUu0GM3BBtJpNfxUnAJctMEfHtDjZ=s128-c0x00000000-cc-rp-mo","rating":5,"relative_time_description":"a year ago","text":"Excellent flight school. Competent instructors, adequate aircraft, equipment, and simulation. Very helpful with the FAA exam also.","time":1582739007}],"types":["university","point_of_interest","establishment"],"url":"https://maps.google.com/?cid=16137764906724569226","utc_offset":-300,"vicinity":"14532 Southwest 129th Street, Miami","website":"http://www.adfairways.net/"},"status":"OK"} | AM37: <span class="street-address">14532 SW 129th St</span>, <span class="locality">Miami</span>, <span class="region">FL</span> <span class="postal-code">33186-5305</span>, <span class="country-name">USA</span> | AN37: (305) 233-6648 | AO37: https://maps.gstatic.com/mapfiles/place_api/icons/v1/png_71/school-71.png | AQ37: +1 305-233-6648 | AR37: university,point_of_interest,establishment | AS37: -300 | AT37: 14532 Southwest 129th Street, Miami | AU37: http://www.adfairways.net/ | AV37: 4.7 | AW37: 5
A38: Advanced Aircraft Center | E38: 14299 SW 127th St | G38: Miami | H38: FL | I38: 33186 | J38: US | K38: (305) 259-8291 | L38: http://www.advancedaircraftcenter.com/ | M38: TMB | N38: PART | Y38: https://maps.google.com/?cid=12351149941133203386 | AB38: Advanced Aircraft Center | AC38: OPERATIONAL | AD38: ChIJCaEtcpHB2YgRutfUqG4ZaKs | AE38: 14299 SW 127th St, Miami, FL 33186, USA | AJ38: 25.649768 | AK38: -80.425466 | AL38: {"html_attributions":[],"result":{"address_components":[{"long_name":"14299","short_name":"14299","types":["street_number"]},{"long_name":"Southwest 127th Street","short_name":"SW 127th St","types":["route"]},{"long_name":"West End","short_name":"West End","types":["neighborhood","political"]},{"long_name":"Miami","short_name":"Miami","types":["locality","political"]},{"long_name":"Miami-Dade County","short_name":"Miami-Dade County","types":["administrative_area_level_2","political"]},{"long_name":"Florida","short_name":"FL","types":["administrative_area_level_1","political"]},{"long_name":"United States","short_name":"US","types":["country","political"]},{"long_name":"33186","short_name":"33186","types":["postal_code"]}],"adr_address":"<span class=\"street-address\">14299 SW 127th St</span>, <span class=\"locality\">Miami</span>, <span class=\"region\">FL</span> <span class=\"postal-code\">33186</span>, <span class=\"country-name\">USA</span>","formatted_address":"14299 SW 127th St, Miami, FL 33186, USA","formatted_phone_number":"(305) 259-8291","geometry":{"location":{"lat":25.649768,"lng":-80.4254658},"viewport":{"northeast":{"lat":25.6511169802915,"lng":-80.42411681970849},"southwest":{"lat":25.6484190197085,"lng":-80.42681478029151}}},"icon":"https://maps.gstatic.com/mapfiles/place_api/icons/v1/png_71/shopping-71.png","id":null,"international_phone_number":"+1 305-259-8291","name":"Advanced Aircraft Center","place_id":"ChIJCaEtcpHB2YgRutfUqG4ZaKs","rating":4.5,"reference":null,"reviews":[{"author_name":"Israel Hohle","author_url":"https://www.google.com/maps/contrib/108021086551011688643/reviews","language":"en","profile_photo_url":"https://lh3.googleusercontent.com/a-/AOh14Gi9swpPKTOJqrYI_y9Pi0DFurx8CEgObQOFRrcXrDI=s128-c0x00000000-cc-rp-mo-ba4","rating":5,"relative_time_description":"2 weeks ago","text":"Nice.","time":1639979833},{"author_name":"aviation results","author_url":"https://www.google.com/maps/contrib/106221479867815353459/reviews","language":"en","profile_photo_url":"https://lh3.googleusercontent.com/a-/AOh14GgcIEL54z9w2d18QUbcc1RHmLM_2bUeJTlnp0Mlvg=s128-c0x00000000-cc-rp-mo","rating":5,"relative_time_description":"3 years ago","text":"Pete went out of his way to make us feel like family. The shop was clean and the staff knowledgeable. Definitely recommend!","time":1534811316},{"author_name":"Chad Jensen","author_url":"https://www.google.com/maps/contrib/104947563373332431906/reviews","language":"en","profile_photo_url":"https://lh3.googleusercontent.com/a-/AOh14GhLPcG5R7ow19AQFiIaIHoK_nXqzIXAPIkSQwlxWg=s128-c0x00000000-cc-rp-mo","rating":5,"relative_time_description":"2 years ago","text":"This is the best aviation repair facility out there. We stopped here for the night on a fuel stop and ended up stranded as we had a problem with the nose gear on our Cirrus SR22. They went above and beyond to get me and my family to Key West. Pete, his Son, and team of mechanics spent most of the day trying different options to get us back in the air. At last, they actually had a spare nose gear in their warehouse that allowed us to get on our way. Amazing! I was impressed with their professionalism, speed, and dedication. Highly recommend Advanced Aviation Services. I owe a huge debt of gratitude.\n\nIf you have a GA airplane, you must use this place!","time":1550476188},{"author_name":"Aviator Services","author_url":"https://www.google.com/maps/contrib/104955783633797497182/reviews","language":"en","profile_photo_url":"https://lh3.googleusercontent.com/a-/AOh14Gg1-3Egrp7mjnMfYiPsJDp1_OyOTuZDjwCpFZ4www=s128-c0x00000000-cc-rp-mo","rating":5,"relative_time_description":"6 years ago","text":"They handle the maintenance for my Cirrus SR22 and do an excellent job. Pete Lobello, the owner, is extremely knowledgble and quickly handles any maintenance issues whether during routine inspections or discrepenacies. He respones quickly even when I call him after hours. He is very customer service oriented. I recommend them highly if you need aircraft maintennace services or any expertise related to your airplane.","time":1449264800},{"author_name":"Victor Caracena","author_url":"https://www.google.com/maps/contrib/117965534352528072984/reviews","language":"en","profile_photo_url":"https://lh3.googleusercontent.com/a-/AOh14Gg2CjJGzfS2WjtyDSajy3selEy9YN_-v9dkoUbnhw=s128-c0x00000000-cc-rp-mo","rating":1,"relative_time_description":"3 years ago","text":"Disagree with the prices of original parts, at about 40% more expensive than other Piper centers. They have also\nscreamed and insulted us by phone.","time":1519229299}],"types":["point_of_interest","store","establishment"],"url":"https://maps.google.com/?cid=12351149941133203386","utc_offset":-300,"vicinity":"14299 Southwest 127th Street, Miami","website":"http://www.advancedaircraftcenter.com/"},"status":"OK"} | AM38: <span class="street-address">14299 SW 127th St</span>, <span class="locality">Miami</span>, <span class="region">FL</span> <span class="postal-code">33186</span>, <span class="country-name">USA</span> | AN38: (305) 259-8291 | AO38: https://maps.gstatic.com/mapfiles/place_api/icons/v1/png_71/shopping-71.png | AQ38: +1 305-259-8291 | AR38: point_of_interest,store,establishment | AS38: -300 | AT38: 14299 Southwest 127th Street, Miami | AU38: http://www.advancedaircraftcenter.com/ | AV38: 4.5 | AW38: 5
A39: Advanced Aircraft Services | E39: 8622 Gibbs Dr | G39: San Diego | H39: CA | I39: 92123-1729 | J39: US | K39: (858) 560-7599 | L39: https://advaircraft.com/ | M39: MYF | N39: P145 | O39: AFLIM | Y39: https://maps.google.com/?cid=11559581204409438426 | AB39: Advanced Aircraft Services | AC39: OPERATIONAL | AD39: ChIJy1Vbd9v_24AR2lAbMdzha6A | AE39: 8622 Gibbs Dr, San Diego, CA 92123, USA | AJ39: 32.810695 | AK39: -117.14342 | AL39: {"html_attributions":[],"result":{"address_components":[{"long_name":"8622","short_name":"8622","types":["street_number"]},{"long_name":"Gibbs Drive","short_name":"Gibbs Dr","types":["route"]},{"long_name":"Kearny Mesa","short_name":"Kearny Mesa","types":["neighborhood","political"]},{"long_name":"San Diego","short_name":"San Diego","types":["locality","political"]},{"long_name":"San Diego County","short_name":"San Diego County","types":["administrative_area_level_2","political"]},{"long_name":"California","short_name":"CA","types":["administrative_area_level_1","political"]},{"long_name":"United States","short_name":"US","types":["country","political"]},{"long_name":"92123","short_name":"92123","types":["postal_code"]},{"long_name":"1729","short_name":"1729","types":["postal_code_suffix"]}],"adr_address":"<span class=\"street-address\">8622 Gibbs Dr</span>, <span class=\"locality\">San Diego</span>, <span class=\"region\">CA</span> <span class=\"postal-code\">92123-1729</span>, <span class=\"country-name\">USA</span>","formatted_address":"8622 Gibbs Dr, San Diego, CA 92123, USA","formatted_phone_number":"(858) 560-7599","geometry":{"location":{"lat":32.8106953,"lng":-117.143422},"viewport":{"northeast":{"lat":32.8119212802915,"lng":-117.1420707697085},"southwest":{"lat":32.80922331970851,"lng":-117.1447687302915}}},"icon":"https://maps.gstatic.com/mapfiles/place_api/icons/v1/png_71/school-71.png","id":null,"international_phone_number":"+1 858-560-7599","name":"Advanced Aircraft Services","place_id":"ChIJy1Vbd9v_24AR2lAbMdzha6A","rating":4.7,"reference":null,"reviews":[{"author_name":"Mortimer Franks","author_url":"https://www.google.com/maps/contrib/112294885156048244620/reviews","language":"en","profile_photo_url":"https://lh3.googleusercontent.com/a/AATXAJxc5AXLyLZB4-qafR1PwVmZqGGhlR0d9R1ICrWh=s128-c0x00000000-cc-rp-mo","rating":5,"relative_time_description":"3 years ago","text":"Great service. Great people","time":1534220550},{"author_name":"Brandon","author_url":"https://www.google.com/maps/contrib/113015094275126792831/reviews","language":null,"profile_photo_url":"https://lh3.googleusercontent.com/a-/AOh14GiT2Z7iDE4IaTA9GdXd_9hV6pw6H9lS1Q8NxMU0mAA=s128-c0x00000000-cc-rp-mo","rating":4,"relative_time_description":"7 years ago","text":"","time":1392950481},{"author_name":"Mike Haley","author_url":"https://www.google.com/maps/contrib/115048405621060827823/reviews","language":null,"profile_photo_url":"https://lh3.googleusercontent.com/a-/AOh14GhzqdYY9rGvQhvJmsJmuptw2kdcvXy_RGdp_Gvx=s128-c0x00000000-cc-rp-mo-ba3","rating":5,"relative_time_description":"4 years ago","text":"","time":1505509084}],"types":["university","point_of_interest","establishment"],"url":"https://maps.google.com/?cid=11559581204409438426","utc_offset":-480,"vicinity":"8622 Gibbs Drive, San Diego","website":"https://advaircraft.com/"},"status":"OK"} | AM39: <span class="street-address">8622 Gibbs Dr</span>, <span class="locality">San Diego</span>, <span class="region">CA</span> <span class="postal-code">92123-1729</span>, <span class="country-name">USA</span> | AN39: (858) 560-7599 | AO39: https://maps.gstatic.com/mapfiles/place_api/icons/v1/png_71/school-71.png | AQ39: +1 858-560-7599 | AR39: university,point_of_interest,establishment | AS39: -480 | AT39: 8622 Gibbs Drive, San Diego | AU39: https://advaircraft.com/ | AV39: 4.7 | AW39: 3
A40: Advanced Aviation Maintenance | E40: 4113 Quando Dr | G40: Belle Isle | H40: FL | I40: 32812-2848 | J40: US | K40: (407) 857-7377 | M40: MCO | Y40: https://maps.google.com/?cid=16881486354508369057 | AB40: Advanced Aviation Maintenance | AC40: OPERATIONAL | AD40: ChIJFfNx4Etj54gRoUwTwWUWR-o | AE40: 4113 Quando Dr, Belle Isle, FL 32812, USA | AJ40: 28.471018 | AK40: -81.33455 | AL40: {"html_attributions":[],"result":{"address_components":[{"long_name":"4113","short_name":"4113","types":["street_number"]},{"long_name":"Quando Drive","short_name":"Quando Dr","types":["route"]},{"long_name":"Belle Isle","short_name":"Belle Isle","types":["locality","political"]},{"long_name":"Orange County","short_name":"Orange County","types":["administrative_area_level_2","political"]},{"long_name":"Florida","short_name":"FL","types":["administrative_area_level_1","political"]},{"long_name":"United States","short_name":"US","types":["country","political"]},{"long_name":"32812","short_name":"32812","types":["postal_code"]},{"long_name":"2848","short_name":"2848","types":["postal_code_suffix"]}],"adr_address":"<span class=\"street-address\">4113 Quando Dr</span>, <span class=\"locality\">Belle Isle</span>, <span class=\"region\">FL</span> <span class=\"postal-code\">32812-2848</span>, <span class=\"country-name\">USA</span>","formatted_address":"4113 Quando Dr, Belle Isle, FL 32812, USA","formatted_phone_number":"(407) 857-7377","geometry":{"location":{"lat":28.471018,"lng":-81.3345499},"viewport":{"northeast":{"lat":28.4722381802915,"lng":-81.33320011970848},"southwest":{"lat":28.4695402197085,"lng":-81.33589808029149}}},"icon":"https://maps.gstatic.com/mapfiles/place_api/icons/v1/png_71/generic_business-71.png","id":null,"international_phone_number":"+1 407-857-7377","name":"Advanced Aviation Maintenance","place_id":"ChIJFfNx4Etj54gRoUwTwWUWR-o","rating":null,"reference":null,"reviews":null,"types":["general_contractor","point_of_interest","establishment"],"url":"https://maps.google.com/?cid=16881486354508369057","utc_offset":-300,"vicinity":"4113 Quando Drive, Belle Isle","website":null},"status":"OK"} | AM40: <span class="street-address">4113 Quando Dr</span>, <span class="locality">Belle Isle</span>, <span class="region">FL</span> <span class="postal-code">32812-2848</span>, <span class="country-name">USA</span> | AN40: (407) 857-7377 | AO40: https://maps.gstatic.com/mapfiles/place_api/icons/v1/png_71/generic_business-71.png | AQ40: +1 407-857-7377 | AR40: general_contractor,point_of_interest,establishment | AS40: -300 | AT40: 4113 Quando Drive, Belle Isle
A41: Advanced Composite Structures | E41: 2111 Spinner Ln | G41: Sanford | H41: FL | I41: 32773-6814 | J41: US | K41: (407) 585-6111 | L41: http://www.acs-composites.com/ | M41: SFB | N41: P145 | Y41: https://maps.google.com/?cid=10668218436911838698 | AB41: Advanced Composite Structures | AC41: OPERATIONAL | AD41: ChIJG66aS8kU54gR6jVnTiUgDZQ | AE41: 2111 Spinner Ln, Sanford, FL 32773, USA | AJ41: 28.767172 | AK41: -81.223267 | AL41: {"html_attributions":[],"result":{"address_components":[{"long_name":"2111","short_name":"2111","types":["street_number"]},{"long_name":"Spinner Lane","short_name":"Spinner Ln","types":["route"]},{"long_name":"Sanford","short_name":"Sanford","types":["locality","political"]},{"long_name":"Seminole County","short_name":"Seminole County","types":["administrative_area_level_2","political"]},{"long_name":"Florida","short_name":"FL","types":["administrative_area_level_1","political"]},{"long_name":"United States","short_name":"US","types":["country","political"]},{"long_name":"32773","short_name":"32773","types":["postal_code"]},{"long_name":"6814","short_name":"6814","types":["postal_code_suffix"]}],"adr_address":"<span class=\"street-address\">2111 Spinner Ln</span>, <span class=\"locality\">Sanford</span>, <span class=\"region\">FL</span> <span class=\"postal-code\">32773-6814</span>, <span class=\"country-name\">USA</span>","formatted_address":"2111 Spinner Ln, Sanford, FL 32773, USA","formatted_phone_number":"(407) 585-6111","geometry":{"location":{"lat":28.7671718,"lng":-81.2232666},"viewport":{"northeast":{"lat":28.7686555802915,"lng":-81.2219162697085},"southwest":{"lat":28.7659576197085,"lng":-81.22461423029151}}},"icon":"https://maps.gstatic.com/mapfiles/place_api/icons/v1/png_71/generic_business-71.png","id":null,"international_phone_number":"+1 407-585-6111","name":"Advanced Composite Structures","place_id":"ChIJG66aS8kU54gR6jVnTiUgDZQ","rating":4.9,"reference":null,"reviews":[{"author_name":"osmar salguero","author_url":"https://www.google.com/maps/contrib/110500786440929922385/reviews","language":"en","profile_photo_url":"https://lh3.googleusercontent.com/a-/AOh14GiV-J-xiIbbSMRvzQ5fpfmZj4oQvCo6T5GqsQZz=s128-c0x00000000-cc-rp-mo-ba5","rating":4,"relative_time_description":"7 months ago","text":"Good job","time":1623260614},{"author_name":"Maid Solutions","author_url":"https://www.google.com/maps/contrib/101107859456053190881/reviews","language":"en","profile_photo_url":"https://lh3.googleusercontent.com/a/AATXAJzGY3rSRv5D1rPGxnHjHvVVCKk-iaK4QXHvu0nr=s128-c0x00000000-cc-rp-mo-ba3","rating":5,"relative_time_description":"a year ago","text":"The owner is great man","time":1592653734},{"author_name":"Robert LeFebvre","author_url":"https://www.google.com/maps/contrib/106727272728628470652/reviews","language":null,"profile_photo_url":"https://lh3.googleusercontent.com/a/AATXAJzgwAFM5CzXABZ-aNsYylDohAJPHYuDFZRYXGxz=s128-c0x00000000-cc-rp-mo-ba4","rating":5,"relative_time_description":"9 months ago","text":"","time":1617655933},{"author_name":"David From Down Under","author_url":"https://www.google.com/maps/contrib/105902456583078872678/reviews","language":null,"profile_photo_url":"https://lh3.googleusercontent.com/a/AATXAJzf2H226D1e9HxCles1-HbxRFgj41r7vKeGBRmZ=s128-c0x00000000-cc-rp-mo","rating":5,"relative_time_description":"a year ago","text":"","time":1592700959},{"author_name":"James Scott","author_url":"https://www.google.com/maps/contrib/108651941704420125345/reviews","language":null,"profile_photo_url":"https://lh3.googleusercontent.com/a/AATXAJy9YqA8U-Pi8dDnMa2mGjv60J56LfTRtCEci0MC=s128-c0x00000000-cc-rp-mo","rating":5,"relative_time_description":"2 years ago","text":"","time":1551193561}],"types":["point_of_interest","establishment"],"url":"https://maps.google.com/?cid=10668218436911838698","utc_offset":-300,"vicinity":"2111 Spinner Lane, Sanford","website":"http://www.acs-composites.com/"},"status":"OK"} | AM41: <span class="street-address">2111 Spinner Ln</span>, <span class="locality">Sanford</span>, <span class="region">FL</span> <span class="postal-code">32773-6814</span>, <span class="country-name">USA</span> | AN41: (407) 585-6111 | AO41: https://maps.gstatic.com/mapfiles/place_api/icons/v1/png_71/generic_business-71.png | AQ41: +1 407-585-6111 | AR41: point_of_interest,establishment | AS41: -300 | AT41: 2111 Spinner Lane, Sanford | AU41: http://www.acs-composites.com/ | AV41: 4.9 | AW41: 5
A42: Advantage Air Charter Inc | E42: 477 Sandau Rd | F42: # H | G42: San Antonio | H42: TX | I42: 78216-3644 | J42: US | K42: (210) 342-3860 | M42: SAT | N42: P135 | Y42: https://maps.google.com/?cid=11014180088136931753 | AB42: Advantage Air Charter Inc | AC42: OPERATIONAL | AD42: ChIJhSsjbR9gXIYRqRmVPW862pg | AE42: 477 Sandau Rd # H, San Antonio, TX 78216, USA | AJ42: 29.538854 | AK42: -98.486813 | AL42: {"html_attributions":[],"result":{"address_components":[{"long_name":"# H","short_name":"# H","types":["subpremise"]},{"long_name":"477","short_name":"477","types":["street_number"]},{"long_name":"Sandau Road","short_name":"Sandau Rd","types":["route"]},{"long_name":"Uptown","short_name":"Uptown","types":["neighborhood","political"]},{"long_name":"San Antonio","short_name":"San Antonio","types":["locality","political"]},{"long_name":"Bexar County","short_name":"Bexar County","types":["administrative_area_level_2","political"]},{"long_name":"Texas","short_name":"TX","types":["administrative_area_level_1","political"]},{"long_name":"United States","short_name":"US","types":["country","political"]},{"long_name":"78216","short_name":"78216","types":["postal_code"]},{"long_name":"3644","short_name":"3644","types":["postal_code_suffix"]}],"adr_address":"<span class=\"street-address\">477 Sandau Rd # H</span>, <span class=\"locality\">San Antonio</span>, <span class=\"region\">TX</span> <span class=\"postal-code\">78216-3644</span>, <span class=\"country-name\">USA</span>","formatted_address":"477 Sandau Rd # H, San Antonio, TX 78216, USA","formatted_phone_number":"(210) 342-3860","geometry":{"location":{"lat":29.5388539,"lng":-98.4868126},"viewport":{"northeast":{"lat":29.5401013302915,"lng":-98.48556811970849},"southwest":{"lat":29.5374033697085,"lng":-98.4882660802915}}},"icon":"https://maps.gstatic.com/mapfiles/place_api/icons/v1/png_71/generic_business-71.png","id":null,"international_phone_number":"+1 210-342-3860","name":"Advantage Air Charter Inc","place_id":"ChIJhSsjbR9gXIYRqRmVPW862pg","rating":null,"reference":null,"reviews":null,"types":["point_of_interest","establishment"],"url":"https://maps.google.com/?cid=11014180088136931753","utc_offset":-360,"vicinity":"477 Sandau Road # H, San Antonio","website":null},"status":"OK"} | AM42: <span class="street-address">477 Sandau Rd # H</span>, <span class="locality">San Antonio</span>, <span class="region">TX</span> <span class="postal-code">78216-3644</span>, <span class="country-name">USA</span> | AN42: (210) 342-3860 | AO42: https://maps.gstatic.com/mapfiles/place_api/icons/v1/png_71/generic_business-71.png | AQ42: +1 210-342-3860 | AR42: point_of_interest,establishment | AS42: -360 | AT42: 477 Sandau Road # H, San Antonio
A43: Adventure Wings Aviation LLC | E43: 724 Cedar St | G43: Pacific Grove | H43: CA | I43: 93950-3912 | J43: US | K43: (831) 383-8620 | L43: https://www.iac.org/flight-school/adventure-wings-aviation | M43: MRY | N43: FLT61 | Y43: https://maps.google.com/?cid=8131155837402519689 | AB43: Adventure Wings Aviation LLC | AC43: OPERATIONAL | AD43: ChIJoTEk0DXhjYARiZi4RSer13A | AE43: 724 Cedar St, Pacific Grove, CA 93950, USA | AJ43: 36.617175 | AK43: -121.92689 | AL43: {"html_attributions":[],"result":{"address_components":[{"long_name":"724","short_name":"724","types":["street_number"]},{"long_name":"Cedar Street","short_name":"Cedar St","types":["route"]},{"long_name":"Pacific Grove","short_name":"Pacific Grove","types":["locality","political"]},{"long_name":"Monterey County","short_name":"Monterey County","types":["administrative_area_level_2","political"]},{"long_name":"California","short_name":"CA","types":["administrative_area_level_1","political"]},{"long_name":"United States","short_name":"US","types":["country","political"]},{"long_name":"93950","short_name":"93950","types":["postal_code"]},{"long_name":"3912","short_name":"3912","types":["postal_code_suffix"]}],"adr_address":"<span class=\"street-address\">724 Cedar St</span>, <span class=\"locality\">Pacific Grove</span>, <span class=\"region\">CA</span> <span class=\"postal-code\">93950-3912</span>, <span class=\"country-name\">USA</span>","formatted_address":"724 Cedar St, Pacific Grove, CA 93950, USA","formatted_phone_number":"(831) 383-8620","geometry":{"location":{"lat":36.617175,"lng":-121.9268891},"viewport":{"northeast":{"lat":36.6184914302915,"lng":-121.9254209697085},"southwest":{"lat":36.6157934697085,"lng":-121.9281189302915}}},"icon":"https://maps.gstatic.com/mapfiles/place_api/icons/v1/png_71/school-71.png","id":null,"international_phone_number":"+1 831-383-8620","name":"Adventure Wings Aviation LLC","place_id":"ChIJoTEk0DXhjYARiZi4RSer13A","rating":null,"reference":null,"reviews":null,"types":["point_of_interest","establishment"],"url":"https://maps.google.com/?cid=8131155837402519689","utc_offset":-480,"vicinity":"724 Cedar Street, Pacific Grove","website":"https://www.iac.org/flight-school/adventure-wings-aviation"},"status":"OK"} | AM43: <span class="street-address">724 Cedar St</span>, <span class="locality">Pacific Grove</span>, <span class="region">CA</span> <span class="postal-code">93950-3912</span>, <span class="country-name">USA</span> | AN43: (831) 383-8620 | AO43: https://maps.gstatic.com/mapfiles/place_api/icons/v1/png_71/school-71.png | AQ43: +1 831-383-8620 | AR43: point_of_interest,establishment | AS43: -480 | AT43: 724 Cedar Street, Pacific Grove | AU43: https://www.iac.org/flight-school/adventure-wings-aviation
A44: Adyson Aviation Group | E44: 1704 Maxwell Dr | G44: Wall Township | H44: NJ | I44: 07719 | J44: US | K44: (848) 220-9370 | L44: https://adysonaviationgroup.com/ | M44: BLM | N44: DEAL | O44: CNSL | Y44: https://maps.google.com/?cid=3317392570458540121 | AB44: Adyson Aviation Group | AC44: OPERATIONAL | AD44: ChIJZ3b_U9spwokRWYizbve-CS4 | AE44: 1704 Maxwell Dr, Wall Township, NJ 07719, USA | AJ44: 40.172307 | AK44: -74.061067 | AL44: {"html_attributions":[],"result":{"address_components":[{"long_name":"1704","short_name":"1704","types":["street_number"]},{"long_name":"Maxwell Drive","short_name":"Maxwell Dr","types":["route"]},{"long_name":"Wall Township","short_name":"Wall Township","types":["locality","political"]},{"long_name":"Monmouth County","short_name":"Monmouth County","types":["administrative_area_level_2","political"]},{"long_name":"New Jersey","short_name":"NJ","types":["administrative_area_level_1","political"]},{"long_name":"United States","short_name":"US","types":["country","political"]},{"long_name":"07719","short_name":"07719","types":["postal_code"]}],"adr_address":"<span class=\"street-address\">1704 Maxwell Dr</span>, <span class=\"locality\">Wall Township</span>, <span class=\"region\">NJ</span> <span class=\"postal-code\">07719</span>, <span class=\"country-name\">USA</span>","formatted_address":"1704 Maxwell Dr, Wall Township, NJ 07719, USA","formatted_phone_number":"(848) 220-9370","geometry":{"location":{"lat":40.1723074,"lng":-74.06106679999999},"viewport":{"northeast":{"lat":40.1736610802915,"lng":-74.0596342697085},"southwest":{"lat":40.1709631197085,"lng":-74.0623322302915}}},"icon":"https://maps.gstatic.com/mapfiles/place_api/icons/v1/png_71/generic_business-71.png","id":null,"international_phone_number":"+1 848-220-9370","name":"Adyson Aviation Group","place_id":"ChIJZ3b_U9spwokRWYizbve-CS4","rating":5.0,"reference":null,"reviews":[{"author_name":"BJ Duncsak","author_url":"https://www.google.com/maps/contrib/114254280271558122275/reviews","language":"en","profile_photo_url":"https://lh3.googleusercontent.com/a/AATXAJzg4JbeD3JOiO8ZO02Z0iCMOLtORZ5iMr50bgVU=s128-c0x00000000-cc-rp-mo","rating":5,"relative_time_description":"a year ago","text":"Dan Dunn and his corporation are first class ... I fully recommend him and his company to anyone I know and network with ... His knowledge and his focus is amazing and love to do business with him anytime... love his experience and back ground to pretty much get any deal done . Very impressed with everything he does . Thank you for providing a great business decision I had ever made ... also great family man also and truly could say he tears everyone as family and I would say I consider himself a friend. Dan get thing handled in a timely manner ... I wish him great success in his new adventure... John Duncsak","time":1582143713}],"types":["point_of_interest","establishment"],"url":"https://maps.google.com/?cid=3317392570458540121","utc_offset":-300,"vicinity":"1704 Maxwell Drive, Wall Township","website":"https://adysonaviationgroup.com/"},"status":"OK"} | AM44: <span class="street-address">1704 Maxwell Dr</span>, <span class="locality">Wall Township</span>, <span class="region">NJ</span> <span class="postal-code">07719</span>, <span class="country-name">USA</span> | AN44: (848) 220-9370 | AO44: https://maps.gstatic.com/mapfiles/place_api/icons/v1/png_71/generic_business-71.png | AQ44: +1 848-220-9370 | AR44: point_of_interest,establishment | AS44: -300 | AT44: 1704 Maxwell Drive, Wall Township | AU44: https://adysonaviationgroup.com/ | AV44: 5 | AW44: 1
A45: Aerial Avionics | E45: 120 Olmsted Way | G45: Monterey | H45: CA | I45: 93940 | J45: US | K45: (831) 324-8305 | L45: http://www.aerialavionics.com/ | M45: MRY | N45: P145 | O45: AFLIM | Y45: https://maps.google.com/?cid=7345194719278279243 | AB45: Aerial Avionics | AC45: OPERATIONAL | AD45: ChIJAQAAAK0yjoARSyqoQK5f72U | AE45: 120 Olmsted Way, Monterey, CA 93940, USA | AJ45: 36.585245 | AK45: -121.84526 | AL45: {"html_attributions":[],"result":{"address_components":[{"long_name":"120","short_name":"120","types":["street_number"]},{"long_name":"Olmsted Way","short_name":"Olmsted Way","types":["route"]},{"long_name":"Monterey","short_name":"Monterey","types":["locality","political"]},{"long_name":"Monterey County","short_name":"Monterey County","types":["administrative_area_level_2","political"]},{"long_name":"California","short_name":"CA","types":["administrative_area_level_1","political"]},{"long_name":"United States","short_name":"US","types":["country","political"]},{"long_name":"93940","short_name":"93940","types":["postal_code"]}],"adr_address":"<span class=\"street-address\">120 Olmsted Way</span>, <span class=\"locality\">Monterey</span>, <span class=\"region\">CA</span> <span class=\"postal-code\">93940</span>, <span class=\"country-name\">USA</span>","formatted_address":"120 Olmsted Way, Monterey, CA 93940, USA","formatted_phone_number":"(831) 324-8305","geometry":{"location":{"lat":36.5852451,"lng":-121.8452577},"viewport":{"northeast":{"lat":36.5863877802915,"lng":-121.8443081197085},"southwest":{"lat":36.5836898197085,"lng":-121.8470060802915}}},"icon":"https://maps.gstatic.com/mapfiles/place_api/icons/v1/png_71/generic_business-71.png","id":null,"international_phone_number":"+1 831-324-8305","name":"Aerial Avionics","place_id":"ChIJAQAAAK0yjoARSyqoQK5f72U","rating":5.0,"reference":null,"reviews":[{"author_name":"Danny Mitchell","author_url":"https://www.google.com/maps/contrib/113014278087407929560/reviews","language":null,"profile_photo_url":"https://lh3.googleusercontent.com/a/AATXAJyZDwa4a_Kxk-YzKu8kCq9fsQfrG9gZZZZMmVFLjQ=s128-c0x00000000-cc-rp-mo","rating":5,"relative_time_description":"a year ago","text":"","time":1588802619}],"types":["point_of_interest","store","establishment"],"url":"https://maps.google.com/?cid=7345194719278279243","utc_offset":-480,"vicinity":"120 Olmsted Way, Monterey","website":"http://www.aerialavionics.com/"},"status":"OK"} | AM45: <span class="street-address">120 Olmsted Way</span>, <span class="locality">Monterey</span>, <span class="region">CA</span> <span class="postal-code">93940</span>, <span class="country-name">USA</span> | AN45: (831) 324-8305 | AO45: https://maps.gstatic.com/mapfiles/place_api/icons/v1/png_71/generic_business-71.png | AQ45: +1 831-324-8305 | AR45: point_of_interest,store,establishment | AS45: -480 | AT45: 120 Olmsted Way, Monterey | AU45: http://www.aerialavionics.com/ | AV45: 5 | AW45: 1
A46: Aerlex | E46: 11900 W Olympic Blvd | F46: #450 | G46: Los Angeles | H46: CA | I46: 90064-1171 | J46: US | K46: (310) 392-5200 | L46: http://www.aerlex.com/ | M46: LAX | N46: AVLAW | Y46: https://maps.google.com/?cid=1317988686845991454 | AB46: Aerlex Law Group | AD46: ChIJ4c6epB27woARHlpwSbpvShI | AE46: 11900 W Olympic Blvd #450, Los Angeles, CA 90064, USA | AJ46: 34.032317 | AK46: -118.45244 | AL46: {"html_attributions":[],"result":{"address_components":[{"long_name":"#450","short_name":"#450","types":["subpremise"]},{"long_name":"11900","short_name":"11900","types":["street_number"]},{"long_name":"West Olympic Boulevard","short_name":"W Olympic Blvd","types":["route"]},{"long_name":"West Los Angeles","short_name":"West Los Angeles","types":["neighborhood","political"]},{"long_name":"Los Angeles","short_name":"Los Angeles","types":["locality","political"]},{"long_name":"Los Angeles County","short_name":"Los Angeles County","types":["administrative_area_level_2","political"]},{"long_name":"California","short_name":"CA","types":["administrative_area_level_1","political"]},{"long_name":"United States","short_name":"US","types":["country","political"]},{"long_name":"90064","short_name":"90064","types":["postal_code"]},{"long_name":"1171","short_name":"1171","types":["postal_code_suffix"]}],"adr_address":"<span class=\"street-address\">11900 W Olympic Blvd #450</span>, <span class=\"locality\">Los Angeles</span>, <span class=\"region\">CA</span> <span class=\"postal-code\">90064-1171</span>, <span class=\"country-name\">USA</span>","formatted_address":"11900 W Olympic Blvd #450, Los Angeles, CA 90064, USA","formatted_phone_number":"(310) 392-5200","geometry":{"location":{"lat":34.0323175,"lng":-118.4524404},"viewport":{"northeast":{"lat":34.0336979302915,"lng":-118.4512022197085},"southwest":{"lat":34.0309999697085,"lng":-118.4539001802915}}},"icon":"https://maps.gstatic.com/mapfiles/place_api/icons/v1/png_71/generic_business-71.png","id":null,"international_phone_number":"+1 310-392-5200","name":"Aerlex Law Group","place_id":"ChIJ4c6epB27woARHlpwSbpvShI","rating":null,"reference":null,"reviews":null,"types":["lawyer","accounting","finance","point_of_interest","establishment"],"url":"https://maps.google.com/?cid=1317988686845991454","utc_offset":-480,"vicinity":"11900 West Olympic Boulevard #450, Los Angeles","website":"http://www.aerlex.com/"},"status":"OK"} | AM46: <span class="street-address">11900 W Olympic Blvd #450</span>, <span class="locality">Los Angeles</span>, <span class="region">CA</span> <span class="postal-code">90064-1171</span>, <span class="country-name">USA</span> | AN46: (310) 392-5200 | AO46: https://maps.gstatic.com/mapfiles/place_api/icons/v1/png_71/generic_business-71.png | AQ46: +1 310-392-5200 | AR46: lawyer,accounting,finance,point_of_interest,establishment | AS46: -480 | AT46: 11900 West Olympic Boulevard #450, Los Angeles | AU46: http://www.aerlex.com/
A47: Aero Alliance Insurance Services, Inc | E47: 2000 Airport Rd | F47: 101a | G47: Chamblee | H47: GA | I47: 30341 | J47: US | K47: (770) 262-7042 | L47: http://aero-alliance.com/ | M47: PDK | N47: INSR | Y47: https://maps.google.com/?cid=4898055159924026312 | AB47: Aero Alliance Insurance Services, Inc | AC47: OPERATIONAL | AD47: ChIJpS60CuyBt4cRyGuKiTdj-UM | AE47: 2000 Airport Rd #101a, Chamblee, GA 30341, USA | AJ47: 33.877789 | AK47: -84.304871 | AL47: {"html_attributions":[],"result":{"address_components":[{"long_name":"101a","short_name":"101a","types":["subpremise"]},{"long_name":"2000","short_name":"2000","types":["street_number"]},{"long_name":"Airport Road","short_name":"Airport Rd","types":["route"]},{"long_name":"Chamblee","short_name":"Chamblee","types":["locality","political"]},{"long_name":"DeKalb County","short_name":"Dekalb County","types":["administrative_area_level_2","political"]},{"long_name":"Georgia","short_name":"GA","types":["administrative_area_level_1","political"]},{"long_name":"United States","short_name":"US","types":["country","political"]},{"long_name":"30341","short_name":"30341","types":["postal_code"]}],"adr_address":"<span class=\"street-address\">2000 Airport Rd #101a</span>, <span class=\"locality\">Chamblee</span>, <span class=\"region\">GA</span> <span class=\"postal-code\">30341</span>, <span class=\"country-name\">USA</span>","formatted_address":"2000 Airport Rd #101a, Chamblee, GA 30341, USA","formatted_phone_number":"(770) 262-7042","geometry":{"location":{"lat":33.8777895,"lng":-84.30487099999999},"viewport":{"northeast":{"lat":33.8793282302915,"lng":-84.30357281970848},"southwest":{"lat":33.8766302697085,"lng":-84.3062707802915}}},"icon":"https://maps.gstatic.com/mapfiles/place_api/icons/v1/png_71/generic_business-71.png","id":null,"international_phone_number":"+1 770-262-7042","name":"Aero Alliance Insurance Services, Inc","place_id":"ChIJpS60CuyBt4cRyGuKiTdj-UM","rating":null,"reference":null,"reviews":null,"types":["insurance_agency","point_of_interest","establishment"],"url":"https://maps.google.com/?cid=4898055159924026312","utc_offset":-300,"vicinity":"2000 Airport Road #101a, Chamblee","website":"http://aero-alliance.com/"},"status":"OK"} | AM47: <span class="street-address">2000 Airport Rd #101a</span>, <span class="locality">Chamblee</span>, <span class="region">GA</span> <span class="postal-code">30341</span>, <span class="country-name">USA</span> | AN47: (770) 262-7042 | AO47: https://maps.gstatic.com/mapfiles/place_api/icons/v1/png_71/generic_business-71.png | AQ47: +1 770-262-7042 | AR47: insurance_agency,point_of_interest,establishment | AS47: -300 | AT47: 2000 Airport Road #101a, Chamblee | AU47: http://aero-alliance.com/
A48: Aero Atlanta Flight Center | E48: 1954 Airport Rd | F48: 66 | G48: Atlanta | H48: GA | I48: 30341 | J48: US | K48: (770) 422-2376 | L48: http://aeroatlanta.com/ | M48: PDK | N48: FLT61 | Y48: https://maps.google.com/?cid=1584433625254133957 | AB48: Aero Atlanta Flight Center | AC48: OPERATIONAL | AD48: ChIJ348r3lkI9YgRxQB1y_wJ_RU | AE48: 1954 Airport Rd #66, Atlanta, GA 30341, USA | AJ48: 33.877061 | AK48: -84.307993 | AL48: {"html_attributions":[],"result":{"address_components":[{"long_name":"66","short_name":"66","types":["subpremise"]},{"long_name":"1954","short_name":"1954","types":["street_number"]},{"long_name":"Airport Road","short_name":"Airport Rd","types":["route"]},{"long_name":"Atlanta","short_name":"Atlanta","types":["locality","political"]},{"long_name":"DeKalb County","short_name":"Dekalb County","types":["administrative_area_level_2","political"]},{"long_name":"Georgia","short_name":"GA","types":["administrative_area_level_1","political"]},{"long_name":"United States","short_name":"US","types":["country","political"]},{"long_name":"30341","short_name":"30341","types":["postal_code"]}],"adr_address":"<span class=\"street-address\">1954 Airport Rd #66</span>, <span class=\"locality\">Atlanta</span>, <span class=\"region\">GA</span> <span class=\"postal-code\">30341</span>, <span class=\"country-name\">USA</span>","formatted_address":"1954 Airport Rd #66, Atlanta, GA 30341, USA","formatted_phone_number":"(770) 422-2376","geometry":{"location":{"lat":33.877061,"lng":-84.307993},"viewport":{"northeast":{"lat":33.8783308302915,"lng":-84.3066440197085},"southwest":{"lat":33.8756328697085,"lng":-84.3093419802915}}},"icon":"https://maps.gstatic.com/mapfiles/place_api/icons/v1/png_71/school-71.png","id":null,"international_phone_number":"+1 770-422-2376","name":"Aero Atlanta Flight Center","place_id":"ChIJ348r3lkI9YgRxQB1y_wJ_RU","rating":5.0,"reference":null,"reviews":[{"author_name":"Nick Kerr","author_url":"https://www.google.com/maps/contrib/116523820900305766264/reviews","language":"en","profile_photo_url":"https://lh3.googleusercontent.com/a-/AOh14GhHul9MUovSH6Ko0ZDaFffmn3o2f41EUWPq2xj0=s128-c0x00000000-cc-rp-mo","rating":5,"relative_time_description":"3 weeks ago","text":"My experience since I started flying here back in July 21 has been nothing but amazing. The personnel are very friendly the facility is always kept clean and my instructor Aaron got me from knowing nothing about aviation to flying planes relatively quickly. Great school, definitely worth checking out!","time":1639778525},{"author_name":"Matthew Garner","author_url":"https://www.google.com/maps/contrib/107011918904946942641/reviews","language":"en","profile_photo_url":"https://lh3.googleusercontent.com/a/AATXAJw9Oe22oX-4koXjY7aeSC5K2dFUrZpR0pP_7Th2=s128-c0x00000000-cc-rp-mo-ba2","rating":5,"relative_time_description":"a year ago","text":"Great flight school! The instructors are very skilled and helped me pass my check ride on the first try! Love renting from here. The planes are always in amazing condition!","time":1610061849},{"author_name":"Scott Morrow","author_url":"https://www.google.com/maps/contrib/110078597095048199546/reviews","language":"en","profile_photo_url":"https://lh3.googleusercontent.com/a/AATXAJx2ZvSsexogZ1pZPS7dPFuAqCzHIegy22RtsqLK=s128-c0x00000000-cc-rp-mo","rating":5,"relative_time_description":"a year ago","text":"What I Iike best about Areo Atlanta is their culture. All of the employees from top to bottom seem very happy to be a part of the organization and they are all very professional.\nIt is clear that they all enjoy what they do and have a passion for flying.\n\nThe flight instructors are all very knowledgeable and are willing to help in every step of your aviation endeavor.\n\nAreo has a large fleet planes and fly out of both Pdk and Kennesaw. Their fleet is well maintained and on the newer side.\n\nI had very little flying experience when I started my private pilot training with Areo. My instructor was very patient but definitely pushed me along when needed. He was with me at every step of the process and I successfully secured my private pilots license. There was absolutely no way I would have completed my training if not for Areo and my instructor. Thank you Antoine you did a great job!!!","time":1603333902},{"author_name":"Clemmie Mathis","author_url":"https://www.google.com/maps/contrib/112770805802221834720/reviews","language":"en","profile_photo_url":"https://lh3.googleusercontent.com/a-/AOh14GjoJYBVYywgUHN9W-abc4WW9Ke1QdoEr7HJLU9m2A=s128-c0x00000000-cc-rp-mo","rating":5,"relative_time_description":"7 years ago","text":"I relocated to Atlanta and was looking for a place to rent a nice plane and get periodic training. Aero has new and nearly new Cirrus SR22 aircraft, a nice study area a pro shop and excellent instructors. I completed my Cirrus transition course and my instrument proficiency check and have been flying their aircraft every since. The aircraft are meticulously maintained and I have never had one issue. If you want to fly the most modern, well maintained aircraft in Atlanta look no farther.","time":1414718793},{"author_name":"msolo","author_url":"https://www.google.com/maps/contrib/108185821138333582694/reviews","language":"en","profile_photo_url":"https://lh3.googleusercontent.com/a-/AOh14GjVsHruME-SAB1txaUKt0R2vSDQ44Cy9CLw2gj6vA=s128-c0x00000000-cc-rp-mo","rating":5,"relative_time_description":"3 years ago","text":"Great place to train and to shop. Great customer service as well.","time":1536836453}],"types":["university","point_of_interest","establishment"],"url":"https://maps.google.com/?cid=1584433625254133957","utc_offset":-300,"vicinity":"1954 Airport Road #66, Atlanta","website":"http://aeroatlanta.com/"},"status":"OK"} | AM48: <span class="street-address">1954 Airport Rd #66</span>, <span class="locality">Atlanta</span>, <span class="region">GA</span> <span class="postal-code">30341</span>, <span class="country-name">USA</span> | AN48: (770) 422-2376 | AO48: https://maps.gstatic.com/mapfiles/place_api/icons/v1/png_71/school-71.png | AQ48: +1 770-422-2376 | AR48: university,point_of_interest,establishment | AS48: -300 | AT48: 1954 Airport Road #66, Atlanta | AU48: http://aeroatlanta.com/ | AV48: 5 | AW48: 5
A49: Aero Bear Aviation | E49: 81118 Taos Trail | G49: Indio | H49: CA | I49: 92201-5367 | J49: US | K49: (760) 342-3052 | M49: TRM | N49: P147 | Y49: https://maps.google.com/?cid=337962260062396448 | AB49: Aero Bear Aviation | AD49: ChIJU3wsGDT42oARIOCBiuKusAQ | AE49: 81118 Taos Trail, Indio, CA 92201, USA | AJ49: 33.712871 | AK49: -116.24948 | AL49: {"html_attributions":[],"result":{"address_components":[{"long_name":"81118","short_name":"81118","types":["street_number"]},{"long_name":"Taos Trail","short_name":"Taos Trail","types":["route"]},{"long_name":"Indio","short_name":"Indio","types":["locality","political"]},{"long_name":"Riverside County","short_name":"Riverside County","types":["administrative_area_level_2","political"]},{"long_name":"California","short_name":"CA","types":["administrative_area_level_1","political"]},{"long_name":"United States","short_name":"US","types":["country","political"]},{"long_name":"92201","short_name":"92201","types":["postal_code"]},{"long_name":"5367","short_name":"5367","types":["postal_code_suffix"]}],"adr_address":"<span class=\"street-address\">81118 Taos Trail</span>, <span class=\"locality\">Indio</span>, <span class=\"region\">CA</span> <span class=\"postal-code\">92201-5367</span>, <span class=\"country-name\">USA</span>","formatted_address":"81118 Taos Trail, Indio, CA 92201, USA","formatted_phone_number":"(760) 342-3052","geometry":{"location":{"lat":33.712871,"lng":-116.249484},"viewport":{"northeast":{"lat":33.7141340802915,"lng":-116.2481360697085},"southwest":{"lat":33.7114361197085,"lng":-116.2508340302915}}},"icon":"https://maps.gstatic.com/mapfiles/place_api/icons/v1/png_71/school-71.png","id":null,"international_phone_number":"+1 760-342-3052","name":"Aero Bear Aviation","place_id":"ChIJU3wsGDT42oARIOCBiuKusAQ","rating":null,"reference":null,"reviews":null,"types":["point_of_interest","establishment"],"url":"https://maps.google.com/?cid=337962260062396448","utc_offset":-480,"vicinity":"81118 Taos Trail, Indio","website":null},"status":"OK"} | AM49: <span class="street-address">81118 Taos Trail</span>, <span class="locality">Indio</span>, <span class="region">CA</span> <span class="postal-code">92201-5367</span>, <span class="country-name">USA</span> | AN49: (760) 342-3052 | AO49: https://maps.gstatic.com/mapfiles/place_api/icons/v1/png_71/school-71.png | AQ49: +1 760-342-3052 | AR49: point_of_interest,establishment | AS49: -480 | AT49: 81118 Taos Trail, Indio
A50: Aero City Jets | E50: 20511 Skywest Dr | G50: Hayward | H50: CA | I50: 94541-4605 | J50: US | K50: (510) 732-6033 | L50: http://www.aerocityjets.com/ | M50: HWD | N50: FLT61 | O50: RENT | Y50: https://maps.google.com/?cid=2044789605205474042 | AB50: Aero City Jets | AD50: ChIJM6i-l1uRj4AR-vqu6k-NYBw | AE50: 20511 Skywest Dr, Hayward, CA 94541, USA | AJ50: 37.661688 | AK50: -122.11951 | AL50: {"html_attributions":[],"result":{"address_components":[{"long_name":"20511","short_name":"20511","types":["street_number"]},{"long_name":"Skywest Drive","short_name":"Skywest Dr","types":["route"]},{"long_name":"Hayward","short_name":"Hayward","types":["locality","political"]},{"long_name":"Alameda County","short_name":"Alameda County","types":["administrative_area_level_2","political"]},{"long_name":"California","short_name":"CA","types":["administrative_area_level_1","political"]},{"long_name":"United States","short_name":"US","types":["country","political"]},{"long_name":"94541","short_name":"94541","types":["postal_code"]},{"long_name":"4605","short_name":"4605","types":["postal_code_suffix"]}],"adr_address":"<span class=\"street-address\">20511 Skywest Dr</span>, <span class=\"locality\">Hayward</span>, <span class=\"region\">CA</span> <span class=\"postal-code\">94541-4605</span>, <span class=\"country-name\">USA</span>","formatted_address":"20511 Skywest Dr, Hayward, CA 94541, USA","formatted_phone_number":"(510) 732-6033","geometry":{"location":{"lat":37.6616885,"lng":-122.1195122},"viewport":{"northeast":{"lat":37.6633048302915,"lng":-122.1180836697085},"southwest":{"lat":37.6606068697085,"lng":-122.1207816302915}}},"icon":"https://maps.gstatic.com/mapfiles/place_api/icons/v1/png_71/school-71.png","id":null,"international_phone_number":"+1 510-732-6033","name":"Aero City Jets","place_id":"ChIJM6i-l1uRj4AR-vqu6k-NYBw","rating":null,"reference":null,"reviews":null,"types":["university","point_of_interest","establishment"],"url":"https://maps.google.com/?cid=2044789605205474042","utc_offset":-480,"vicinity":"20511 Skywest Drive, Hayward","website":"http://www.aerocityjets.com/"},"status":"OK"} | AM50: <span class="street-address">20511 Skywest Dr</span>, <span class="locality">Hayward</span>, <span class="region">CA</span> <span class="postal-code">94541-4605</span>, <span class="country-name">USA</span> | AN50: (510) 732-6033 | AO50: https://maps.gstatic.com/mapfiles/place_api/icons/v1/png_71/school-71.png | AQ50: +1 510-732-6033 | AR50: university,point_of_interest,establishment | AS50: -480 | AT50: 20511 Skywest Drive, Hayward | AU50: http://www.aerocityjets.com/
A51: Aero Club of New England | E51: 200 Hanscom Dr | G51: Bedford | H51: MA | I51: 01730 | J51: US | K51: (978) 243-0844 | L51: http://www.acone.org/ | M51: BED | N51: CLUB | Y51: https://maps.google.com/?cid=8600241511709506580 | AB51: Aero Club of New England | AC51: OPERATIONAL | AD51: ChIJKWRCzf6b44kRFHwDwBYyWnc | AE51: Box 27, 200 Hanscom Dr, Bedford, MA 01730, USA | AJ51: 42.463147 | AK51: -71.291272 | AL51: {"html_attributions":[],"result":{"address_components":[{"long_name":"Box 27","short_name":"Box 27","types":["post_box"]},{"long_name":"200","short_name":"200","types":["street_number"]},{"long_name":"Hanscom Drive","short_name":"Hanscom Dr","types":["route"]},{"long_name":"Bedford","short_name":"Bedford","types":["locality","political"]},{"long_name":"Middlesex County","short_name":"Middlesex County","types":["administrative_area_level_2","political"]},{"long_name":"Massachusetts","short_name":"MA","types":["administrative_area_level_1","political"]},{"long_name":"United States","short_name":"US","types":["country","political"]},{"long_name":"01730","short_name":"01730","types":["postal_code"]}],"adr_address":"<span class=\"post-office-box\">Box 27</span>, <span class=\"street-address\">200 Hanscom Dr</span>, <span class=\"locality\">Bedford</span>, <span class=\"region\">MA</span> <span class=\"postal-code\">01730</span>, <span class=\"country-name\">USA</span>","formatted_address":"Box 27, 200 Hanscom Dr, Bedford, MA 01730, USA","formatted_phone_number":"(978) 243-0844","geometry":{"location":{"lat":42.4631473,"lng":-71.2912722},"viewport":{"northeast":{"lat":42.4643541302915,"lng":-71.29003371970848},"southwest":{"lat":42.4616561697085,"lng":-71.2927316802915}}},"icon":"https://maps.gstatic.com/mapfiles/place_api/icons/v1/png_71/generic_business-71.png","id":null,"international_phone_number":"+1 978-243-0844","name":"Aero Club of New England","place_id":"ChIJKWRCzf6b44kRFHwDwBYyWnc","rating":null,"reference":null,"reviews":null,"types":["point_of_interest","establishment"],"url":"https://maps.google.com/?cid=8600241511709506580","utc_offset":-300,"vicinity":"200 Hanscom Drive, Bedford","website":"http://www.acone.org/"},"status":"OK"} | AM51: <span class="post-office-box">Box 27</span>, <span class="street-address">200 Hanscom Dr</span>, <span class="locality">Bedford</span>, <span class="region">MA</span> <span class="postal-code">01730</span>, <span class="country-name">USA</span> | AN51: (978) 243-0844 | AO51: https://maps.gstatic.com/mapfiles/place_api/icons/v1/png_71/generic_business-71.png | AQ51: +1 978-243-0844 | AR51: point_of_interest,establishment | AS51: -300 | AT51: 200 Hanscom Drive, Bedford | AU51: http://www.acone.org/
A52: Aero Design & Manufacturing Inc | E52: 3409 E Wood St | G52: Phoenix | H52: AZ | I52: 85040-1822 | J52: US | K52: (602) 437-8080 | L52: http://www.cadenceaerospace.com/ | M52: PHX | N52: PART | Y52: https://maps.google.com/?cid=3881898002888634783 | AB52: Aero Design & Manufacturing Inc | AC52: OPERATIONAL | AD52: ChIJb6JCIawPK4cRn7F5nKpF3zU | AE52: 3409 E Wood St, Phoenix, AZ 85040, USA | AJ52: 33.408592 | AK52: -112.00796 | AL52: {"html_attributions":[],"result":{"address_components":[{"long_name":"3409","short_name":"3409","types":["street_number"]},{"long_name":"East Wood Street","short_name":"E Wood St","types":["route"]},{"long_name":"South Mountain Village","short_name":"South Mountain Village","types":["neighborhood","political"]},{"long_name":"Phoenix","short_name":"Phoenix","types":["locality","political"]},{"long_name":"Maricopa County","short_name":"Maricopa County","types":["administrative_area_level_2","political"]},{"long_name":"Arizona","short_name":"AZ","types":["administrative_area_level_1","political"]},{"long_name":"United States","short_name":"US","types":["country","political"]},{"long_name":"85040","short_name":"85040","types":["postal_code"]},{"long_name":"1822","short_name":"1822","types":["postal_code_suffix"]}],"adr_address":"<span class=\"street-address\">3409 E Wood St</span>, <span class=\"locality\">Phoenix</span>, <span class=\"region\">AZ</span> <span class=\"postal-code\">85040-1822</span>, <span class=\"country-name\">USA</span>","formatted_address":"3409 E Wood St, Phoenix, AZ 85040, USA","formatted_phone_number":"(602) 437-8080","geometry":{"location":{"lat":33.4085916,"lng":-112.0079579},"viewport":{"northeast":{"lat":33.4099490302915,"lng":-112.0067690197085},"southwest":{"lat":33.4072510697085,"lng":-112.0094669802915}}},"icon":"https://maps.gstatic.com/mapfiles/place_api/icons/v1/png_71/generic_business-71.png","id":null,"international_phone_number":"+1 602-437-8080","name":"Aero Design & Manufacturing Inc","place_id":"ChIJb6JCIawPK4cRn7F5nKpF3zU","rating":5.0,"reference":null,"reviews":[{"author_name":"Chris Dowdy","author_url":"https://www.google.com/maps/contrib/107521570392344894828/reviews","language":"en","profile_photo_url":"https://lh3.googleusercontent.com/a-/AOh14GiQoOYFExHkinDx6NcBvoG8bZfRiI2XLlLI5K_mjw=s128-c0x00000000-cc-rp-mo-ba2","rating":5,"relative_time_description":"2 years ago","text":"It's a great place full of great people!","time":1577392483},{"author_name":"Big Mike","author_url":"https://www.google.com/maps/contrib/116922631146744334442/reviews","language":"en","profile_photo_url":"https://lh3.googleusercontent.com/a-/AOh14Gg3rwAhxKBcKAJSWIpuYdQGg7zvs-Tq5e7VHUh2Ng=s128-c0x00000000-cc-rp-mo-ba4","rating":5,"relative_time_description":"2 years ago","text":"Excellent place to work..","time":1575220700},{"author_name":"Will Schuhardt","author_url":"https://www.google.com/maps/contrib/116764230101705492789/reviews","language":"en","profile_photo_url":"https://lh3.googleusercontent.com/a/AATXAJxgmbfHTUtCPMTSMBw-BsL5Ba1GeoGS64ze0Pch=s128-c0x00000000-cc-rp-mo-ba4","rating":5,"relative_time_description":"a year ago","text":"Great leadership","time":1594770887},{"author_name":"Rahul Bodha","author_url":"https://www.google.com/maps/contrib/112290242092105639570/reviews","language":null,"profile_photo_url":"https://lh3.googleusercontent.com/a-/AOh14GiCpgyt8W7vFCWadpZiO8VC3HRq7sx94agDwvwr=s128-c0x00000000-cc-rp-mo-ba3","rating":5,"relative_time_description":"4 years ago","text":"","time":1513419215},{"author_name":"Rick Gunn","author_url":"https://www.google.com/maps/contrib/117536513456555656444/reviews","language":null,"profile_photo_url":"https://lh3.googleusercontent.com/a/AATXAJznnuJClOjmlM7mO0Qd6zkWKmWYXsWEuU-3sKQ6=s128-c0x00000000-cc-rp-mo","rating":5,"relative_time_description":"4 years ago","text":"","time":1511485211}],"types":["point_of_interest","establishment"],"url":"https://maps.google.com/?cid=3881898002888634783","utc_offset":-420,"vicinity":"3409 East Wood Street, Phoenix","website":"http://www.cadenceaerospace.com/"},"status":"OK"} | AM52: <span class="street-address">3409 E Wood St</span>, <span class="locality">Phoenix</span>, <span class="region">AZ</span> <span class="postal-code">85040-1822</span>, <span class="country-name">USA</span> | AN52: (602) 437-8080 | AO52: https://maps.gstatic.com/mapfiles/place_api/icons/v1/png_71/generic_business-71.png | AQ52: +1 602-437-8080 | AR52: point_of_interest,establishment | AS52: -420 | AT52: 3409 East Wood Street, Phoenix | AU52: http://www.cadenceaerospace.com/ | AV52: 5 | AW52: 5
